Workbook
Name Array_ElectricalChargeData: 'Electricity Meters'!$O$3:$AR$202
Name Array_ElectricalCharges: HIDE_ELEC!$B$17:$P$216
Name Array_EmissionChargeData: 'Other Emission Meters'!$K$3:$T$202
Name Array_EmissionCharges: HIDE_EMISSION!$B$3:$F$201
Name Array_MobileChargeData: 'Mobile Fuel Meters'!$R$3:$AA$202
Name Array_MobileCharges: HIDE_MOBILE!$B$16:$F$215
Name Array_OtherEnergyChargeData: 'Other Energy Meters'!$O$3:$X$202
Name Array_OtherEnergyCharges: HIDE_ENERGY!$B$25:$F$224
Name Array_PredictorsLookup: HIDE_PREDICT!$B$15:$P$214
Name Array_StationaryChargeData: 'Stationary Fuel Meters'!$P$3:$AS$202
Name Array_StationaryCharges: HIDE_STATIONARY!$B$37:$P$236
Name Array_WaterChargeData: 'Water Meters'!$M$3:$AF$202
Name Array_WaterCharges: HIDE_WATER!$B$15:$K$214
Name List_ChargeNumbers_Electricial: HIDE_ELEC!$B$15:$P$16
Name List_ChargeNumbers_Emissions: HIDE_EMISSION!$A$1:$F$2
Name List_ChargeNumbers_Mobile: HIDE_MOBILE!$B$14:$F$15
Name List_ChargeNumbers_OtherEnergy: HIDE_ENERGY!$B$23:$F$24
Name List_ChargeNumbers_Stationary: HIDE_STATIONARY!$B$35:$P$36
Name List_ChargeNumbers_Water: HIDE_WATER!$A$13:$K$14
Name List_ElectricityMeters: HIDE_ELEC!$A$17:$A$216
Name List_EmissionMeters: HIDE_EMISSION!$A$3:$A$201
Name List_Facilities: HIDE_FACILITIES!$F$2:$F$101
Name List_MobileFuelMeters: HIDE_MOBILE!$A$16:$A$215
Name List_OtherEnergyMeters: HIDE_ENERGY!$A$25:$A$224
Name List_PredictorFacilities: HIDE_PREDICT!$A$15:$A$214
Name List_PredictorNumbers: HIDE_PREDICT!$B$13:$P$14
Name List_Predictors: 'Predictor Setup'!$B$3:$B$202
Name List_StationaryFuelMeters: HIDE_STATIONARY!$A$37:$A$236
Name List_WaterMeters: HIDE_WATER!$A$15:$A$214
Name NAIC_2: HIDE_FACILITIES!$C$2:$C$21
Name NAIC_3: HIDE_FACILITIES!$D$2:$D$100
Name NAIC_3_11: HIDE_FACILITIES!$D$2:$D$6
Name NAIC_3_21: HIDE_FACILITIES!$D$7:$D$9
Name NAIC_3_22: HIDE_FACILITIES!$D$10
Name NAIC_3_23: HIDE_FACILITIES!$D$11:$D$13
Name NAIC_3_31: HIDE_FACILITIES!$D$14:$D$34
Name NAIC_3_42: HIDE_FACILITIES!$D$35:$D$37
Name NAIC_3_44: HIDE_FACILITIES!$D$38:$D$49
Name NAIC_3_48: HIDE_FACILITIES!$D$50:$D$60
Name NAIC_3_51: HIDE_FACILITIES!$D$61:$D$66
Name NAIC_3_52: HIDE_FACILITIES!$D$67:$D$71
Name NAIC_3_53: HIDE_FACILITIES!$D$72:$D$74
Name NAIC_3_54: HIDE_FACILITIES!$D$75
Name NAIC_3_55: HIDE_FACILITIES!$D$76
Name NAIC_3_56: HIDE_FACILITIES!$D$77:$D$78
Name NAIC_3_61: HIDE_FACILITIES!$D$79:$D$80
Name NAIC_3_62: HIDE_FACILITIES!$D$81:$D$83
Name NAIC_3_71: HIDE_FACILITIES!$D$84:$D$86
Name NAIC_3_72: HIDE_FACILITIES!$D$87:$D$88
Name NAIC_3_81: HIDE_FACILITIES!$D$89:$D$92
Name NAIC_3_92: HIDE_FACILITIES!$D$93:$D$100
Name Option_VehicleType: HIDE_MOBILE!$A$2:$A$12
Name Options_Calendarizing: HIDE_ELEC!$B$2:$B$4
Name Options_Countries: HIDE_FACILITIES!$A$2:$A$250
Name Options_ElecAgreementType: HIDE_ELEC!$A$2:$A$9
Name Options_ElectricityChargeTypes: HIDE_ELEC!$E$2:$E$7
Name Options_FuelsGas: HIDE_STATIONARY!$B$2:$B$10
Name Options_FuelsLiquid: HIDE_STATIONARY!$C$2:$C$32
Name Options_FuelsMaterial: HIDE_MOBILE!$E$2:$E$4
Name Options_FuelsNonRoad: HIDE_MOBILE!$D$2:$D$6

Sheet OVERVIEW
D2: VERIFI - Data Upload Template Version: 3.2 Release: 03/02/2026
B4: This template is for bulk data upload to VERIFI including adding facilities, meters, and data. It can also be used for bulk updating - please just add data to the bottom of each data sheet.
B6: Updates (03/02/2026)
B8: The VERIFI template has been updated to simplify the upload process, reduce troubleshooting needs, and accommodate the wide variety of charges that can occur on utility bills. The latest update simplifies the initially displayed tabs. Please see the below for help on getting started with this new template.
B10: Getting Started
B12: This template can be used for setting up your account or for updating your data every month if you choose to not enter data manually within VERIFI.
B14: > When uploading with this template, you have the choice of replacing existing data if you updated previous readings or only upload new data.
B15: > When entering data in this template, there is no need to sort by meter or read date. VERIFI uses the meter number and date column to parse data appropriately.
B17: This worksheet is password protected to protect formatting and features. If you need to unlock and modify the column widths or other things to better match your needs, the password is "VERIFI". PLEASE DO NOT change any column names as this will break VERIFI's ability to import data from this file.
B19: Input Guide
D21: Cell is not active or not applicable
D22: Cell is free data entry
D23: Cell is a dropdown
D24: Cell is autofilled
D25: Cell is mandatory and is blank (in error)
D26: Cell is suggested but not required and is blank
B28: Facilities
B29: Start here! This is where you will setup and input information about the different facilities in your company.
B31: Data Tabs
B32: By default, the VERIFI template shows Meter and Data tabs for electricity and stationary fuels, plus predictors. If you want to track something beyond these, please right click the tab area and unhide the TWO tabs for each additional trackable group (mobile fuels, other energy, and water)
B33: Electricity: All electricity-based energy streams including grid purchased electricity, on-site generation, and other electricity financial agreements Stationary Fuels: All fuels burned in stationary systems (e.g., natural gas, diesel, coal, propane) Mobile Fuels: All fuels burned in mobile systems, usage estimated via direct consumption or miles driven Other Energy: Other utilities purchased where the energetic transformation occurred over the fence (e.g., steam, compressed air, chilled water) Other: Refrigerant and process losses Water: Water supply and discharge utilities
B35: "---- Meters" Tabs
B36: Each meter type has a its own setup tab. This is where you enter data on the meters you want to track in your facilities. You can group similar meters together using the "Meter Group" column so that you can combine, for example, all your office building electricity meters together for analysis. You can also use the optional cost columns to track different charges on your bills over time.
B38: "----" Tabs
B39: After setting up your meters, each meter type has its own data input tab. These tabs allow you to input utility data from your bills into VERIFI. Each row will correspond to one reading for each of the meters you setup in the meter setup tabs.
B41: Predictors
B42: This tab is where you enter data about any predictors you will use for correlation or regression analysis (e.g., production data, weather data). Predictors are associated with a facility and are not calendarized. Please enter only 1 row of predictor data for each month for each facility.
B44: "HIDE" Tabs
B45: There are many hidden tabs used to make this template work. You may need to unhide these tabs to troubleshoot any errors that may occur in this template.

Sheet Facilities
A1: √ Facility Setup
A2: Facility Name | B2: Address | C2: Country | D2: U.S. State | E2: City | F2: ZIP Code | G2: NAICS Code (2-digit) | H2: NAICS Code (3-digit) | I2: Contact Name | J2: Contact Phone | K2: Contact Email

Sheet HIDE_FACILITIES
A1: Countries | B1: States | C1: 2 Digit NAIC | D1: 3 Digit NAIC | F1: Facilities
A2: United States of America (the) | B2: ALABAMA | C2: 11 - Agriculture | D2: 111 - Crop Production | F2: =IF(Facilities!A3="","",Facilities!A3)
A3: Afghanistan | B3: ALASKA | C3: 21 - Mining | D3: 112 - Animal Production and Aquaculture | F3: =IF(Facilities!A4="",F2,Facilities!A4)
A4: Albania | B4: AMERICAN SAMOA | C4: 22 - Utilities | D4: 113 - Forestry and Logging | F4: =IF(Facilities!A5="",F3,Facilities!A5)
A5: Algeria | B5: ARIZONA | C5: 23 - Construction | D5: 114 - Fishing, Hunting and Trapping | F5: =IF(Facilities!A6="",F4,Facilities!A6)
A6: American Samoa | B6: ARKANSAS | C6: 31 - 33 - Manufacturing | D6: 115 - Support Activities for Agriculture and Forestr | F6: =IF(Facilities!A7="",F5,Facilities!A7)
A7: Andorra | B7: CALIFORNIA | C7: 42 - Wholesale Trade | D7: 211 - Oil and Gas Extraction | F7: =IF(Facilities!A8="",F6,Facilities!A8)
A8: Angola | B8: COLORADO | C8: 44 -45 - Retail Trade | D8: 212 - Mining (except Oil and Gas) | F8: =IF(Facilities!A9="",F7,Facilities!A9)
A9: Anguilla | B9: CONNECTICUT | C9: 48 - 49 - Transportation and Warehousing | D9: 213 - Support Activities for Mining | F9: =IF(Facilities!A10="",F8,Facilities!A10)
A10: Antarctica | B10: DELAWARE | C10: 51 - Information | D10: 221 - Utilities | F10: =IF(Facilities!A11="",F9,Facilities!A11)
A11: Antigua and Barbuda | B11: DISTRICT OF COLUMBIA | C11: 52 - Finance and Insurance | D11: 236 - Construction of Buildings | F11: =IF(Facilities!A12="",F10,Facilities!A12)
A12: Argentina | B12: FEDERATED STATES OF MICRONESIA | C12: 53 - Real Estate and Rental and Leasing | D12: 237 - Heavy and Civil Engineering Construction | F12: =IF(Facilities!A13="",F11,Facilities!A13)
A13: Armenia | B13: FLORIDA | C13: 54 - Professional | D13: 238 - Specialty Trade Contractors | F13: =IF(Facilities!A14="",F12,Facilities!A14)
A14: Aruba | B14: GEORGIA | C14: 55 - Management of Companies and Enterprises | D14: 311 - Food Manufacturing | F14: =IF(Facilities!A15="",F13,Facilities!A15)
... A21: Barbados | B21: KANSAS | C21: 92 - Public Administration | D21: 322 - Paper Manufacturing | F21: =IF(Facilities!A22="",F20,Facilities!A22)
A22: Belarus | B22: KENTUCKY | D22: 323 - Printing and Related Support Activities | F22: =IF(Facilities!A23="",F21,Facilities!A23)
A23: Belgium | B23: LOUISIANA | D23: 324 - Petroleum and Coal Products Manufacturing | F23: =IF(Facilities!A24="",F22,Facilities!A24)
A24: Belize | B24: MAINE | D24: 325 - Chemical Manufacturing | F24: =IF(Facilities!A25="",F23,Facilities!A25)
A25: Benin | B25: MARSHALL ISLANDS | D25: 326 - Plastics and Rubber Products Manufacturing | F25: =IF(Facilities!A26="",F24,Facilities!A26)
A26: Bermuda | B26: MARYLAND | D26: 327 - Nonmetallic Mineral Product Manufacturing | F26: =IF(Facilities!A27="",F25,Facilities!A27)
A27: Bhutan | B27: MASSACHUSETTS | D27: 331 - Primary Metal Manufacturing | F27: =IF(Facilities!A28="",F26,Facilities!A28)
A28: Bolivia (Plurinational State of) | B28: MICHIGAN | D28: 332 - Fabricated Metal Product Manufacturing | F28: =IF(Facilities!A29="",F27,Facilities!A29)
A29: Bonaire, Sint Eustatius and Saba | B29: MINNESOTA | D29: 333 - Machinery Manufacturing | F29: =IF(Facilities!A30="",F28,Facilities!A30)
A30: Bosnia and Herzegovina | B30: MISSISSIPPI | D30: 334 - Computer and Electronic Product Manufacturing | F30: =IF(Facilities!A31="",F29,Facilities!A31)
A31: Botswana | B31: MISSOURI | D31: 335 - Electrical Equipment, Appliance, and Component | F31: =IF(Facilities!A32="",F30,Facilities!A32)
A32: Bouvet Island | B32: MONTANA | D32: 336 - Transportation Equipment Manufacturing | F32: =IF(Facilities!A33="",F31,Facilities!A33)
A33: Brazil | B33: NEBRASKA | D33: 337 - Furniture and Related Product Manufacturing | F33: =IF(Facilities!A34="",F32,Facilities!A34)
... A60: Czechia | B60: WYOMING | D60: 493 - Warehousing and Storage | F60: =IF(Facilities!A61="",F59,Facilities!A61)
A61: Côte d"Ivoire | D61: 511 - Publishing Industries (except Internet) | F61: =IF(Facilities!A62="",F60,Facilities!A62)
A62: Denmark | D62: 512 - Motion Picture and Sound Recording Industries | F62: =IF(Facilities!A63="",F61,Facilities!A63)
A63: Djibouti | D63: 515 - Broadcasting (except Internet) | F63: =IF(Facilities!A64="",F62,Facilities!A64)
A64: Dominica | D64: 517 - Telecommunications | F64: =IF(Facilities!A65="",F63,Facilities!A65)
A65: Dominican Republic (the) | D65: 518 - Data Processing, Hosting, and Related Services | F65: =IF(Facilities!A66="",F64,Facilities!A66)
A66: Ecuador | D66: 519 - Other Information Services | F66: =IF(Facilities!A67="",F65,Facilities!A67)
A67: Egypt | D67: 521 - Monetary Authorities-Central Bank | F67: =IF(Facilities!A68="",F66,Facilities!A68)
A68: El Salvador | D68: 522 - Credit Intermediation and Related Activities | F68: =IF(Facilities!A69="",F67,Facilities!A69)
A69: Equatorial Guinea | D69: 523 - Securities, Commodity Contracts, and Other Fin | F69: =IF(Facilities!A70="",F68,Facilities!A70)
A70: Eritrea | D70: 524 - Insurance Carriers and Related Activities | F70: =IF(Facilities!A71="",F69,Facilities!A71)
A71: Estonia | D71: 525 - Funds, Trusts, and Other Financial Vehicles | F71: =IF(Facilities!A72="",F70,Facilities!A72)
A72: Eswatini | D72: 531 - Real Estate | F72: =IF(Facilities!A73="",F71,Facilities!A73)
... A100: Holy See (the) | D100: 928 - National Security and International Affairs | F100: =IF(Facilities!A101="",F99,Facilities!A101)
A101: Honduras | F101: =IF(Facilities!A102="",F100,Facilities!A102)
A102: Hong Kong
A103: Hungary
A104: Iceland
A105: India
A106: Indonesia
A107: Iran (Islamic Republic of)
A108: Iraq
A109: Ireland
A110: Isle of Man
A111: Israel
A112: Italy
A113: Jamaica
... A250: Åland Islands

Sheet Electricity Meters
A1: √ Electricity Meter Setup | O1: √ Electricity Charge Setup (Optional)
A2: Facility Name | B2: Meter Number (UNIQUE) | C2: Meter Name (DISPLAY) | D2: Meter Group (ANALYSIS) | E2: Calendarize Readings? | F2: Unit (USAGE) | G2: Unit (DEMAND) | H2: S2S Factor | I2: Agreement Type | J2: Retain RECs? | K2: Account # | L2: Supplier | M2: Location | N2: Notes | O2: ="Charge "&QUOTIENT(COLUMN()-13,2)&" Name" -> Charge 1 Name | P2: ="Charge "&QUOTIENT(COLUMN()-13,2)&" Type" -> Charge 1 Type | Q2: ="Charge "&QUOTIENT(COLUMN()-13,2)&" Name" -> Charge 2 Name | R2: ="Charge "&QUOTIENT(COLUMN()-13,2)&" Type" -> Charge 2 Type | S2: ="Charge "&QUOTIENT(COLUMN()-13,2)&" Name" -> Charge 3 Name | T2: ="Charge "&QUOTIENT(COLUMN()-13,2)&" Type" -> Charge 3 Type | U2: ="Charge "&QUOTIENT(COLUMN()-13,2)&" Name" -> Charge 4 Name | V2: ="Charge "&QUOTIENT(COLUMN()-13,2)&" Type" -> Charge 4 Type | W2: ="Charge "&QUOTIENT(COLUMN()-13,2)&" Name" -> Charge 5 Name | X2: ="Charge "&QUOTIENT(COLUMN()-13,2)&" Type" -> Charge 5 Type | Y2: ="Charge "&QUOTIENT(COLUMN()-13,2)&" Name" -> Charge 6 Name | Z2: ="Charge "&QUOTIENT(COLUMN()-13,2)&" Type" -> Charge 6 Type | AA2: ="Charge "&QUOTIENT(COLUMN()-13,2)&" Name" -> Charge 7 Name | AB2: ="Charge "&QUOTIENT(COLUMN()-13,2)&" Type" -> Charge 7 Type | AC2: ="Charge "&QUOTIENT(COLUMN()-13,2)&" Name" -> Charge 8 Name | AD2: ="Charge "&QUOTIENT(COLUMN()-13,2)&" Type" -> Charge 8 Type | AE2: ="Charge "&QUOTIENT(COLUMN()-13,2)&" Name" -> Charge 9 Name | AF2: ="Charge "&QUOTIENT(COLUMN()-13,2)&" Type" -> Charge 9 Type | AG2: ="Charge "&QUOTIENT(COLUMN()-13,2)&" Name" -> Charge 10 Name | AH2: ="Charge "&QUOTIENT(COLUMN()-13,2)&" Type" -> Charge 10 Type | AI2: ="Charge "&QUOTIENT(COLUMN()-13,2)&" Name" -> Charge 11 Name | AJ2: ="Charge "&QUOTIENT(COLUMN()-13,2)&" Type" -> Charge 11 Type | AK2: ="Charge "&QUOTIENT(COLUMN()-13,2)&" Name" -> Charge 12 Name | AL2: ="Charge "&QUOTIENT(COLUMN()-13,2)&" Type" -> Charge 12 Type | AM2: ="Charge "&QUOTIENT(COLUMN()-13,2)&" Name" -> Charge 13 Name | AN2: ="Charge "&QUOTIENT(COLUMN()-13,2)&" Type" -> Charge 13 Type | AO2: ="Charge "&QUOTIENT(COLUMN()-13,2)&" Name" -> Charge 14 Name | AP2: ="Charge "&QUOTIENT(COLUMN()-13,2)&" Type" -> Charge 14 Type | AQ2: ="Charge "&QUOTIENT(COLUMN()-13,2)&" Name" -> Charge 15 Name | AR2: ="Charge "&QUOTIENT(COLUMN()-13,2)&" Type" -> Charge 15 Type

Sheet Electricity
A1: √ Electricity Meter Readings | G1: √ Electricity Charges (Optional)
A2: Meter Number | B2: Read Date | C2: Total Usage | D2: Actual Demand | E2: Power Factor | F2: Total Cost ($) | G2: =IF(INDEX(List_ChargeNumbers_Electricial, 1, ROUNDUP(COLUMN()/3-2,0)) = 0,"",INDEX(List_ChargeNumbers_Electricial, 2, ROUNDUP(COLUMN()/3-2,0))&" Name") | H2: =IF(INDEX(List_ChargeNumbers_Electricial, 1, ROUNDUP(COLUMN()/3-2,0)) = 0,"",INDEX(List_ChargeNumbers_Electricial, 2, ROUNDUP(COLUMN()/3-2,0))&" Reading") | I2: =IF(INDEX(List_ChargeNumbers_Electricial, 1, ROUNDUP(COLUMN()/3-2,0)) = 0,"",INDEX(List_ChargeNumbers_Electricial, 2, ROUNDUP(COLUMN()/3-2,0))&" Cost") | J2: =IF(INDEX(List_ChargeNumbers_Electricial, 1, ROUNDUP(COLUMN()/3-2,0)) = 0,"",INDEX(List_ChargeNumbers_Electricial, 2, ROUNDUP(COLUMN()/3-2,0))&" Name") | K2: =IF(INDEX(List_ChargeNumbers_Electricial, 1, ROUNDUP(COLUMN()/3-2,0)) = 0,"",INDEX(List_ChargeNumbers_Electricial, 2, ROUNDUP(COLUMN()/3-2,0))&" Reading") | L2: =IF(INDEX(List_ChargeNumbers_Electricial, 1, ROUNDUP(COLUMN()/3-2,0)) = 0,"",INDEX(List_ChargeNumbers_Electricial, 2, ROUNDUP(COLUMN()/3-2,0))&" Cost") | M2: =IF(INDEX(List_ChargeNumbers_Electricial, 1, ROUNDUP(COLUMN()/3-2,0)) = 0,"",INDEX(List_ChargeNumbers_Electricial, 2, ROUNDUP(COLUMN()/3-2,0))&" Name") | N2: =IF(INDEX(List_ChargeNumbers_Electricial, 1, ROUNDUP(COLUMN()/3-2,0)) = 0,"",INDEX(List_ChargeNumbers_Electricial, 2, ROUNDUP(COLUMN()/3-2,0))&" Reading") | O2: =IF(INDEX(List_ChargeNumbers_Electricial, 1, ROUNDUP(COLUMN()/3-2,0)) = 0,"",INDEX(List_ChargeNumbers_Electricial, 2, ROUNDUP(COLUMN()/3-2,0))&" Cost") | P2: =IF(INDEX(List_ChargeNumbers_Electricial, 1, ROUNDUP(COLUMN()/3-2,0)) = 0,"",INDEX(List_ChargeNumbers_Electricial, 2, ROUNDUP(COLUMN()/3-2,0))&" Name") | Q2: =IF(INDEX(List_ChargeNumbers_Electricial, 1, ROUNDUP(COLUMN()/3-2,0)) = 0,"",INDEX(List_ChargeNumbers_Electricial, 2, ROUNDUP(COLUMN()/3-2,0))&" Reading") | R2: =IF(INDEX(List_ChargeNumbers_Electricial, 1, ROUNDUP(COLUMN()/3-2,0)) = 0,"",INDEX(List_ChargeNumbers_Electricial, 2, ROUNDUP(COLUMN()/3-2,0))&" Cost") | S2: =IF(INDEX(List_ChargeNumbers_Electricial, 1, ROUNDUP(COLUMN()/3-2,0)) = 0,"",INDEX(List_ChargeNumbers_Electricial, 2, ROUNDUP(COLUMN()/3-2,0))&" Name") | T2: =IF(INDEX(List_ChargeNumbers_Electricial, 1, ROUNDUP(COLUMN()/3-2,0)) = 0,"",INDEX(List_ChargeNumbers_Electricial, 2, ROUNDUP(COLUMN()/3-2,0))&" Reading") | U2: =IF(INDEX(List_ChargeNumbers_Electricial, 1, ROUNDUP(COLUMN()/3-2,0)) = 0,"",INDEX(List_ChargeNumbers_Electricial, 2, ROUNDUP(COLUMN()/3-2,0))&" Cost") | V2: =IF(INDEX(List_ChargeNumbers_Electricial, 1, ROUNDUP(COLUMN()/3-2,0)) = 0,"",INDEX(List_ChargeNumbers_Electricial, 2, ROUNDUP(COLUMN()/3-2,0))&" Name") | W2: =IF(INDEX(List_ChargeNumbers_Electricial, 1, ROUNDUP(COLUMN()/3-2,0)) = 0,"",INDEX(List_ChargeNumbers_Electricial, 2, ROUNDUP(COLUMN()/3-2,0))&" Reading") | X2: =IF(INDEX(List_ChargeNumbers_Electricial, 1, ROUNDUP(COLUMN()/3-2,0)) = 0,"",INDEX(List_ChargeNumbers_Electricial, 2, ROUNDUP(COLUMN()/3-2,0))&" Cost") | Y2: =IF(INDEX(List_ChargeNumbers_Electricial, 1, ROUNDUP(COLUMN()/3-2,0)) = 0,"",INDEX(List_ChargeNumbers_Electricial, 2, ROUNDUP(COLUMN()/3-2,0))&" Name") | Z2: =IF(INDEX(List_ChargeNumbers_Electricial, 1, ROUNDUP(COLUMN()/3-2,0)) = 0,"",INDEX(List_ChargeNumbers_Electricial, 2, ROUNDUP(COLUMN()/3-2,0))&" Reading") | AA2: =IF(INDEX(List_ChargeNumbers_Electricial, 1, ROUNDUP(COLUMN()/3-2,0)) = 0,"",INDEX(List_ChargeNumbers_Electricial, 2, ROUNDUP(COLUMN()/3-2,0))&" Cost") | AB2: =IF(INDEX(List_ChargeNumbers_Electricial, 1, ROUNDUP(COLUMN()/3-2,0)) = 0,"",INDEX(List_ChargeNumbers_Electricial, 2, ROUNDUP(COLUMN()/3-2,0))&" Name") | AC2: =IF(INDEX(List_ChargeNumbers_Electricial, 1, ROUNDUP(COLUMN()/3-2,0)) = 0,"",INDEX(List_ChargeNumbers_Electricial, 2, ROUNDUP(COLUMN()/3-2,0))&" Reading") | AD2: =IF(INDEX(List_ChargeNumbers_Electricial, 1, ROUNDUP(COLUMN()/3-2,0)) = 0,"",INDEX(List_ChargeNumbers_Electricial, 2, ROUNDUP(COLUMN()/3-2,0))&" Cost") | AE2: =IF(INDEX(List_ChargeNumbers_Electricial, 1, ROUNDUP(COLUMN()/3-2,0)) = 0,"",INDEX(List_ChargeNumbers_Electricial, 2, ROUNDUP(COLUMN()/3-2,0))&" Name") | AF2: =IF(INDEX(List_ChargeNumbers_Electricial, 1, ROUNDUP(COLUMN()/3-2,0)) = 0,"",INDEX(List_ChargeNumbers_Electricial, 2, ROUNDUP(COLUMN()/3-2,0))&" Reading") | AG2: =IF(INDEX(List_ChargeNumbers_Electricial, 1, ROUNDUP(COLUMN()/3-2,0)) = 0,"",INDEX(List_ChargeNumbers_Electricial, 2, ROUNDUP(COLUMN()/3-2,0))&" Cost") | AH2: =IF(INDEX(List_ChargeNumbers_Electricial, 1, ROUNDUP(COLUMN()/3-2,0)) = 0,"",INDEX(List_ChargeNumbers_Electricial, 2, ROUNDUP(COLUMN()/3-2,0))&" Name") | AI2: =IF(INDEX(List_ChargeNumbers_Electricial, 1, ROUNDUP(COLUMN()/3-2,0)) = 0,"",INDEX(List_ChargeNumbers_Electricial, 2, ROUNDUP(COLUMN()/3-2,0))&" Reading") | AJ2: =IF(INDEX(List_ChargeNumbers_Electricial, 1, ROUNDUP(COLUMN()/3-2,0)) = 0,"",INDEX(List_ChargeNumbers_Electricial, 2, ROUNDUP(COLUMN()/3-2,0))&" Cost") | AK2: =IF(INDEX(List_ChargeNumbers_Electricial, 1, ROUNDUP(COLUMN()/3-2,0)) = 0,"",INDEX(List_ChargeNumbers_Electricial, 2, ROUNDUP(COLUMN()/3-2,0))&" Name") | AL2: =IF(INDEX(List_ChargeNumbers_Electricial, 1, ROUNDUP(COLUMN()/3-2,0)) = 0,"",INDEX(List_ChargeNumbers_Electricial, 2, ROUNDUP(COLUMN()/3-2,0))&" Reading") | AM2: =IF(INDEX(List_ChargeNumbers_Electricial, 1, ROUNDUP(COLUMN()/3-2,0)) = 0,"",INDEX(List_ChargeNumbers_Electricial, 2, ROUNDUP(COLUMN()/3-2,0))&" Cost") | AN2: =IF(INDEX(List_ChargeNumbers_Electricial, 1, ROUNDUP(COLUMN()/3-2,0)) = 0,"",INDEX(List_ChargeNumbers_Electricial, 2, ROUNDUP(COLUMN()/3-2,0))&" Name") | AO2: =IF(INDEX(List_ChargeNumbers_Electricial, 1, ROUNDUP(COLUMN()/3-2,0)) = 0,"",INDEX(List_ChargeNumbers_Electricial, 2, ROUNDUP(COLUMN()/3-2,0))&" Reading") | AP2: =IF(INDEX(List_ChargeNumbers_Electricial, 1, ROUNDUP(COLUMN()/3-2,0)) = 0,"",INDEX(List_ChargeNumbers_Electricial, 2, ROUNDUP(COLUMN()/3-2,0))&" Cost") | AQ2: =IF(INDEX(List_ChargeNumbers_Electricial, 1, ROUNDUP(COLUMN()/3-2,0)) = 0,"",INDEX(List_ChargeNumbers_Electricial, 2, ROUNDUP(COLUMN()/3-2,0))&" Name") | AR2: =IF(INDEX(List_ChargeNumbers_Electricial, 1, ROUNDUP(COLUMN()/3-2,0)) = 0,"",INDEX(List_ChargeNumbers_Electricial, 2, ROUNDUP(COLUMN()/3-2,0))&" Reading") | AS2: =IF(INDEX(List_ChargeNumbers_Electricial, 1, ROUNDUP(COLUMN()/3-2,0)) = 0,"",INDEX(List_ChargeNumbers_Electricial, 2, ROUNDUP(COLUMN()/3-2,0))&" Cost") | AT2: =IF(INDEX(List_ChargeNumbers_Electricial, 1, ROUNDUP(COLUMN()/3-2,0)) = 0,"",INDEX(List_ChargeNumbers_Electricial, 2, ROUNDUP(COLUMN()/3-2,0))&" Name") | AU2: =IF(INDEX(List_ChargeNumbers_Electricial, 1, ROUNDUP(COLUMN()/3-2,0)) = 0,"",INDEX(List_ChargeNumbers_Electricial, 2, ROUNDUP(COLUMN()/3-2,0))&" Reading") | AV2: =IF(INDEX(List_ChargeNumbers_Electricial, 1, ROUNDUP(COLUMN()/3-2,0)) = 0,"",INDEX(List_ChargeNumbers_Electricial, 2, ROUNDUP(COLUMN()/3-2,0))&" Cost") | AW2: =IF(INDEX(List_ChargeNumbers_Electricial, 1, ROUNDUP(COLUMN()/3-2,0)) = 0,"",INDEX(List_ChargeNumbers_Electricial, 2, ROUNDUP(COLUMN()/3-2,0))&" Name") | AX2: =IF(INDEX(List_ChargeNumbers_Electricial, 1, ROUNDUP(COLUMN()/3-2,0)) = 0,"",INDEX(List_ChargeNumbers_Electricial, 2, ROUNDUP(COLUMN()/3-2,0))&" Reading") | AY2: =IF(INDEX(List_ChargeNumbers_Electricial, 1, ROUNDUP(COLUMN()/3-2,0)) = 0,"",INDEX(List_ChargeNumbers_Electricial, 2, ROUNDUP(COLUMN()/3-2,0))&" Cost")
G3: =IF(ISBLANK($A3),"",INDEX(Array_ElectricalCharges,MATCH($A3,List_ElectricityMeters,0),ROUNDUP(COLUMN()/3,0)-2)) | J3: =IF(ISBLANK($A3),"",INDEX(Array_ElectricalCharges,MATCH($A3,List_ElectricityMeters,0),ROUNDUP(COLUMN()/3,0)-2)) | M3: =IF(ISBLANK($A3),"",INDEX(Array_ElectricalCharges,MATCH($A3,List_ElectricityMeters,0),ROUNDUP(COLUMN()/3,0)-2)) | P3: =IF(ISBLANK($A3),"",INDEX(Array_ElectricalCharges,MATCH($A3,List_ElectricityMeters,0),ROUNDUP(COLUMN()/3,0)-2)) | S3: =IF(ISBLANK($A3),"",INDEX(Array_ElectricalCharges,MATCH($A3,List_ElectricityMeters,0),ROUNDUP(COLUMN()/3,0)-2)) | V3: =IF(ISBLANK($A3),"",INDEX(Array_ElectricalCharges,MATCH($A3,List_ElectricityMeters,0),ROUNDUP(COLUMN()/3,0)-2)) | Y3: =IF(ISBLANK($A3),"",INDEX(Array_ElectricalCharges,MATCH($A3,List_ElectricityMeters,0),ROUNDUP(COLUMN()/3,0)-2)) | AB3: =IF(ISBLANK($A3),"",INDEX(Array_ElectricalCharges,MATCH($A3,List_ElectricityMeters,0),ROUNDUP(COLUMN()/3,0)-2)) | AE3: =IF(ISBLANK($A3),"",INDEX(Array_ElectricalCharges,MATCH($A3,List_ElectricityMeters,0),ROUNDUP(COLUMN()/3,0)-2)) | AH3: =IF(ISBLANK($A3),"",INDEX(Array_ElectricalCharges,MATCH($A3,List_ElectricityMeters,0),ROUNDUP(COLUMN()/3,0)-2)) | AK3: =IF(ISBLANK($A3),"",INDEX(Array_ElectricalCharges,MATCH($A3,List_ElectricityMeters,0),ROUNDUP(COLUMN()/3,0)-2)) | AN3: =IF(ISBLANK($A3),"",INDEX(Array_ElectricalCharges,MATCH($A3,List_ElectricityMeters,0),ROUNDUP(COLUMN()/3,0)-2)) | AQ3: =IF(ISBLANK($A3),"",INDEX(Array_ElectricalCharges,MATCH($A3,List_ElectricityMeters,0),ROUNDUP(COLUMN()/3,0)-2)) | AT3: =IF(ISBLANK($A3),"",INDEX(Array_ElectricalCharges,MATCH($A3,List_ElectricityMeters,0),ROUNDUP(COLUMN()/3,0)-2)) | AW3: =IF(ISBLANK($A3),"",INDEX(Array_ElectricalCharges,MATCH($A3,List_ElectricityMeters,0),ROUNDUP(COLUMN()/3,0)-2))
G4: =IF(ISBLANK($A4),"",INDEX(Array_ElectricalCharges,MATCH($A4,List_ElectricityMeters,0),ROUNDUP(COLUMN()/3,0)-2)) | J4: =IF(ISBLANK($A4),"",INDEX(Array_ElectricalCharges,MATCH($A4,List_ElectricityMeters,0),ROUNDUP(COLUMN()/3,0)-2)) | M4: =IF(ISBLANK($A4),"",INDEX(Array_ElectricalCharges,MATCH($A4,List_ElectricityMeters,0),ROUNDUP(COLUMN()/3,0)-2)) | P4: =IF(ISBLANK($A4),"",INDEX(Array_ElectricalCharges,MATCH($A4,List_ElectricityMeters,0),ROUNDUP(COLUMN()/3,0)-2)) | S4: =IF(ISBLANK($A4),"",INDEX(Array_ElectricalCharges,MATCH($A4,List_ElectricityMeters,0),ROUNDUP(COLUMN()/3,0)-2)) | V4: =IF(ISBLANK($A4),"",INDEX(Array_ElectricalCharges,MATCH($A4,List_ElectricityMeters,0),ROUNDUP(COLUMN()/3,0)-2)) | Y4: =IF(ISBLANK($A4),"",INDEX(Array_ElectricalCharges,MATCH($A4,List_ElectricityMeters,0),ROUNDUP(COLUMN()/3,0)-2)) | AB4: =IF(ISBLANK($A4),"",INDEX(Array_ElectricalCharges,MATCH($A4,List_ElectricityMeters,0),ROUNDUP(COLUMN()/3,0)-2)) | AE4: =IF(ISBLANK($A4),"",INDEX(Array_ElectricalCharges,MATCH($A4,List_ElectricityMeters,0),ROUNDUP(COLUMN()/3,0)-2)) | AH4: =IF(ISBLANK($A4),"",INDEX(Array_ElectricalCharges,MATCH($A4,List_ElectricityMeters,0),ROUNDUP(COLUMN()/3,0)-2)) | AK4: =IF(ISBLANK($A4),"",INDEX(Array_ElectricalCharges,MATCH($A4,List_ElectricityMeters,0),ROUNDUP(COLUMN()/3,0)-2)) | AN4: =IF(ISBLANK($A4),"",INDEX(Array_ElectricalCharges,MATCH($A4,List_ElectricityMeters,0),ROUNDUP(COLUMN()/3,0)-2)) | AQ4: =IF(ISBLANK($A4),"",INDEX(Array_ElectricalCharges,MATCH($A4,List_ElectricityMeters,0),ROUNDUP(COLUMN()/3,0)-2)) | AT4: =IF(ISBLANK($A4),"",INDEX(Array_ElectricalCharges,MATCH($A4,List_ElectricityMeters,0),ROUNDUP(COLUMN()/3,0)-2)) | AW4: =IF(ISBLANK($A4),"",INDEX(Array_ElectricalCharges,MATCH($A4,List_ElectricityMeters,0),ROUNDUP(COLUMN()/3,0)-2))
G5: =IF(ISBLANK($A5),"",INDEX(Array_ElectricalCharges,MATCH($A5,List_ElectricityMeters,0),ROUNDUP(COLUMN()/3,0)-2)) | J5: =IF(ISBLANK($A5),"",INDEX(Array_ElectricalCharges,MATCH($A5,List_ElectricityMeters,0),ROUNDUP(COLUMN()/3,0)-2)) | M5: =IF(ISBLANK($A5),"",INDEX(Array_ElectricalCharges,MATCH($A5,List_ElectricityMeters,0),ROUNDUP(COLUMN()/3,0)-2)) | P5: =IF(ISBLANK($A5),"",INDEX(Array_ElectricalCharges,MATCH($A5,List_ElectricityMeters,0),ROUNDUP(COLUMN()/3,0)-2)) | S5: =IF(ISBLANK($A5),"",INDEX(Array_ElectricalCharges,MATCH($A5,List_ElectricityMeters,0),ROUNDUP(COLUMN()/3,0)-2)) | V5: =IF(ISBLANK($A5),"",INDEX(Array_ElectricalCharges,MATCH($A5,List_ElectricityMeters,0),ROUNDUP(COLUMN()/3,0)-2)) | Y5: =IF(ISBLANK($A5),"",INDEX(Array_ElectricalCharges,MATCH($A5,List_ElectricityMeters,0),ROUNDUP(COLUMN()/3,0)-2)) | AB5: =IF(ISBLANK($A5),"",INDEX(Array_ElectricalCharges,MATCH($A5,List_ElectricityMeters,0),ROUNDUP(COLUMN()/3,0)-2)) | AE5: =IF(ISBLANK($A5),"",INDEX(Array_ElectricalCharges,MATCH($A5,List_ElectricityMeters,0),ROUNDUP(COLUMN()/3,0)-2)) | AH5: =IF(ISBLANK($A5),"",INDEX(Array_ElectricalCharges,MATCH($A5,List_ElectricityMeters,0),ROUNDUP(COLUMN()/3,0)-2)) | AK5: =IF(ISBLANK($A5),"",INDEX(Array_ElectricalCharges,MATCH($A5,List_ElectricityMeters,0),ROUNDUP(COLUMN()/3,0)-2)) | AN5: =IF(ISBLANK($A5),"",INDEX(Array_ElectricalCharges,MATCH($A5,List_ElectricityMeters,0),ROUNDUP(COLUMN()/3,0)-2)) | AQ5: =IF(ISBLANK($A5),"",INDEX(Array_ElectricalCharges,MATCH($A5,List_ElectricityMeters,0),ROUNDUP(COLUMN()/3,0)-2)) | AT5: =IF(ISBLANK($A5),"",INDEX(Array_ElectricalCharges,MATCH($A5,List_ElectricityMeters,0),ROUNDUP(COLUMN()/3,0)-2)) | AW5: =IF(ISBLANK($A5),"",INDEX(Array_ElectricalCharges,MATCH($A5,List_ElectricityMeters,0),ROUNDUP(COLUMN()/3,0)-2))
G6: =IF(ISBLANK($A6),"",INDEX(Array_ElectricalCharges,MATCH($A6,List_ElectricityMeters,0),ROUNDUP(COLUMN()/3,0)-2)) | J6: =IF(ISBLANK($A6),"",INDEX(Array_ElectricalCharges,MATCH($A6,List_ElectricityMeters,0),ROUNDUP(COLUMN()/3,0)-2)) | M6: =IF(ISBLANK($A6),"",INDEX(Array_ElectricalCharges,MATCH($A6,List_ElectricityMeters,0),ROUNDUP(COLUMN()/3,0)-2)) | P6: =IF(ISBLANK($A6),"",INDEX(Array_ElectricalCharges,MATCH($A6,List_ElectricityMeters,0),ROUNDUP(COLUMN()/3,0)-2)) | S6: =IF(ISBLANK($A6),"",INDEX(Array_ElectricalCharges,MATCH($A6,List_ElectricityMeters,0),ROUNDUP(COLUMN()/3,0)-2)) | V6: =IF(ISBLANK($A6),"",INDEX(Array_ElectricalCharges,MATCH($A6,List_ElectricityMeters,0),ROUNDUP(COLUMN()/3,0)-2)) | Y6: =IF(ISBLANK($A6),"",INDEX(Array_ElectricalCharges,MATCH($A6,List_ElectricityMeters,0),ROUNDUP(COLUMN()/3,0)-2)) | AB6: =IF(ISBLANK($A6),"",INDEX(Array_ElectricalCharges,MATCH($A6,List_ElectricityMeters,0),ROUNDUP(COLUMN()/3,0)-2)) | AE6: =IF(ISBLANK($A6),"",INDEX(Array_ElectricalCharges,MATCH($A6,List_ElectricityMeters,0),ROUNDUP(COLUMN()/3,0)-2)) | AH6: =IF(ISBLANK($A6),"",INDEX(Array_ElectricalCharges,MATCH($A6,List_ElectricityMeters,0),ROUNDUP(COLUMN()/3,0)-2)) | AK6: =IF(ISBLANK($A6),"",INDEX(Array_ElectricalCharges,MATCH($A6,List_ElectricityMeters,0),ROUNDUP(COLUMN()/3,0)-2)) | AN6: =IF(ISBLANK($A6),"",INDEX(Array_ElectricalCharges,MATCH($A6,List_ElectricityMeters,0),ROUNDUP(COLUMN()/3,0)-2)) | AQ6: =IF(ISBLANK($A6),"",INDEX(Array_ElectricalCharges,MATCH($A6,List_ElectricityMeters,0),ROUNDUP(COLUMN()/3,0)-2)) | AT6: =IF(ISBLANK($A6),"",INDEX(Array_ElectricalCharges,MATCH($A6,List_ElectricityMeters,0),ROUNDUP(COLUMN()/3,0)-2)) | AW6: =IF(ISBLANK($A6),"",INDEX(Array_ElectricalCharges,MATCH($A6,List_ElectricityMeters,0),ROUNDUP(COLUMN()/3,0)-2))
G7: =IF(ISBLANK($A7),"",INDEX(Array_ElectricalCharges,MATCH($A7,List_ElectricityMeters,0),ROUNDUP(COLUMN()/3,0)-2)) | J7: =IF(ISBLANK($A7),"",INDEX(Array_ElectricalCharges,MATCH($A7,List_ElectricityMeters,0),ROUNDUP(COLUMN()/3,0)-2)) | M7: =IF(ISBLANK($A7),"",INDEX(Array_ElectricalCharges,MATCH($A7,List_ElectricityMeters,0),ROUNDUP(COLUMN()/3,0)-2)) | P7: =IF(ISBLANK($A7),"",INDEX(Array_ElectricalCharges,MATCH($A7,List_ElectricityMeters,0),ROUNDUP(COLUMN()/3,0)-2)) | S7: =IF(ISBLANK($A7),"",INDEX(Array_ElectricalCharges,MATCH($A7,List_ElectricityMeters,0),ROUNDUP(COLUMN()/3,0)-2)) | V7: =IF(ISBLANK($A7),"",INDEX(Array_ElectricalCharges,MATCH($A7,List_ElectricityMeters,0),ROUNDUP(COLUMN()/3,0)-2)) | Y7: =IF(ISBLANK($A7),"",INDEX(Array_ElectricalCharges,MATCH($A7,List_ElectricityMeters,0),ROUNDUP(COLUMN()/3,0)-2)) | AB7: =IF(ISBLANK($A7),"",INDEX(Array_ElectricalCharges,MATCH($A7,List_ElectricityMeters,0),ROUNDUP(COLUMN()/3,0)-2)) | AE7: =IF(ISBLANK($A7),"",INDEX(Array_ElectricalCharges,MATCH($A7,List_ElectricityMeters,0),ROUNDUP(COLUMN()/3,0)-2)) | AH7: =IF(ISBLANK($A7),"",INDEX(Array_ElectricalCharges,MATCH($A7,List_ElectricityMeters,0),ROUNDUP(COLUMN()/3,0)-2)) | AK7: =IF(ISBLANK($A7),"",INDEX(Array_ElectricalCharges,MATCH($A7,List_ElectricityMeters,0),ROUNDUP(COLUMN()/3,0)-2)) | AN7: =IF(ISBLANK($A7),"",INDEX(Array_ElectricalCharges,MATCH($A7,List_ElectricityMeters,0),ROUNDUP(COLUMN()/3,0)-2)) | AQ7: =IF(ISBLANK($A7),"",INDEX(Array_ElectricalCharges,MATCH($A7,List_ElectricityMeters,0),ROUNDUP(COLUMN()/3,0)-2)) | AT7: =IF(ISBLANK($A7),"",INDEX(Array_ElectricalCharges,MATCH($A7,List_ElectricityMeters,0),ROUNDUP(COLUMN()/3,0)-2)) | AW7: =IF(ISBLANK($A7),"",INDEX(Array_ElectricalCharges,MATCH($A7,List_ElectricityMeters,0),ROUNDUP(COLUMN()/3,0)-2))
G8: =IF(ISBLANK($A8),"",INDEX(Array_ElectricalCharges,MATCH($A8,List_ElectricityMeters,0),ROUNDUP(COLUMN()/3,0)-2)) | J8: =IF(ISBLANK($A8),"",INDEX(Array_ElectricalCharges,MATCH($A8,List_ElectricityMeters,0),ROUNDUP(COLUMN()/3,0)-2)) | M8: =IF(ISBLANK($A8),"",INDEX(Array_ElectricalCharges,MATCH($A8,List_ElectricityMeters,0),ROUNDUP(COLUMN()/3,0)-2)) | P8: =IF(ISBLANK($A8),"",INDEX(Array_ElectricalCharges,MATCH($A8,List_ElectricityMeters,0),ROUNDUP(COLUMN()/3,0)-2)) | S8: =IF(ISBLANK($A8),"",INDEX(Array_ElectricalCharges,MATCH($A8,List_ElectricityMeters,0),ROUNDUP(COLUMN()/3,0)-2)) | V8: =IF(ISBLANK($A8),"",INDEX(Array_ElectricalCharges,MATCH($A8,List_ElectricityMeters,0),ROUNDUP(COLUMN()/3,0)-2)) | Y8: =IF(ISBLANK($A8),"",INDEX(Array_ElectricalCharges,MATCH($A8,List_ElectricityMeters,0),ROUNDUP(COLUMN()/3,0)-2)) | AB8: =IF(ISBLANK($A8),"",INDEX(Array_ElectricalCharges,MATCH($A8,List_ElectricityMeters,0),ROUNDUP(COLUMN()/3,0)-2)) | AE8: =IF(ISBLANK($A8),"",INDEX(Array_ElectricalCharges,MATCH($A8,List_ElectricityMeters,0),ROUNDUP(COLUMN()/3,0)-2)) | AH8: =IF(ISBLANK($A8),"",INDEX(Array_ElectricalCharges,MATCH($A8,List_ElectricityMeters,0),ROUNDUP(COLUMN()/3,0)-2)) | AK8: =IF(ISBLANK($A8),"",INDEX(Array_ElectricalCharges,MATCH($A8,List_ElectricityMeters,0),ROUNDUP(COLUMN()/3,0)-2)) | AN8: =IF(ISBLANK($A8),"",INDEX(Array_ElectricalCharges,MATCH($A8,List_ElectricityMeters,0),ROUNDUP(COLUMN()/3,0)-2)) | AQ8: =IF(ISBLANK($A8),"",INDEX(Array_ElectricalCharges,MATCH($A8,List_ElectricityMeters,0),ROUNDUP(COLUMN()/3,0)-2)) | AT8: =IF(ISBLANK($A8),"",INDEX(Array_ElectricalCharges,MATCH($A8,List_ElectricityMeters,0),ROUNDUP(COLUMN()/3,0)-2)) | AW8: =IF(ISBLANK($A8),"",INDEX(Array_ElectricalCharges,MATCH($A8,List_ElectricityMeters,0),ROUNDUP(COLUMN()/3,0)-2))
G9: =IF(ISBLANK($A9),"",INDEX(Array_ElectricalCharges,MATCH($A9,List_ElectricityMeters,0),ROUNDUP(COLUMN()/3,0)-2)) | J9: =IF(ISBLANK($A9),"",INDEX(Array_ElectricalCharges,MATCH($A9,List_ElectricityMeters,0),ROUNDUP(COLUMN()/3,0)-2)) | M9: =IF(ISBLANK($A9),"",INDEX(Array_ElectricalCharges,MATCH($A9,List_ElectricityMeters,0),ROUNDUP(COLUMN()/3,0)-2)) | P9: =IF(ISBLANK($A9),"",INDEX(Array_ElectricalCharges,MATCH($A9,List_ElectricityMeters,0),ROUNDUP(COLUMN()/3,0)-2)) | S9: =IF(ISBLANK($A9),"",INDEX(Array_ElectricalCharges,MATCH($A9,List_ElectricityMeters,0),ROUNDUP(COLUMN()/3,0)-2)) | V9: =IF(ISBLANK($A9),"",INDEX(Array_ElectricalCharges,MATCH($A9,List_ElectricityMeters,0),ROUNDUP(COLUMN()/3,0)-2)) | Y9: =IF(ISBLANK($A9),"",INDEX(Array_ElectricalCharges,MATCH($A9,List_ElectricityMeters,0),ROUNDUP(COLUMN()/3,0)-2)) | AB9: =IF(ISBLANK($A9),"",INDEX(Array_ElectricalCharges,MATCH($A9,List_ElectricityMeters,0),ROUNDUP(COLUMN()/3,0)-2)) | AE9: =IF(ISBLANK($A9),"",INDEX(Array_ElectricalCharges,MATCH($A9,List_ElectricityMeters,0),ROUNDUP(COLUMN()/3,0)-2)) | AH9: =IF(ISBLANK($A9),"",INDEX(Array_ElectricalCharges,MATCH($A9,List_ElectricityMeters,0),ROUNDUP(COLUMN()/3,0)-2)) | AK9: =IF(ISBLANK($A9),"",INDEX(Array_ElectricalCharges,MATCH($A9,List_ElectricityMeters,0),ROUNDUP(COLUMN()/3,0)-2)) | AN9: =IF(ISBLANK($A9),"",INDEX(Array_ElectricalCharges,MATCH($A9,List_ElectricityMeters,0),ROUNDUP(COLUMN()/3,0)-2)) | AQ9: =IF(ISBLANK($A9),"",INDEX(Array_ElectricalCharges,MATCH($A9,List_ElectricityMeters,0),ROUNDUP(COLUMN()/3,0)-2)) | AT9: =IF(ISBLANK($A9),"",INDEX(Array_ElectricalCharges,MATCH($A9,List_ElectricityMeters,0),ROUNDUP(COLUMN()/3,0)-2)) | AW9: =IF(ISBLANK($A9),"",INDEX(Array_ElectricalCharges,MATCH($A9,List_ElectricityMeters,0),ROUNDUP(COLUMN()/3,0)-2))
G10: =IF(ISBLANK($A10),"",INDEX(Array_ElectricalCharges,MATCH($A10,List_ElectricityMeters,0),ROUNDUP(COLUMN()/3,0)-2)) | J10: =IF(ISBLANK($A10),"",INDEX(Array_ElectricalCharges,MATCH($A10,List_ElectricityMeters,0),ROUNDUP(COLUMN()/3,0)-2)) | M10: =IF(ISBLANK($A10),"",INDEX(Array_ElectricalCharges,MATCH($A10,List_ElectricityMeters,0),ROUNDUP(COLUMN()/3,0)-2)) | P10: =IF(ISBLANK($A10),"",INDEX(Array_ElectricalCharges,MATCH($A10,List_ElectricityMeters,0),ROUNDUP(COLUMN()/3,0)-2)) | S10: =IF(ISBLANK($A10),"",INDEX(Array_ElectricalCharges,MATCH($A10,List_ElectricityMeters,0),ROUNDUP(COLUMN()/3,0)-2)) | V10: =IF(ISBLANK($A10),"",INDEX(Array_ElectricalCharges,MATCH($A10,List_ElectricityMeters,0),ROUNDUP(COLUMN()/3,0)-2)) | Y10: =IF(ISBLANK($A10),"",INDEX(Array_ElectricalCharges,MATCH($A10,List_ElectricityMeters,0),ROUNDUP(COLUMN()/3,0)-2)) | AB10: =IF(ISBLANK($A10),"",INDEX(Array_ElectricalCharges,MATCH($A10,List_ElectricityMeters,0),ROUNDUP(COLUMN()/3,0)-2)) | AE10: =IF(ISBLANK($A10),"",INDEX(Array_ElectricalCharges,MATCH($A10,List_ElectricityMeters,0),ROUNDUP(COLUMN()/3,0)-2)) | AH10: =IF(ISBLANK($A10),"",INDEX(Array_ElectricalCharges,MATCH($A10,List_ElectricityMeters,0),ROUNDUP(COLUMN()/3,0)-2)) | AK10: =IF(ISBLANK($A10),"",INDEX(Array_ElectricalCharges,MATCH($A10,List_ElectricityMeters,0),ROUNDUP(COLUMN()/3,0)-2)) | AN10: =IF(ISBLANK($A10),"",INDEX(Array_ElectricalCharges,MATCH($A10,List_ElectricityMeters,0),ROUNDUP(COLUMN()/3,0)-2)) | AQ10: =IF(ISBLANK($A10),"",INDEX(Array_ElectricalCharges,MATCH($A10,List_ElectricityMeters,0),ROUNDUP(COLUMN()/3,0)-2)) | AT10: =IF(ISBLANK($A10),"",INDEX(Array_ElectricalCharges,MATCH($A10,List_ElectricityMeters,0),ROUNDUP(COLUMN()/3,0)-2)) | AW10: =IF(ISBLANK($A10),"",INDEX(Array_ElectricalCharges,MATCH($A10,List_ElectricityMeters,0),ROUNDUP(COLUMN()/3,0)-2))
G11: =IF(ISBLANK($A11),"",INDEX(Array_ElectricalCharges,MATCH($A11,List_ElectricityMeters,0),ROUNDUP(COLUMN()/3,0)-2)) | J11: =IF(ISBLANK($A11),"",INDEX(Array_ElectricalCharges,MATCH($A11,List_ElectricityMeters,0),ROUNDUP(COLUMN()/3,0)-2)) | M11: =IF(ISBLANK($A11),"",INDEX(Array_ElectricalCharges,MATCH($A11,List_ElectricityMeters,0),ROUNDUP(COLUMN()/3,0)-2)) | P11: =IF(ISBLANK($A11),"",INDEX(Array_ElectricalCharges,MATCH($A11,List_ElectricityMeters,0),ROUNDUP(COLUMN()/3,0)-2)) | S11: =IF(ISBLANK($A11),"",INDEX(Array_ElectricalCharges,MATCH($A11,List_ElectricityMeters,0),ROUNDUP(COLUMN()/3,0)-2)) | V11: =IF(ISBLANK($A11),"",INDEX(Array_ElectricalCharges,MATCH($A11,List_ElectricityMeters,0),ROUNDUP(COLUMN()/3,0)-2)) | Y11: =IF(ISBLANK($A11),"",INDEX(Array_ElectricalCharges,MATCH($A11,List_ElectricityMeters,0),ROUNDUP(COLUMN()/3,0)-2)) | AB11: =IF(ISBLANK($A11),"",INDEX(Array_ElectricalCharges,MATCH($A11,List_ElectricityMeters,0),ROUNDUP(COLUMN()/3,0)-2)) | AE11: =IF(ISBLANK($A11),"",INDEX(Array_ElectricalCharges,MATCH($A11,List_ElectricityMeters,0),ROUNDUP(COLUMN()/3,0)-2)) | AH11: =IF(ISBLANK($A11),"",INDEX(Array_ElectricalCharges,MATCH($A11,List_ElectricityMeters,0),ROUNDUP(COLUMN()/3,0)-2)) | AK11: =IF(ISBLANK($A11),"",INDEX(Array_ElectricalCharges,MATCH($A11,List_ElectricityMeters,0),ROUNDUP(COLUMN()/3,0)-2)) | AN11: =IF(ISBLANK($A11),"",INDEX(Array_ElectricalCharges,MATCH($A11,List_ElectricityMeters,0),ROUNDUP(COLUMN()/3,0)-2)) | AQ11: =IF(ISBLANK($A11),"",INDEX(Array_ElectricalCharges,MATCH($A11,List_ElectricityMeters,0),ROUNDUP(COLUMN()/3,0)-2)) | AT11: =IF(ISBLANK($A11),"",INDEX(Array_ElectricalCharges,MATCH($A11,List_ElectricityMeters,0),ROUNDUP(COLUMN()/3,0)-2)) | AW11: =IF(ISBLANK($A11),"",INDEX(Array_ElectricalCharges,MATCH($A11,List_ElectricityMeters,0),ROUNDUP(COLUMN()/3,0)-2))
G12: =IF(ISBLANK($A12),"",INDEX(Array_ElectricalCharges,MATCH($A12,List_ElectricityMeters,0),ROUNDUP(COLUMN()/3,0)-2)) | J12: =IF(ISBLANK($A12),"",INDEX(Array_ElectricalCharges,MATCH($A12,List_ElectricityMeters,0),ROUNDUP(COLUMN()/3,0)-2)) | M12: =IF(ISBLANK($A12),"",INDEX(Array_ElectricalCharges,MATCH($A12,List_ElectricityMeters,0),ROUNDUP(COLUMN()/3,0)-2)) | P12: =IF(ISBLANK($A12),"",INDEX(Array_ElectricalCharges,MATCH($A12,List_ElectricityMeters,0),ROUNDUP(COLUMN()/3,0)-2)) | S12: =IF(ISBLANK($A12),"",INDEX(Array_ElectricalCharges,MATCH($A12,List_ElectricityMeters,0),ROUNDUP(COLUMN()/3,0)-2)) | V12: =IF(ISBLANK($A12),"",INDEX(Array_ElectricalCharges,MATCH($A12,List_ElectricityMeters,0),ROUNDUP(COLUMN()/3,0)-2)) | Y12: =IF(ISBLANK($A12),"",INDEX(Array_ElectricalCharges,MATCH($A12,List_ElectricityMeters,0),ROUNDUP(COLUMN()/3,0)-2)) | AB12: =IF(ISBLANK($A12),"",INDEX(Array_ElectricalCharges,MATCH($A12,List_ElectricityMeters,0),ROUNDUP(COLUMN()/3,0)-2)) | AE12: =IF(ISBLANK($A12),"",INDEX(Array_ElectricalCharges,MATCH($A12,List_ElectricityMeters,0),ROUNDUP(COLUMN()/3,0)-2)) | AH12: =IF(ISBLANK($A12),"",INDEX(Array_ElectricalCharges,MATCH($A12,List_ElectricityMeters,0),ROUNDUP(COLUMN()/3,0)-2)) | AK12: =IF(ISBLANK($A12),"",INDEX(Array_ElectricalCharges,MATCH($A12,List_ElectricityMeters,0),ROUNDUP(COLUMN()/3,0)-2)) | AN12: =IF(ISBLANK($A12),"",INDEX(Array_ElectricalCharges,MATCH($A12,List_ElectricityMeters,0),ROUNDUP(COLUMN()/3,0)-2)) | AQ12: =IF(ISBLANK($A12),"",INDEX(Array_ElectricalCharges,MATCH($A12,List_ElectricityMeters,0),ROUNDUP(COLUMN()/3,0)-2)) | AT12: =IF(ISBLANK($A12),"",INDEX(Array_ElectricalCharges,MATCH($A12,List_ElectricityMeters,0),ROUNDUP(COLUMN()/3,0)-2)) | AW12: =IF(ISBLANK($A12),"",INDEX(Array_ElectricalCharges,MATCH($A12,List_ElectricityMeters,0),ROUNDUP(COLUMN()/3,0)-2))
G13: =IF(ISBLANK($A13),"",INDEX(Array_ElectricalCharges,MATCH($A13,List_ElectricityMeters,0),ROUNDUP(COLUMN()/3,0)-2)) | J13: =IF(ISBLANK($A13),"",INDEX(Array_ElectricalCharges,MATCH($A13,List_ElectricityMeters,0),ROUNDUP(COLUMN()/3,0)-2)) | M13: =IF(ISBLANK($A13),"",INDEX(Array_ElectricalCharges,MATCH($A13,List_ElectricityMeters,0),ROUNDUP(COLUMN()/3,0)-2)) | P13: =IF(ISBLANK($A13),"",INDEX(Array_ElectricalCharges,MATCH($A13,List_ElectricityMeters,0),ROUNDUP(COLUMN()/3,0)-2)) | S13: =IF(ISBLANK($A13),"",INDEX(Array_ElectricalCharges,MATCH($A13,List_ElectricityMeters,0),ROUNDUP(COLUMN()/3,0)-2)) | V13: =IF(ISBLANK($A13),"",INDEX(Array_ElectricalCharges,MATCH($A13,List_ElectricityMeters,0),ROUNDUP(COLUMN()/3,0)-2)) | Y13: =IF(ISBLANK($A13),"",INDEX(Array_ElectricalCharges,MATCH($A13,List_ElectricityMeters,0),ROUNDUP(COLUMN()/3,0)-2)) | AB13: =IF(ISBLANK($A13),"",INDEX(Array_ElectricalCharges,MATCH($A13,List_ElectricityMeters,0),ROUNDUP(COLUMN()/3,0)-2)) | AE13: =IF(ISBLANK($A13),"",INDEX(Array_ElectricalCharges,MATCH($A13,List_ElectricityMeters,0),ROUNDUP(COLUMN()/3,0)-2)) | AH13: =IF(ISBLANK($A13),"",INDEX(Array_ElectricalCharges,MATCH($A13,List_ElectricityMeters,0),ROUNDUP(COLUMN()/3,0)-2)) | AK13: =IF(ISBLANK($A13),"",INDEX(Array_ElectricalCharges,MATCH($A13,List_ElectricityMeters,0),ROUNDUP(COLUMN()/3,0)-2)) | AN13: =IF(ISBLANK($A13),"",INDEX(Array_ElectricalCharges,MATCH($A13,List_ElectricityMeters,0),ROUNDUP(COLUMN()/3,0)-2)) | AQ13: =IF(ISBLANK($A13),"",INDEX(Array_ElectricalCharges,MATCH($A13,List_ElectricityMeters,0),ROUNDUP(COLUMN()/3,0)-2)) | AT13: =IF(ISBLANK($A13),"",INDEX(Array_ElectricalCharges,MATCH($A13,List_ElectricityMeters,0),ROUNDUP(COLUMN()/3,0)-2)) | AW13: =IF(ISBLANK($A13),"",INDEX(Array_ElectricalCharges,MATCH($A13,List_ElectricityMeters,0),ROUNDUP(COLUMN()/3,0)-2))
G14: =IF(ISBLANK($A14),"",INDEX(Array_ElectricalCharges,MATCH($A14,List_ElectricityMeters,0),ROUNDUP(COLUMN()/3,0)-2)) | J14: =IF(ISBLANK($A14),"",INDEX(Array_ElectricalCharges,MATCH($A14,List_ElectricityMeters,0),ROUNDUP(COLUMN()/3,0)-2)) | M14: =IF(ISBLANK($A14),"",INDEX(Array_ElectricalCharges,MATCH($A14,List_ElectricityMeters,0),ROUNDUP(COLUMN()/3,0)-2)) | P14: =IF(ISBLANK($A14),"",INDEX(Array_ElectricalCharges,MATCH($A14,List_ElectricityMeters,0),ROUNDUP(COLUMN()/3,0)-2)) | S14: =IF(ISBLANK($A14),"",INDEX(Array_ElectricalCharges,MATCH($A14,List_ElectricityMeters,0),ROUNDUP(COLUMN()/3,0)-2)) | V14: =IF(ISBLANK($A14),"",INDEX(Array_ElectricalCharges,MATCH($A14,List_ElectricityMeters,0),ROUNDUP(COLUMN()/3,0)-2)) | Y14: =IF(ISBLANK($A14),"",INDEX(Array_ElectricalCharges,MATCH($A14,List_ElectricityMeters,0),ROUNDUP(COLUMN()/3,0)-2)) | AB14: =IF(ISBLANK($A14),"",INDEX(Array_ElectricalCharges,MATCH($A14,List_ElectricityMeters,0),ROUNDUP(COLUMN()/3,0)-2)) | AE14: =IF(ISBLANK($A14),"",INDEX(Array_ElectricalCharges,MATCH($A14,List_ElectricityMeters,0),ROUNDUP(COLUMN()/3,0)-2)) | AH14: =IF(ISBLANK($A14),"",INDEX(Array_ElectricalCharges,MATCH($A14,List_ElectricityMeters,0),ROUNDUP(COLUMN()/3,0)-2)) | AK14: =IF(ISBLANK($A14),"",INDEX(Array_ElectricalCharges,MATCH($A14,List_ElectricityMeters,0),ROUNDUP(COLUMN()/3,0)-2)) | AN14: =IF(ISBLANK($A14),"",INDEX(Array_ElectricalCharges,MATCH($A14,List_ElectricityMeters,0),ROUNDUP(COLUMN()/3,0)-2)) | AQ14: =IF(ISBLANK($A14),"",INDEX(Array_ElectricalCharges,MATCH($A14,List_ElectricityMeters,0),ROUNDUP(COLUMN()/3,0)-2)) | AT14: =IF(ISBLANK($A14),"",INDEX(Array_ElectricalCharges,MATCH($A14,List_ElectricityMeters,0),ROUNDUP(COLUMN()/3,0)-2)) | AW14: =IF(ISBLANK($A14),"",INDEX(Array_ElectricalCharges,MATCH($A14,List_ElectricityMeters,0),ROUNDUP(COLUMN()/3,0)-2))
... G502: =IF(ISBLANK($A502),"",INDEX(Array_ElectricalCharges,MATCH($A502,List_ElectricityMeters,0),ROUNDUP(COLUMN()/3,0)-2)) | J502: =IF(ISBLANK($A502),"",INDEX(Array_ElectricalCharges,MATCH($A502,List_ElectricityMeters,0),ROUNDUP(COLUMN()/3,0)-2)) | M502: =IF(ISBLANK($A502),"",INDEX(Array_ElectricalCharges,MATCH($A502,List_ElectricityMeters,0),ROUNDUP(COLUMN()/3,0)-2)) | P502: =IF(ISBLANK($A502),"",INDEX(Array_ElectricalCharges,MATCH($A502,List_ElectricityMeters,0),ROUNDUP(COLUMN()/3,0)-2)) | S502: =IF(ISBLANK($A502),"",INDEX(Array_ElectricalCharges,MATCH($A502,List_ElectricityMeters,0),ROUNDUP(COLUMN()/3,0)-2)) | V502: =IF(ISBLANK($A502),"",INDEX(Array_ElectricalCharges,MATCH($A502,List_ElectricityMeters,0),ROUNDUP(COLUMN()/3,0)-2)) | Y502: =IF(ISBLANK($A502),"",INDEX(Array_ElectricalCharges,MATCH($A502,List_ElectricityMeters,0),ROUNDUP(COLUMN()/3,0)-2)) | AB502: =IF(ISBLANK($A502),"",INDEX(Array_ElectricalCharges,MATCH($A502,List_ElectricityMeters,0),ROUNDUP(COLUMN()/3,0)-2)) | AE502: =IF(ISBLANK($A502),"",INDEX(Array_ElectricalCharges,MATCH($A502,List_ElectricityMeters,0),ROUNDUP(COLUMN()/3,0)-2)) | AH502: =IF(ISBLANK($A502),"",INDEX(Array_ElectricalCharges,MATCH($A502,List_ElectricityMeters,0),ROUNDUP(COLUMN()/3,0)-2)) | AK502: =IF(ISBLANK($A502),"",INDEX(Array_ElectricalCharges,MATCH($A502,List_ElectricityMeters,0),ROUNDUP(COLUMN()/3,0)-2)) | AN502: =IF(ISBLANK($A502),"",INDEX(Array_ElectricalCharges,MATCH($A502,List_ElectricityMeters,0),ROUNDUP(COLUMN()/3,0)-2)) | AQ502: =IF(ISBLANK($A502),"",INDEX(Array_ElectricalCharges,MATCH($A502,List_ElectricityMeters,0),ROUNDUP(COLUMN()/3,0)-2)) | AT502: =IF(ISBLANK($A502),"",INDEX(Array_ElectricalCharges,MATCH($A502,List_ElectricityMeters,0),ROUNDUP(COLUMN()/3,0)-2)) | AW502: =IF(ISBLANK($A502),"",INDEX(Array_ElectricalCharges,MATCH($A502,List_ElectricityMeters,0),ROUNDUP(COLUMN()/3,0)-2))

Sheet HIDE_ELEC
A1: Agreement Type | B1: Calendarize Options | C1: Usage Units | D1: Demand Units | E1: Charge Types | J1: Other Settings | K1: Value
A2: Grid Electricity | B2: Yes | C2: kWh | D2: kW | E2: Consumption | J2: Source | K2: Electricity
A3: Other Non-RE Electricity | B3: No | C3: MWh | D3: kVA | E3: Demand | J3: Scope | K3: Scope 2: Purchased Electricity
A4: Utility Green Product | B4: Evenly Distribute | C4: MMBtu | D4: MW | E4: Tax | J4: Max Allowed Charges | K4: 16
A5: Onsite Renewable Energy | C5: GJ | D5: MVA | E5: Late Fee
A6: Direct Delivered Physical Power Purchase Agreement (P-PPA) | C6: MJ | E6: Flat Fee
A7: Grid Delivered Physical Power Purchase Agreement (P-PPA) | C7: kJ | E7: Other | J7: REACTIVE TABLE
A8: Virtual Power Purchase Agreement | C8: Therms
A9: Unbundled RECs | C9: DTherms | J9: FIXED LIST
C10: kcal
A15: Charge count: | B15: =COUNTIF(B17:B116,"?*") -> 0 | C15: =COUNTIF(C17:C116,"?*") -> 0 | D15: =COUNTIF(D17:D116,"?*") -> 0 | E15: =COUNTIF(E17:E116,"?*") -> 0 | F15: =COUNTIF(F17:F116,"?*") -> 0 | G15: =COUNTIF(G17:G116,"?*") -> 0 | H15: =COUNTIF(H17:H116,"?*") -> 0 | I15: =COUNTIF(I17:I116,"?*") -> 0 | ... P15: =COUNTIF(P17:P116,"?*") -> 0
A16: Meter Numbers | B16: Charge 1 | C16: Charge 2 | D16: Charge 3 | E16: Charge 4 | F16: Charge 5 | G16: Charge 6 | H16: Charge 7 | I16: Charge 8 | J16: Charge 9 | K16: Charge 10 | L16: Charge 11 | M16: Charge 12 | N16: Charge 13 | O16: Charge 14 | P16: Charge 15
A17: =IF('Electricity Meters'!B3="",A16,'Electricity Meters'!B3) -> Meter Numbers | B17: =IF(ISBLANK(INDEX(Array_ElectricalChargeData,ROW()-16,COLUMN()*2-3)),"",INDEX(Array_ElectricalChargeData,ROW()-16,COLUMN()*2-3)) | C17: =IF(ISBLANK(INDEX(Array_ElectricalChargeData,ROW()-16,COLUMN()*2-3)),"",INDEX(Array_ElectricalChargeData,ROW()-16,COLUMN()*2-3)) | D17: =IF(ISBLANK(INDEX(Array_ElectricalChargeData,ROW()-16,COLUMN()*2-3)),"",INDEX(Array_ElectricalChargeData,ROW()-16,COLUMN()*2-3)) | E17: =IF(ISBLANK(INDEX(Array_ElectricalChargeData,ROW()-16,COLUMN()*2-3)),"",INDEX(Array_ElectricalChargeData,ROW()-16,COLUMN()*2-3)) | F17: =IF(ISBLANK(INDEX(Array_ElectricalChargeData,ROW()-16,COLUMN()*2-3)),"",INDEX(Array_ElectricalChargeData,ROW()-16,COLUMN()*2-3)) | G17: =IF(ISBLANK(INDEX(Array_ElectricalChargeData,ROW()-16,COLUMN()*2-3)),"",INDEX(Array_ElectricalChargeData,ROW()-16,COLUMN()*2-3)) | H17: =IF(ISBLANK(INDEX(Array_ElectricalChargeData,ROW()-16,COLUMN()*2-3)),"",INDEX(Array_ElectricalChargeData,ROW()-16,COLUMN()*2-3)) | I17: =IF(ISBLANK(INDEX(Array_ElectricalChargeData,ROW()-16,COLUMN()*2-3)),"",INDEX(Array_ElectricalChargeData,ROW()-16,COLUMN()*2-3)) | ... P17: =IF(ISBLANK(INDEX(Array_ElectricalChargeData,ROW()-16,COLUMN()*2-3)),"",INDEX(Array_ElectricalChargeData,ROW()-16,COLUMN()*2-3))
A18: =IF('Electricity Meters'!B4="",A17,'Electricity Meters'!B4) -> Meter Numbers | B18: =IF(ISBLANK(INDEX(Array_ElectricalChargeData,ROW()-16,COLUMN()*2-3)),"",INDEX(Array_ElectricalChargeData,ROW()-16,COLUMN()*2-3)) | C18: =IF(ISBLANK(INDEX(Array_ElectricalChargeData,ROW()-16,COLUMN()*2-3)),"",INDEX(Array_ElectricalChargeData,ROW()-16,COLUMN()*2-3)) | D18: =IF(ISBLANK(INDEX(Array_ElectricalChargeData,ROW()-16,COLUMN()*2-3)),"",INDEX(Array_ElectricalChargeData,ROW()-16,COLUMN()*2-3)) | E18: =IF(ISBLANK(INDEX(Array_ElectricalChargeData,ROW()-16,COLUMN()*2-3)),"",INDEX(Array_ElectricalChargeData,ROW()-16,COLUMN()*2-3)) | F18: =IF(ISBLANK(INDEX(Array_ElectricalChargeData,ROW()-16,COLUMN()*2-3)),"",INDEX(Array_ElectricalChargeData,ROW()-16,COLUMN()*2-3)) | G18: =IF(ISBLANK(INDEX(Array_ElectricalChargeData,ROW()-16,COLUMN()*2-3)),"",INDEX(Array_ElectricalChargeData,ROW()-16,COLUMN()*2-3)) | H18: =IF(ISBLANK(INDEX(Array_ElectricalChargeData,ROW()-16,COLUMN()*2-3)),"",INDEX(Array_ElectricalChargeData,ROW()-16,COLUMN()*2-3)) | I18: =IF(ISBLANK(INDEX(Array_ElectricalChargeData,ROW()-16,COLUMN()*2-3)),"",INDEX(Array_ElectricalChargeData,ROW()-16,COLUMN()*2-3)) | ... P18: =IF(ISBLANK(INDEX(Array_ElectricalChargeData,ROW()-16,COLUMN()*2-3)),"",INDEX(Array_ElectricalChargeData,ROW()-16,COLUMN()*2-3))
A19: =IF('Electricity Meters'!B5="",A18,'Electricity Meters'!B5) -> Meter Numbers | B19: =IF(ISBLANK(INDEX(Array_ElectricalChargeData,ROW()-16,COLUMN()*2-3)),"",INDEX(Array_ElectricalChargeData,ROW()-16,COLUMN()*2-3)) | C19: =IF(ISBLANK(INDEX(Array_ElectricalChargeData,ROW()-16,COLUMN()*2-3)),"",INDEX(Array_ElectricalChargeData,ROW()-16,COLUMN()*2-3)) | D19: =IF(ISBLANK(INDEX(Array_ElectricalChargeData,ROW()-16,COLUMN()*2-3)),"",INDEX(Array_ElectricalChargeData,ROW()-16,COLUMN()*2-3)) | E19: =IF(ISBLANK(INDEX(Array_ElectricalChargeData,ROW()-16,COLUMN()*2-3)),"",INDEX(Array_ElectricalChargeData,ROW()-16,COLUMN()*2-3)) | F19: =IF(ISBLANK(INDEX(Array_ElectricalChargeData,ROW()-16,COLUMN()*2-3)),"",INDEX(Array_ElectricalChargeData,ROW()-16,COLUMN()*2-3)) | G19: =IF(ISBLANK(INDEX(Array_ElectricalChargeData,ROW()-16,COLUMN()*2-3)),"",INDEX(Array_ElectricalChargeData,ROW()-16,COLUMN()*2-3)) | H19: =IF(ISBLANK(INDEX(Array_ElectricalChargeData,ROW()-16,COLUMN()*2-3)),"",INDEX(Array_ElectricalChargeData,ROW()-16,COLUMN()*2-3)) | I19: =IF(ISBLANK(INDEX(Array_ElectricalChargeData,ROW()-16,COLUMN()*2-3)),"",INDEX(Array_ElectricalChargeData,ROW()-16,COLUMN()*2-3)) | ... P19: =IF(ISBLANK(INDEX(Array_ElectricalChargeData,ROW()-16,COLUMN()*2-3)),"",INDEX(Array_ElectricalChargeData,ROW()-16,COLUMN()*2-3))
A20: =IF('Electricity Meters'!B6="",A19,'Electricity Meters'!B6) -> Meter Numbers | B20: =IF(ISBLANK(INDEX(Array_ElectricalChargeData,ROW()-16,COLUMN()*2-3)),"",INDEX(Array_ElectricalChargeData,ROW()-16,COLUMN()*2-3)) | C20: =IF(ISBLANK(INDEX(Array_ElectricalChargeData,ROW()-16,COLUMN()*2-3)),"",INDEX(Array_ElectricalChargeData,ROW()-16,COLUMN()*2-3)) | D20: =IF(ISBLANK(INDEX(Array_ElectricalChargeData,ROW()-16,COLUMN()*2-3)),"",INDEX(Array_ElectricalChargeData,ROW()-16,COLUMN()*2-3)) | E20: =IF(ISBLANK(INDEX(Array_ElectricalChargeData,ROW()-16,COLUMN()*2-3)),"",INDEX(Array_ElectricalChargeData,ROW()-16,COLUMN()*2-3)) | F20: =IF(ISBLANK(INDEX(Array_ElectricalChargeData,ROW()-16,COLUMN()*2-3)),"",INDEX(Array_ElectricalChargeData,ROW()-16,COLUMN()*2-3)) | G20: =IF(ISBLANK(INDEX(Array_ElectricalChargeData,ROW()-16,COLUMN()*2-3)),"",INDEX(Array_ElectricalChargeData,ROW()-16,COLUMN()*2-3)) | H20: =IF(ISBLANK(INDEX(Array_ElectricalChargeData,ROW()-16,COLUMN()*2-3)),"",INDEX(Array_ElectricalChargeData,ROW()-16,COLUMN()*2-3)) | I20: =IF(ISBLANK(INDEX(Array_ElectricalChargeData,ROW()-16,COLUMN()*2-3)),"",INDEX(Array_ElectricalChargeData,ROW()-16,COLUMN()*2-3)) | ... P20: =IF(ISBLANK(INDEX(Array_ElectricalChargeData,ROW()-16,COLUMN()*2-3)),"",INDEX(Array_ElectricalChargeData,ROW()-16,COLUMN()*2-3))
A21: =IF('Electricity Meters'!B7="",A20,'Electricity Meters'!B7) -> Meter Numbers | B21: =IF(ISBLANK(INDEX(Array_ElectricalChargeData,ROW()-16,COLUMN()*2-3)),"",INDEX(Array_ElectricalChargeData,ROW()-16,COLUMN()*2-3)) | C21: =IF(ISBLANK(INDEX(Array_ElectricalChargeData,ROW()-16,COLUMN()*2-3)),"",INDEX(Array_ElectricalChargeData,ROW()-16,COLUMN()*2-3)) | D21: =IF(ISBLANK(INDEX(Array_ElectricalChargeData,ROW()-16,COLUMN()*2-3)),"",INDEX(Array_ElectricalChargeData,ROW()-16,COLUMN()*2-3)) | E21: =IF(ISBLANK(INDEX(Array_ElectricalChargeData,ROW()-16,COLUMN()*2-3)),"",INDEX(Array_ElectricalChargeData,ROW()-16,COLUMN()*2-3)) | F21: =IF(ISBLANK(INDEX(Array_ElectricalChargeData,ROW()-16,COLUMN()*2-3)),"",INDEX(Array_ElectricalChargeData,ROW()-16,COLUMN()*2-3)) | G21: =IF(ISBLANK(INDEX(Array_ElectricalChargeData,ROW()-16,COLUMN()*2-3)),"",INDEX(Array_ElectricalChargeData,ROW()-16,COLUMN()*2-3)) | H21: =IF(ISBLANK(INDEX(Array_ElectricalChargeData,ROW()-16,COLUMN()*2-3)),"",INDEX(Array_ElectricalChargeData,ROW()-16,COLUMN()*2-3)) | I21: =IF(ISBLANK(INDEX(Array_ElectricalChargeData,ROW()-16,COLUMN()*2-3)),"",INDEX(Array_ElectricalChargeData,ROW()-16,COLUMN()*2-3)) | ... P21: =IF(ISBLANK(INDEX(Array_ElectricalChargeData,ROW()-16,COLUMN()*2-3)),"",INDEX(Array_ElectricalChargeData,ROW()-16,COLUMN()*2-3))
A22: =IF('Electricity Meters'!B8="",A21,'Electricity Meters'!B8) -> Meter Numbers | B22: =IF(ISBLANK(INDEX(Array_ElectricalChargeData,ROW()-16,COLUMN()*2-3)),"",INDEX(Array_ElectricalChargeData,ROW()-16,COLUMN()*2-3)) | C22: =IF(ISBLANK(INDEX(Array_ElectricalChargeData,ROW()-16,COLUMN()*2-3)),"",INDEX(Array_ElectricalChargeData,ROW()-16,COLUMN()*2-3)) | D22: =IF(ISBLANK(INDEX(Array_ElectricalChargeData,ROW()-16,COLUMN()*2-3)),"",INDEX(Array_ElectricalChargeData,ROW()-16,COLUMN()*2-3)) | E22: =IF(ISBLANK(INDEX(Array_ElectricalChargeData,ROW()-16,COLUMN()*2-3)),"",INDEX(Array_ElectricalChargeData,ROW()-16,COLUMN()*2-3)) | F22: =IF(ISBLANK(INDEX(Array_ElectricalChargeData,ROW()-16,COLUMN()*2-3)),"",INDEX(Array_ElectricalChargeData,ROW()-16,COLUMN()*2-3)) | G22: =IF(ISBLANK(INDEX(Array_ElectricalChargeData,ROW()-16,COLUMN()*2-3)),"",INDEX(Array_ElectricalChargeData,ROW()-16,COLUMN()*2-3)) | H22: =IF(ISBLANK(INDEX(Array_ElectricalChargeData,ROW()-16,COLUMN()*2-3)),"",INDEX(Array_ElectricalChargeData,ROW()-16,COLUMN()*2-3)) | I22: =IF(ISBLANK(INDEX(Array_ElectricalChargeData,ROW()-16,COLUMN()*2-3)),"",INDEX(Array_ElectricalChargeData,ROW()-16,COLUMN()*2-3)) | ... P22: =IF(ISBLANK(INDEX(Array_ElectricalChargeData,ROW()-16,COLUMN()*2-3)),"",INDEX(Array_ElectricalChargeData,ROW()-16,COLUMN()*2-3))
A23: =IF('Electricity Meters'!B9="",A22,'Electricity Meters'!B9) -> Meter Numbers | B23: =IF(ISBLANK(INDEX(Array_ElectricalChargeData,ROW()-16,COLUMN()*2-3)),"",INDEX(Array_ElectricalChargeData,ROW()-16,COLUMN()*2-3)) | C23: =IF(ISBLANK(INDEX(Array_ElectricalChargeData,ROW()-16,COLUMN()*2-3)),"",INDEX(Array_ElectricalChargeData,ROW()-16,COLUMN()*2-3)) | D23: =IF(ISBLANK(INDEX(Array_ElectricalChargeData,ROW()-16,COLUMN()*2-3)),"",INDEX(Array_ElectricalChargeData,ROW()-16,COLUMN()*2-3)) | E23: =IF(ISBLANK(INDEX(Array_ElectricalChargeData,ROW()-16,COLUMN()*2-3)),"",INDEX(Array_ElectricalChargeData,ROW()-16,COLUMN()*2-3)) | F23: =IF(ISBLANK(INDEX(Array_ElectricalChargeData,ROW()-16,COLUMN()*2-3)),"",INDEX(Array_ElectricalChargeData,ROW()-16,COLUMN()*2-3)) | G23: =IF(ISBLANK(INDEX(Array_ElectricalChargeData,ROW()-16,COLUMN()*2-3)),"",INDEX(Array_ElectricalChargeData,ROW()-16,COLUMN()*2-3)) | H23: =IF(ISBLANK(INDEX(Array_ElectricalChargeData,ROW()-16,COLUMN()*2-3)),"",INDEX(Array_ElectricalChargeData,ROW()-16,COLUMN()*2-3)) | I23: =IF(ISBLANK(INDEX(Array_ElectricalChargeData,ROW()-16,COLUMN()*2-3)),"",INDEX(Array_ElectricalChargeData,ROW()-16,COLUMN()*2-3)) | ... P23: =IF(ISBLANK(INDEX(Array_ElectricalChargeData,ROW()-16,COLUMN()*2-3)),"",INDEX(Array_ElectricalChargeData,ROW()-16,COLUMN()*2-3))
A24: =IF('Electricity Meters'!B10="",A23,'Electricity Meters'!B10) -> Meter Numbers | B24: =IF(ISBLANK(INDEX(Array_ElectricalChargeData,ROW()-16,COLUMN()*2-3)),"",INDEX(Array_ElectricalChargeData,ROW()-16,COLUMN()*2-3)) | C24: =IF(ISBLANK(INDEX(Array_ElectricalChargeData,ROW()-16,COLUMN()*2-3)),"",INDEX(Array_ElectricalChargeData,ROW()-16,COLUMN()*2-3)) | D24: =IF(ISBLANK(INDEX(Array_ElectricalChargeData,ROW()-16,COLUMN()*2-3)),"",INDEX(Array_ElectricalChargeData,ROW()-16,COLUMN()*2-3)) | E24: =IF(ISBLANK(INDEX(Array_ElectricalChargeData,ROW()-16,COLUMN()*2-3)),"",INDEX(Array_ElectricalChargeData,ROW()-16,COLUMN()*2-3)) | F24: =IF(ISBLANK(INDEX(Array_ElectricalChargeData,ROW()-16,COLUMN()*2-3)),"",INDEX(Array_ElectricalChargeData,ROW()-16,COLUMN()*2-3)) | G24: =IF(ISBLANK(INDEX(Array_ElectricalChargeData,ROW()-16,COLUMN()*2-3)),"",INDEX(Array_ElectricalChargeData,ROW()-16,COLUMN()*2-3)) | H24: =IF(ISBLANK(INDEX(Array_ElectricalChargeData,ROW()-16,COLUMN()*2-3)),"",INDEX(Array_ElectricalChargeData,ROW()-16,COLUMN()*2-3)) | I24: =IF(ISBLANK(INDEX(Array_ElectricalChargeData,ROW()-16,COLUMN()*2-3)),"",INDEX(Array_ElectricalChargeData,ROW()-16,COLUMN()*2-3)) | ... P24: =IF(ISBLANK(INDEX(Array_ElectricalChargeData,ROW()-16,COLUMN()*2-3)),"",INDEX(Array_ElectricalChargeData,ROW()-16,COLUMN()*2-3))
A25: =IF('Electricity Meters'!B11="",A24,'Electricity Meters'!B11) -> Meter Numbers | B25: =IF(ISBLANK(INDEX(Array_ElectricalChargeData,ROW()-16,COLUMN()*2-3)),"",INDEX(Array_ElectricalChargeData,ROW()-16,COLUMN()*2-3)) | C25: =IF(ISBLANK(INDEX(Array_ElectricalChargeData,ROW()-16,COLUMN()*2-3)),"",INDEX(Array_ElectricalChargeData,ROW()-16,COLUMN()*2-3)) | D25: =IF(ISBLANK(INDEX(Array_ElectricalChargeData,ROW()-16,COLUMN()*2-3)),"",INDEX(Array_ElectricalChargeData,ROW()-16,COLUMN()*2-3)) | E25: =IF(ISBLANK(INDEX(Array_ElectricalChargeData,ROW()-16,COLUMN()*2-3)),"",INDEX(Array_ElectricalChargeData,ROW()-16,COLUMN()*2-3)) | F25: =IF(ISBLANK(INDEX(Array_ElectricalChargeData,ROW()-16,COLUMN()*2-3)),"",INDEX(Array_ElectricalChargeData,ROW()-16,COLUMN()*2-3)) | G25: =IF(ISBLANK(INDEX(Array_ElectricalChargeData,ROW()-16,COLUMN()*2-3)),"",INDEX(Array_ElectricalChargeData,ROW()-16,COLUMN()*2-3)) | H25: =IF(ISBLANK(INDEX(Array_ElectricalChargeData,ROW()-16,COLUMN()*2-3)),"",INDEX(Array_ElectricalChargeData,ROW()-16,COLUMN()*2-3)) | I25: =IF(ISBLANK(INDEX(Array_ElectricalChargeData,ROW()-16,COLUMN()*2-3)),"",INDEX(Array_ElectricalChargeData,ROW()-16,COLUMN()*2-3)) | ... P25: =IF(ISBLANK(INDEX(Array_ElectricalChargeData,ROW()-16,COLUMN()*2-3)),"",INDEX(Array_ElectricalChargeData,ROW()-16,COLUMN()*2-3))
A26: =IF('Electricity Meters'!B12="",A25,'Electricity Meters'!B12) -> Meter Numbers | B26: =IF(ISBLANK(INDEX(Array_ElectricalChargeData,ROW()-16,COLUMN()*2-3)),"",INDEX(Array_ElectricalChargeData,ROW()-16,COLUMN()*2-3)) | C26: =IF(ISBLANK(INDEX(Array_ElectricalChargeData,ROW()-16,COLUMN()*2-3)),"",INDEX(Array_ElectricalChargeData,ROW()-16,COLUMN()*2-3)) | D26: =IF(ISBLANK(INDEX(Array_ElectricalChargeData,ROW()-16,COLUMN()*2-3)),"",INDEX(Array_ElectricalChargeData,ROW()-16,COLUMN()*2-3)) | E26: =IF(ISBLANK(INDEX(Array_ElectricalChargeData,ROW()-16,COLUMN()*2-3)),"",INDEX(Array_ElectricalChargeData,ROW()-16,COLUMN()*2-3)) | F26: =IF(ISBLANK(INDEX(Array_ElectricalChargeData,ROW()-16,COLUMN()*2-3)),"",INDEX(Array_ElectricalChargeData,ROW()-16,COLUMN()*2-3)) | G26: =IF(ISBLANK(INDEX(Array_ElectricalChargeData,ROW()-16,COLUMN()*2-3)),"",INDEX(Array_ElectricalChargeData,ROW()-16,COLUMN()*2-3)) | H26: =IF(ISBLANK(INDEX(Array_ElectricalChargeData,ROW()-16,COLUMN()*2-3)),"",INDEX(Array_ElectricalChargeData,ROW()-16,COLUMN()*2-3)) | I26: =IF(ISBLANK(INDEX(Array_ElectricalChargeData,ROW()-16,COLUMN()*2-3)),"",INDEX(Array_ElectricalChargeData,ROW()-16,COLUMN()*2-3)) | ... P26: =IF(ISBLANK(INDEX(Array_ElectricalChargeData,ROW()-16,COLUMN()*2-3)),"",INDEX(Array_ElectricalChargeData,ROW()-16,COLUMN()*2-3))
A27: =IF('Electricity Meters'!B13="",A26,'Electricity Meters'!B13) -> Meter Numbers | B27: =IF(ISBLANK(INDEX(Array_ElectricalChargeData,ROW()-16,COLUMN()*2-3)),"",INDEX(Array_ElectricalChargeData,ROW()-16,COLUMN()*2-3)) | C27: =IF(ISBLANK(INDEX(Array_ElectricalChargeData,ROW()-16,COLUMN()*2-3)),"",INDEX(Array_ElectricalChargeData,ROW()-16,COLUMN()*2-3)) | D27: =IF(ISBLANK(INDEX(Array_ElectricalChargeData,ROW()-16,COLUMN()*2-3)),"",INDEX(Array_ElectricalChargeData,ROW()-16,COLUMN()*2-3)) | E27: =IF(ISBLANK(INDEX(Array_ElectricalChargeData,ROW()-16,COLUMN()*2-3)),"",INDEX(Array_ElectricalChargeData,ROW()-16,COLUMN()*2-3)) | F27: =IF(ISBLANK(INDEX(Array_ElectricalChargeData,ROW()-16,COLUMN()*2-3)),"",INDEX(Array_ElectricalChargeData,ROW()-16,COLUMN()*2-3)) | G27: =IF(ISBLANK(INDEX(Array_ElectricalChargeData,ROW()-16,COLUMN()*2-3)),"",INDEX(Array_ElectricalChargeData,ROW()-16,COLUMN()*2-3)) | H27: =IF(ISBLANK(INDEX(Array_ElectricalChargeData,ROW()-16,COLUMN()*2-3)),"",INDEX(Array_ElectricalChargeData,ROW()-16,COLUMN()*2-3)) | I27: =IF(ISBLANK(INDEX(Array_ElectricalChargeData,ROW()-16,COLUMN()*2-3)),"",INDEX(Array_ElectricalChargeData,ROW()-16,COLUMN()*2-3)) | ... P27: =IF(ISBLANK(INDEX(Array_ElectricalChargeData,ROW()-16,COLUMN()*2-3)),"",INDEX(Array_ElectricalChargeData,ROW()-16,COLUMN()*2-3))
A28: =IF('Electricity Meters'!B14="",A27,'Electricity Meters'!B14) -> Meter Numbers | B28: =IF(ISBLANK(INDEX(Array_ElectricalChargeData,ROW()-16,COLUMN()*2-3)),"",INDEX(Array_ElectricalChargeData,ROW()-16,COLUMN()*2-3)) | C28: =IF(ISBLANK(INDEX(Array_ElectricalChargeData,ROW()-16,COLUMN()*2-3)),"",INDEX(Array_ElectricalChargeData,ROW()-16,COLUMN()*2-3)) | D28: =IF(ISBLANK(INDEX(Array_ElectricalChargeData,ROW()-16,COLUMN()*2-3)),"",INDEX(Array_ElectricalChargeData,ROW()-16,COLUMN()*2-3)) | E28: =IF(ISBLANK(INDEX(Array_ElectricalChargeData,ROW()-16,COLUMN()*2-3)),"",INDEX(Array_ElectricalChargeData,ROW()-16,COLUMN()*2-3)) | F28: =IF(ISBLANK(INDEX(Array_ElectricalChargeData,ROW()-16,COLUMN()*2-3)),"",INDEX(Array_ElectricalChargeData,ROW()-16,COLUMN()*2-3)) | G28: =IF(ISBLANK(INDEX(Array_ElectricalChargeData,ROW()-16,COLUMN()*2-3)),"",INDEX(Array_ElectricalChargeData,ROW()-16,COLUMN()*2-3)) | H28: =IF(ISBLANK(INDEX(Array_ElectricalChargeData,ROW()-16,COLUMN()*2-3)),"",INDEX(Array_ElectricalChargeData,ROW()-16,COLUMN()*2-3)) | I28: =IF(ISBLANK(INDEX(Array_ElectricalChargeData,ROW()-16,COLUMN()*2-3)),"",INDEX(Array_ElectricalChargeData,ROW()-16,COLUMN()*2-3)) | ... P28: =IF(ISBLANK(INDEX(Array_ElectricalChargeData,ROW()-16,COLUMN()*2-3)),"",INDEX(Array_ElectricalChargeData,ROW()-16,COLUMN()*2-3))
... A216: =IF('Electricity Meters'!B202="",A215,'Electricity Meters'!B202) -> Meter Numbers | B216: =IF(ISBLANK(INDEX(Array_ElectricalChargeData,ROW()-16,COLUMN()*2-3)),"",INDEX(Array_ElectricalChargeData,ROW()-16,COLUMN()*2-3)) | C216: =IF(ISBLANK(INDEX(Array_ElectricalChargeData,ROW()-16,COLUMN()*2-3)),"",INDEX(Array_ElectricalChargeData,ROW()-16,COLUMN()*2-3)) | D216: =IF(ISBLANK(INDEX(Array_ElectricalChargeData,ROW()-16,COLUMN()*2-3)),"",INDEX(Array_ElectricalChargeData,ROW()-16,COLUMN()*2-3)) | E216: =IF(ISBLANK(INDEX(Array_ElectricalChargeData,ROW()-16,COLUMN()*2-3)),"",INDEX(Array_ElectricalChargeData,ROW()-16,COLUMN()*2-3)) | F216: =IF(ISBLANK(INDEX(Array_ElectricalChargeData,ROW()-16,COLUMN()*2-3)),"",INDEX(Array_ElectricalChargeData,ROW()-16,COLUMN()*2-3)) | G216: =IF(ISBLANK(INDEX(Array_ElectricalChargeData,ROW()-16,COLUMN()*2-3)),"",INDEX(Array_ElectricalChargeData,ROW()-16,COLUMN()*2-3)) | H216: =IF(ISBLANK(INDEX(Array_ElectricalChargeData,ROW()-16,COLUMN()*2-3)),"",INDEX(Array_ElectricalChargeData,ROW()-16,COLUMN()*2-3)) | I216: =IF(ISBLANK(INDEX(Array_ElectricalChargeData,ROW()-16,COLUMN()*2-3)),"",INDEX(Array_ElectricalChargeData,ROW()-16,COLUMN()*2-3)) | ... P216: =IF(ISBLANK(INDEX(Array_ElectricalChargeData,ROW()-16,COLUMN()*2-3)),"",INDEX(Array_ElectricalChargeData,ROW()-16,COLUMN()*2-3))

Sheet Stationary Fuel Meters
A1: √ Stationary Fuel Meters Setup | P1: √ Stationary Fuel Charge Setup (Optional)
A2: Facility Name | B2: Meter Number (UNIQUE) | C2: Meter Name (DISPLAY) | D2: Meter Group (ANALYSIS) | E2: Calendarize Readings? | F2: Phase | G2: Fuel | H2: Unit (COLLECTION) | I2: S2S Factor | J2: Energy Factor (HHV) | K2: Unit (ENERGY) | L2: Account # | M2: Supplier | N2: Location | O2: Notes | P2: ="Charge "&QUOTIENT(COLUMN()-14,2)&" Name" -> Charge 1 Name | Q2: ="Charge "&QUOTIENT(COLUMN()-14,2)&" Type" -> Charge 1 Type | R2: ="Charge "&QUOTIENT(COLUMN()-14,2)&" Name" -> Charge 2 Name | S2: ="Charge "&QUOTIENT(COLUMN()-14,2)&" Type" -> Charge 2 Type | T2: ="Charge "&QUOTIENT(COLUMN()-14,2)&" Name" -> Charge 3 Name | U2: ="Charge "&QUOTIENT(COLUMN()-14,2)&" Type" -> Charge 3 Type | V2: ="Charge "&QUOTIENT(COLUMN()-14,2)&" Name" -> Charge 4 Name | W2: ="Charge "&QUOTIENT(COLUMN()-14,2)&" Type" -> Charge 4 Type | X2: ="Charge "&QUOTIENT(COLUMN()-14,2)&" Name" -> Charge 5 Name | Y2: ="Charge "&QUOTIENT(COLUMN()-14,2)&" Type" -> Charge 5 Type | Z2: ="Charge "&QUOTIENT(COLUMN()-14,2)&" Name" -> Charge 6 Name | AA2: ="Charge "&QUOTIENT(COLUMN()-14,2)&" Type" -> Charge 6 Type | AB2: ="Charge "&QUOTIENT(COLUMN()-14,2)&" Name" -> Charge 7 Name | AC2: ="Charge "&QUOTIENT(COLUMN()-14,2)&" Type" -> Charge 7 Type | AD2: ="Charge "&QUOTIENT(COLUMN()-14,2)&" Name" -> Charge 8 Name | AE2: ="Charge "&QUOTIENT(COLUMN()-14,2)&" Type" -> Charge 8 Type | AF2: ="Charge "&QUOTIENT(COLUMN()-14,2)&" Name" -> Charge 9 Name | AG2: ="Charge "&QUOTIENT(COLUMN()-14,2)&" Type" -> Charge 9 Type | AH2: ="Charge "&QUOTIENT(COLUMN()-14,2)&" Name" -> Charge 10 Name | AI2: ="Charge "&QUOTIENT(COLUMN()-14,2)&" Type" -> Charge 10 Type | AJ2: ="Charge "&QUOTIENT(COLUMN()-14,2)&" Name" -> Charge 11 Name | AK2: ="Charge "&QUOTIENT(COLUMN()-14,2)&" Type" -> Charge 11 Type | AL2: ="Charge "&QUOTIENT(COLUMN()-14,2)&" Name" -> Charge 12 Name | AM2: ="Charge "&QUOTIENT(COLUMN()-14,2)&" Type" -> Charge 12 Type | AN2: ="Charge "&QUOTIENT(COLUMN()-14,2)&" Name" -> Charge 13 Name | AO2: ="Charge "&QUOTIENT(COLUMN()-14,2)&" Type" -> Charge 13 Type | AP2: ="Charge "&QUOTIENT(COLUMN()-14,2)&" Name" -> Charge 14 Name | AQ2: ="Charge "&QUOTIENT(COLUMN()-14,2)&" Type" -> Charge 14 Type | AR2: ="Charge "&QUOTIENT(COLUMN()-14,2)&" Name" -> Charge 15 Name | AS2: ="Charge "&QUOTIENT(COLUMN()-14,2)&" Type" -> Charge 15 Type

Sheet Stationary Fuel
A1: √ Stationary Fuel Meter Readings | F1: √ Stationary Fuel Charges (Optional)
A2: Meter Number | B2: Read Date | C2: Total Usage | D2: Total Cost ($) | E2: Higher Heating Value | F2: =IF(INDEX(List_ChargeNumbers_Stationary, 1, ROUNDUP((COLUMN()+1)/3-2,0)) = 0,"",INDEX(List_ChargeNumbers_Stationary, 2, ROUNDUP((COLUMN()+1)/3-2,0))&" Name") | G2: =IF(INDEX(List_ChargeNumbers_Stationary, 1, ROUNDUP((COLUMN()+1)/3-2,0)) = 0,"",INDEX(List_ChargeNumbers_Stationary, 2, ROUNDUP((COLUMN()+1)/3-2,0))&" Reading") | H2: =IF(INDEX(List_ChargeNumbers_Stationary, 1, ROUNDUP((COLUMN()+1)/3-2,0)) = 0,"",INDEX(List_ChargeNumbers_Stationary, 2, ROUNDUP((COLUMN()+1)/3-2,0))&" Cost") | I2: =IF(INDEX(List_ChargeNumbers_Stationary, 1, ROUNDUP((COLUMN()+1)/3-2,0)) = 0,"",INDEX(List_ChargeNumbers_Stationary, 2, ROUNDUP((COLUMN()+1)/3-2,0))&" Name") | J2: =IF(INDEX(List_ChargeNumbers_Stationary, 1, ROUNDUP((COLUMN()+1)/3-2,0)) = 0,"",INDEX(List_ChargeNumbers_Stationary, 2, ROUNDUP((COLUMN()+1)/3-2,0))&" Reading") | K2: =IF(INDEX(List_ChargeNumbers_Stationary, 1, ROUNDUP((COLUMN()+1)/3-2,0)) = 0,"",INDEX(List_ChargeNumbers_Stationary, 2, ROUNDUP((COLUMN()+1)/3-2,0))&" Cost") | L2: =IF(INDEX(List_ChargeNumbers_Stationary, 1, ROUNDUP((COLUMN()+1)/3-2,0)) = 0,"",INDEX(List_ChargeNumbers_Stationary, 2, ROUNDUP((COLUMN()+1)/3-2,0))&" Name") | M2: =IF(INDEX(List_ChargeNumbers_Stationary, 1, ROUNDUP((COLUMN()+1)/3-2,0)) = 0,"",INDEX(List_ChargeNumbers_Stationary, 2, ROUNDUP((COLUMN()+1)/3-2,0))&" Reading") | N2: =IF(INDEX(List_ChargeNumbers_Stationary, 1, ROUNDUP((COLUMN()+1)/3-2,0)) = 0,"",INDEX(List_ChargeNumbers_Stationary, 2, ROUNDUP((COLUMN()+1)/3-2,0))&" Cost") | O2: =IF(INDEX(List_ChargeNumbers_Stationary, 1, ROUNDUP((COLUMN()+1)/3-2,0)) = 0,"",INDEX(List_ChargeNumbers_Stationary, 2, ROUNDUP((COLUMN()+1)/3-2,0))&" Name") | P2: =IF(INDEX(List_ChargeNumbers_Stationary, 1, ROUNDUP((COLUMN()+1)/3-2,0)) = 0,"",INDEX(List_ChargeNumbers_Stationary, 2, ROUNDUP((COLUMN()+1)/3-2,0))&" Reading") | Q2: =IF(INDEX(List_ChargeNumbers_Stationary, 1, ROUNDUP((COLUMN()+1)/3-2,0)) = 0,"",INDEX(List_ChargeNumbers_Stationary, 2, ROUNDUP((COLUMN()+1)/3-2,0))&" Cost") | R2: =IF(INDEX(List_ChargeNumbers_Stationary, 1, ROUNDUP((COLUMN()+1)/3-2,0)) = 0,"",INDEX(List_ChargeNumbers_Stationary, 2, ROUNDUP((COLUMN()+1)/3-2,0))&" Name") | S2: =IF(INDEX(List_ChargeNumbers_Stationary, 1, ROUNDUP((COLUMN()+1)/3-2,0)) = 0,"",INDEX(List_ChargeNumbers_Stationary, 2, ROUNDUP((COLUMN()+1)/3-2,0))&" Reading") | T2: =IF(INDEX(List_ChargeNumbers_Stationary, 1, ROUNDUP((COLUMN()+1)/3-2,0)) = 0,"",INDEX(List_ChargeNumbers_Stationary, 2, ROUNDUP((COLUMN()+1)/3-2,0))&" Cost") | U2: =IF(INDEX(List_ChargeNumbers_Stationary, 1, ROUNDUP((COLUMN()+1)/3-2,0)) = 0,"",INDEX(List_ChargeNumbers_Stationary, 2, ROUNDUP((COLUMN()+1)/3-2,0))&" Name") | V2: =IF(INDEX(List_ChargeNumbers_Stationary, 1, ROUNDUP((COLUMN()+1)/3-2,0)) = 0,"",INDEX(List_ChargeNumbers_Stationary, 2, ROUNDUP((COLUMN()+1)/3-2,0))&" Reading") | W2: =IF(INDEX(List_ChargeNumbers_Stationary, 1, ROUNDUP((COLUMN()+1)/3-2,0)) = 0,"",INDEX(List_ChargeNumbers_Stationary, 2, ROUNDUP((COLUMN()+1)/3-2,0))&" Cost") | X2: =IF(INDEX(List_ChargeNumbers_Stationary, 1, ROUNDUP((COLUMN()+1)/3-2,0)) = 0,"",INDEX(List_ChargeNumbers_Stationary, 2, ROUNDUP((COLUMN()+1)/3-2,0))&" Name") | Y2: =IF(INDEX(List_ChargeNumbers_Stationary, 1, ROUNDUP((COLUMN()+1)/3-2,0)) = 0,"",INDEX(List_ChargeNumbers_Stationary, 2, ROUNDUP((COLUMN()+1)/3-2,0))&" Reading") | Z2: =IF(INDEX(List_ChargeNumbers_Stationary, 1, ROUNDUP((COLUMN()+1)/3-2,0)) = 0,"",INDEX(List_ChargeNumbers_Stationary, 2, ROUNDUP((COLUMN()+1)/3-2,0))&" Cost") | AA2: =IF(INDEX(List_ChargeNumbers_Stationary, 1, ROUNDUP((COLUMN()+1)/3-2,0)) = 0,"",INDEX(List_ChargeNumbers_Stationary, 2, ROUNDUP((COLUMN()+1)/3-2,0))&" Name") | AB2: =IF(INDEX(List_ChargeNumbers_Stationary, 1, ROUNDUP((COLUMN()+1)/3-2,0)) = 0,"",INDEX(List_ChargeNumbers_Stationary, 2, ROUNDUP((COLUMN()+1)/3-2,0))&" Reading") | AC2: =IF(INDEX(List_ChargeNumbers_Stationary, 1, ROUNDUP((COLUMN()+1)/3-2,0)) = 0,"",INDEX(List_ChargeNumbers_Stationary, 2, ROUNDUP((COLUMN()+1)/3-2,0))&" Cost") | AD2: =IF(INDEX(List_ChargeNumbers_Stationary, 1, ROUNDUP((COLUMN()+1)/3-2,0)) = 0,"",INDEX(List_ChargeNumbers_Stationary, 2, ROUNDUP((COLUMN()+1)/3-2,0))&" Name") | AE2: =IF(INDEX(List_ChargeNumbers_Stationary, 1, ROUNDUP((COLUMN()+1)/3-2,0)) = 0,"",INDEX(List_ChargeNumbers_Stationary, 2, ROUNDUP((COLUMN()+1)/3-2,0))&" Reading") | AF2: =IF(INDEX(List_ChargeNumbers_Stationary, 1, ROUNDUP((COLUMN()+1)/3-2,0)) = 0,"",INDEX(List_ChargeNumbers_Stationary, 2, ROUNDUP((COLUMN()+1)/3-2,0))&" Cost") | AG2: =IF(INDEX(List_ChargeNumbers_Stationary, 1, ROUNDUP((COLUMN()+1)/3-2,0)) = 0,"",INDEX(List_ChargeNumbers_Stationary, 2, ROUNDUP((COLUMN()+1)/3-2,0))&" Name") | AH2: =IF(INDEX(List_ChargeNumbers_Stationary, 1, ROUNDUP((COLUMN()+1)/3-2,0)) = 0,"",INDEX(List_ChargeNumbers_Stationary, 2, ROUNDUP((COLUMN()+1)/3-2,0))&" Reading") | AI2: =IF(INDEX(List_ChargeNumbers_Stationary, 1, ROUNDUP((COLUMN()+1)/3-2,0)) = 0,"",INDEX(List_ChargeNumbers_Stationary, 2, ROUNDUP((COLUMN()+1)/3-2,0))&" Cost") | AJ2: =IF(INDEX(List_ChargeNumbers_Stationary, 1, ROUNDUP((COLUMN()+1)/3-2,0)) = 0,"",INDEX(List_ChargeNumbers_Stationary, 2, ROUNDUP((COLUMN()+1)/3-2,0))&" Name") | AK2: =IF(INDEX(List_ChargeNumbers_Stationary, 1, ROUNDUP((COLUMN()+1)/3-2,0)) = 0,"",INDEX(List_ChargeNumbers_Stationary, 2, ROUNDUP((COLUMN()+1)/3-2,0))&" Reading") | AL2: =IF(INDEX(List_ChargeNumbers_Stationary, 1, ROUNDUP((COLUMN()+1)/3-2,0)) = 0,"",INDEX(List_ChargeNumbers_Stationary, 2, ROUNDUP((COLUMN()+1)/3-2,0))&" Cost") | AM2: =IF(INDEX(List_ChargeNumbers_Stationary, 1, ROUNDUP((COLUMN()+1)/3-2,0)) = 0,"",INDEX(List_ChargeNumbers_Stationary, 2, ROUNDUP((COLUMN()+1)/3-2,0))&" Name") | AN2: =IF(INDEX(List_ChargeNumbers_Stationary, 1, ROUNDUP((COLUMN()+1)/3-2,0)) = 0,"",INDEX(List_ChargeNumbers_Stationary, 2, ROUNDUP((COLUMN()+1)/3-2,0))&" Reading") | AO2: =IF(INDEX(List_ChargeNumbers_Stationary, 1, ROUNDUP((COLUMN()+1)/3-2,0)) = 0,"",INDEX(List_ChargeNumbers_Stationary, 2, ROUNDUP((COLUMN()+1)/3-2,0))&" Cost") | AP2: =IF(INDEX(List_ChargeNumbers_Stationary, 1, ROUNDUP((COLUMN()+1)/3-2,0)) = 0,"",INDEX(List_ChargeNumbers_Stationary, 2, ROUNDUP((COLUMN()+1)/3-2,0))&" Name") | AQ2: =IF(INDEX(List_ChargeNumbers_Stationary, 1, ROUNDUP((COLUMN()+1)/3-2,0)) = 0,"",INDEX(List_ChargeNumbers_Stationary, 2, ROUNDUP((COLUMN()+1)/3-2,0))&" Reading") | AR2: =IF(INDEX(List_ChargeNumbers_Stationary, 1, ROUNDUP((COLUMN()+1)/3-2,0)) = 0,"",INDEX(List_ChargeNumbers_Stationary, 2, ROUNDUP((COLUMN()+1)/3-2,0))&" Cost") | AS2: =IF(INDEX(List_ChargeNumbers_Stationary, 1, ROUNDUP((COLUMN()+1)/3-2,0)) = 0,"",INDEX(List_ChargeNumbers_Stationary, 2, ROUNDUP((COLUMN()+1)/3-2,0))&" Name") | AT2: =IF(INDEX(List_ChargeNumbers_Stationary, 1, ROUNDUP((COLUMN()+1)/3-2,0)) = 0,"",INDEX(List_ChargeNumbers_Stationary, 2, ROUNDUP((COLUMN()+1)/3-2,0))&" Reading") | AU2: =IF(INDEX(List_ChargeNumbers_Stationary, 1, ROUNDUP((COLUMN()+1)/3-2,0)) = 0,"",INDEX(List_ChargeNumbers_Stationary, 2, ROUNDUP((COLUMN()+1)/3-2,0))&" Cost") | AV2: =IF(INDEX(List_ChargeNumbers_Stationary, 1, ROUNDUP((COLUMN()+1)/3-2,0)) = 0,"",INDEX(List_ChargeNumbers_Stationary, 2, ROUNDUP((COLUMN()+1)/3-2,0))&" Name") | AW2: =IF(INDEX(List_ChargeNumbers_Stationary, 1, ROUNDUP((COLUMN()+1)/3-2,0)) = 0,"",INDEX(List_ChargeNumbers_Stationary, 2, ROUNDUP((COLUMN()+1)/3-2,0))&" Reading") | AX2: =IF(INDEX(List_ChargeNumbers_Stationary, 1, ROUNDUP((COLUMN()+1)/3-2,0)) = 0,"",INDEX(List_ChargeNumbers_Stationary, 2, ROUNDUP((COLUMN()+1)/3-2,0))&" Cost")
F3: =IFERROR(IF(ISBLANK($A3),"",INDEX(Array_StationaryCharges,MATCH($A3,List_StationaryFuelMeters,0),ROUNDUP((COLUMN()+1)/3-2,0))),"") | I3: =IFERROR(IF(ISBLANK($A3),"",INDEX(Array_StationaryCharges,MATCH($A3,List_StationaryFuelMeters,0),ROUNDUP((COLUMN()+1)/3-2,0))),"") | L3: =IFERROR(IF(ISBLANK($A3),"",INDEX(Array_StationaryCharges,MATCH($A3,List_StationaryFuelMeters,0),ROUNDUP((COLUMN()+1)/3-2,0))),"") | O3: =IFERROR(IF(ISBLANK($A3),"",INDEX(Array_StationaryCharges,MATCH($A3,List_StationaryFuelMeters,0),ROUNDUP((COLUMN()+1)/3-2,0))),"") | R3: =IFERROR(IF(ISBLANK($A3),"",INDEX(Array_StationaryCharges,MATCH($A3,List_StationaryFuelMeters,0),ROUNDUP((COLUMN()+1)/3-2,0))),"") | U3: =IFERROR(IF(ISBLANK($A3),"",INDEX(Array_StationaryCharges,MATCH($A3,List_StationaryFuelMeters,0),ROUNDUP((COLUMN()+1)/3-2,0))),"") | X3: =IFERROR(IF(ISBLANK($A3),"",INDEX(Array_StationaryCharges,MATCH($A3,List_StationaryFuelMeters,0),ROUNDUP((COLUMN()+1)/3-2,0))),"") | AA3: =IFERROR(IF(ISBLANK($A3),"",INDEX(Array_StationaryCharges,MATCH($A3,List_StationaryFuelMeters,0),ROUNDUP((COLUMN()+1)/3-2,0))),"") | AD3: =IFERROR(IF(ISBLANK($A3),"",INDEX(Array_StationaryCharges,MATCH($A3,List_StationaryFuelMeters,0),ROUNDUP((COLUMN()+1)/3-2,0))),"") | AG3: =IFERROR(IF(ISBLANK($A3),"",INDEX(Array_StationaryCharges,MATCH($A3,List_StationaryFuelMeters,0),ROUNDUP((COLUMN()+1)/3-2,0))),"") | AJ3: =IFERROR(IF(ISBLANK($A3),"",INDEX(Array_StationaryCharges,MATCH($A3,List_StationaryFuelMeters,0),ROUNDUP((COLUMN()+1)/3-2,0))),"") | AM3: =IFERROR(IF(ISBLANK($A3),"",INDEX(Array_StationaryCharges,MATCH($A3,List_StationaryFuelMeters,0),ROUNDUP((COLUMN()+1)/3-2,0))),"") | AP3: =IFERROR(IF(ISBLANK($A3),"",INDEX(Array_StationaryCharges,MATCH($A3,List_StationaryFuelMeters,0),ROUNDUP((COLUMN()+1)/3-2,0))),"") | AS3: =IFERROR(IF(ISBLANK($A3),"",INDEX(Array_StationaryCharges,MATCH($A3,List_StationaryFuelMeters,0),ROUNDUP((COLUMN()+1)/3-2,0))),"") | AV3: =IFERROR(IF(ISBLANK($A3),"",INDEX(Array_StationaryCharges,MATCH($A3,List_StationaryFuelMeters,0),ROUNDUP((COLUMN()+1)/3-2,0))),"")
F4: =IFERROR(IF(ISBLANK($A4),"",INDEX(Array_StationaryCharges,MATCH($A4,List_StationaryFuelMeters,0),ROUNDUP((COLUMN()+1)/3-2,0))),"") | I4: =IFERROR(IF(ISBLANK($A4),"",INDEX(Array_StationaryCharges,MATCH($A4,List_StationaryFuelMeters,0),ROUNDUP((COLUMN()+1)/3-2,0))),"") | L4: =IFERROR(IF(ISBLANK($A4),"",INDEX(Array_StationaryCharges,MATCH($A4,List_StationaryFuelMeters,0),ROUNDUP((COLUMN()+1)/3-2,0))),"") | O4: =IFERROR(IF(ISBLANK($A4),"",INDEX(Array_StationaryCharges,MATCH($A4,List_StationaryFuelMeters,0),ROUNDUP((COLUMN()+1)/3-2,0))),"") | R4: =IFERROR(IF(ISBLANK($A4),"",INDEX(Array_StationaryCharges,MATCH($A4,List_StationaryFuelMeters,0),ROUNDUP((COLUMN()+1)/3-2,0))),"") | U4: =IFERROR(IF(ISBLANK($A4),"",INDEX(Array_StationaryCharges,MATCH($A4,List_StationaryFuelMeters,0),ROUNDUP((COLUMN()+1)/3-2,0))),"") | X4: =IFERROR(IF(ISBLANK($A4),"",INDEX(Array_StationaryCharges,MATCH($A4,List_StationaryFuelMeters,0),ROUNDUP((COLUMN()+1)/3-2,0))),"") | AA4: =IFERROR(IF(ISBLANK($A4),"",INDEX(Array_StationaryCharges,MATCH($A4,List_StationaryFuelMeters,0),ROUNDUP((COLUMN()+1)/3-2,0))),"") | AD4: =IFERROR(IF(ISBLANK($A4),"",INDEX(Array_StationaryCharges,MATCH($A4,List_StationaryFuelMeters,0),ROUNDUP((COLUMN()+1)/3-2,0))),"") | AG4: =IFERROR(IF(ISBLANK($A4),"",INDEX(Array_StationaryCharges,MATCH($A4,List_StationaryFuelMeters,0),ROUNDUP((COLUMN()+1)/3-2,0))),"") | AJ4: =IFERROR(IF(ISBLANK($A4),"",INDEX(Array_StationaryCharges,MATCH($A4,List_StationaryFuelMeters,0),ROUNDUP((COLUMN()+1)/3-2,0))),"") | AM4: =IFERROR(IF(ISBLANK($A4),"",INDEX(Array_StationaryCharges,MATCH($A4,List_StationaryFuelMeters,0),ROUNDUP((COLUMN()+1)/3-2,0))),"") | AP4: =IFERROR(IF(ISBLANK($A4),"",INDEX(Array_StationaryCharges,MATCH($A4,List_StationaryFuelMeters,0),ROUNDUP((COLUMN()+1)/3-2,0))),"") | AS4: =IFERROR(IF(ISBLANK($A4),"",INDEX(Array_StationaryCharges,MATCH($A4,List_StationaryFuelMeters,0),ROUNDUP((COLUMN()+1)/3-2,0))),"") | AV4: =IFERROR(IF(ISBLANK($A4),"",INDEX(Array_StationaryCharges,MATCH($A4,List_StationaryFuelMeters,0),ROUNDUP((COLUMN()+1)/3-2,0))),"")
F5: =IFERROR(IF(ISBLANK($A5),"",INDEX(Array_StationaryCharges,MATCH($A5,List_StationaryFuelMeters,0),ROUNDUP((COLUMN()+1)/3-2,0))),"") | I5: =IFERROR(IF(ISBLANK($A5),"",INDEX(Array_StationaryCharges,MATCH($A5,List_StationaryFuelMeters,0),ROUNDUP((COLUMN()+1)/3-2,0))),"") | L5: =IFERROR(IF(ISBLANK($A5),"",INDEX(Array_StationaryCharges,MATCH($A5,List_StationaryFuelMeters,0),ROUNDUP((COLUMN()+1)/3-2,0))),"") | O5: =IFERROR(IF(ISBLANK($A5),"",INDEX(Array_StationaryCharges,MATCH($A5,List_StationaryFuelMeters,0),ROUNDUP((COLUMN()+1)/3-2,0))),"") | R5: =IFERROR(IF(ISBLANK($A5),"",INDEX(Array_StationaryCharges,MATCH($A5,List_StationaryFuelMeters,0),ROUNDUP((COLUMN()+1)/3-2,0))),"") | U5: =IFERROR(IF(ISBLANK($A5),"",INDEX(Array_StationaryCharges,MATCH($A5,List_StationaryFuelMeters,0),ROUNDUP((COLUMN()+1)/3-2,0))),"") | X5: =IFERROR(IF(ISBLANK($A5),"",INDEX(Array_StationaryCharges,MATCH($A5,List_StationaryFuelMeters,0),ROUNDUP((COLUMN()+1)/3-2,0))),"") | AA5: =IFERROR(IF(ISBLANK($A5),"",INDEX(Array_StationaryCharges,MATCH($A5,List_StationaryFuelMeters,0),ROUNDUP((COLUMN()+1)/3-2,0))),"") | AD5: =IFERROR(IF(ISBLANK($A5),"",INDEX(Array_StationaryCharges,MATCH($A5,List_StationaryFuelMeters,0),ROUNDUP((COLUMN()+1)/3-2,0))),"") | AG5: =IFERROR(IF(ISBLANK($A5),"",INDEX(Array_StationaryCharges,MATCH($A5,List_StationaryFuelMeters,0),ROUNDUP((COLUMN()+1)/3-2,0))),"") | AJ5: =IFERROR(IF(ISBLANK($A5),"",INDEX(Array_StationaryCharges,MATCH($A5,List_StationaryFuelMeters,0),ROUNDUP((COLUMN()+1)/3-2,0))),"") | AM5: =IFERROR(IF(ISBLANK($A5),"",INDEX(Array_StationaryCharges,MATCH($A5,List_StationaryFuelMeters,0),ROUNDUP((COLUMN()+1)/3-2,0))),"") | AP5: =IFERROR(IF(ISBLANK($A5),"",INDEX(Array_StationaryCharges,MATCH($A5,List_StationaryFuelMeters,0),ROUNDUP((COLUMN()+1)/3-2,0))),"") | AS5: =IFERROR(IF(ISBLANK($A5),"",INDEX(Array_StationaryCharges,MATCH($A5,List_StationaryFuelMeters,0),ROUNDUP((COLUMN()+1)/3-2,0))),"") | AV5: =IFERROR(IF(ISBLANK($A5),"",INDEX(Array_StationaryCharges,MATCH($A5,List_StationaryFuelMeters,0),ROUNDUP((COLUMN()+1)/3-2,0))),"")
F6: =IFERROR(IF(ISBLANK($A6),"",INDEX(Array_StationaryCharges,MATCH($A6,List_StationaryFuelMeters,0),ROUNDUP((COLUMN()+1)/3-2,0))),"") | I6: =IFERROR(IF(ISBLANK($A6),"",INDEX(Array_StationaryCharges,MATCH($A6,List_StationaryFuelMeters,0),ROUNDUP((COLUMN()+1)/3-2,0))),"") | L6: =IFERROR(IF(ISBLANK($A6),"",INDEX(Array_StationaryCharges,MATCH($A6,List_StationaryFuelMeters,0),ROUNDUP((COLUMN()+1)/3-2,0))),"") | O6: =IFERROR(IF(ISBLANK($A6),"",INDEX(Array_StationaryCharges,MATCH($A6,List_StationaryFuelMeters,0),ROUNDUP((COLUMN()+1)/3-2,0))),"") | R6: =IFERROR(IF(ISBLANK($A6),"",INDEX(Array_StationaryCharges,MATCH($A6,List_StationaryFuelMeters,0),ROUNDUP((COLUMN()+1)/3-2,0))),"") | U6: =IFERROR(IF(ISBLANK($A6),"",INDEX(Array_StationaryCharges,MATCH($A6,List_StationaryFuelMeters,0),ROUNDUP((COLUMN()+1)/3-2,0))),"") | X6: =IFERROR(IF(ISBLANK($A6),"",INDEX(Array_StationaryCharges,MATCH($A6,List_StationaryFuelMeters,0),ROUNDUP((COLUMN()+1)/3-2,0))),"") | AA6: =IFERROR(IF(ISBLANK($A6),"",INDEX(Array_StationaryCharges,MATCH($A6,List_StationaryFuelMeters,0),ROUNDUP((COLUMN()+1)/3-2,0))),"") | AD6: =IFERROR(IF(ISBLANK($A6),"",INDEX(Array_StationaryCharges,MATCH($A6,List_StationaryFuelMeters,0),ROUNDUP((COLUMN()+1)/3-2,0))),"") | AG6: =IFERROR(IF(ISBLANK($A6),"",INDEX(Array_StationaryCharges,MATCH($A6,List_StationaryFuelMeters,0),ROUNDUP((COLUMN()+1)/3-2,0))),"") | AJ6: =IFERROR(IF(ISBLANK($A6),"",INDEX(Array_StationaryCharges,MATCH($A6,List_StationaryFuelMeters,0),ROUNDUP((COLUMN()+1)/3-2,0))),"") | AM6: =IFERROR(IF(ISBLANK($A6),"",INDEX(Array_StationaryCharges,MATCH($A6,List_StationaryFuelMeters,0),ROUNDUP((COLUMN()+1)/3-2,0))),"") | AP6: =IFERROR(IF(ISBLANK($A6),"",INDEX(Array_StationaryCharges,MATCH($A6,List_StationaryFuelMeters,0),ROUNDUP((COLUMN()+1)/3-2,0))),"") | AS6: =IFERROR(IF(ISBLANK($A6),"",INDEX(Array_StationaryCharges,MATCH($A6,List_StationaryFuelMeters,0),ROUNDUP((COLUMN()+1)/3-2,0))),"") | AV6: =IFERROR(IF(ISBLANK($A6),"",INDEX(Array_StationaryCharges,MATCH($A6,List_StationaryFuelMeters,0),ROUNDUP((COLUMN()+1)/3-2,0))),"")
F7: =IFERROR(IF(ISBLANK($A7),"",INDEX(Array_StationaryCharges,MATCH($A7,List_StationaryFuelMeters,0),ROUNDUP((COLUMN()+1)/3-2,0))),"") | I7: =IFERROR(IF(ISBLANK($A7),"",INDEX(Array_StationaryCharges,MATCH($A7,List_StationaryFuelMeters,0),ROUNDUP((COLUMN()+1)/3-2,0))),"") | L7: =IFERROR(IF(ISBLANK($A7),"",INDEX(Array_StationaryCharges,MATCH($A7,List_StationaryFuelMeters,0),ROUNDUP((COLUMN()+1)/3-2,0))),"") | O7: =IFERROR(IF(ISBLANK($A7),"",INDEX(Array_StationaryCharges,MATCH($A7,List_StationaryFuelMeters,0),ROUNDUP((COLUMN()+1)/3-2,0))),"") | R7: =IFERROR(IF(ISBLANK($A7),"",INDEX(Array_StationaryCharges,MATCH($A7,List_StationaryFuelMeters,0),ROUNDUP((COLUMN()+1)/3-2,0))),"") | U7: =IFERROR(IF(ISBLANK($A7),"",INDEX(Array_StationaryCharges,MATCH($A7,List_StationaryFuelMeters,0),ROUNDUP((COLUMN()+1)/3-2,0))),"") | X7: =IFERROR(IF(ISBLANK($A7),"",INDEX(Array_StationaryCharges,MATCH($A7,List_StationaryFuelMeters,0),ROUNDUP((COLUMN()+1)/3-2,0))),"") | AA7: =IFERROR(IF(ISBLANK($A7),"",INDEX(Array_StationaryCharges,MATCH($A7,List_StationaryFuelMeters,0),ROUNDUP((COLUMN()+1)/3-2,0))),"") | AD7: =IFERROR(IF(ISBLANK($A7),"",INDEX(Array_StationaryCharges,MATCH($A7,List_StationaryFuelMeters,0),ROUNDUP((COLUMN()+1)/3-2,0))),"") | AG7: =IFERROR(IF(ISBLANK($A7),"",INDEX(Array_StationaryCharges,MATCH($A7,List_StationaryFuelMeters,0),ROUNDUP((COLUMN()+1)/3-2,0))),"") | AJ7: =IFERROR(IF(ISBLANK($A7),"",INDEX(Array_StationaryCharges,MATCH($A7,List_StationaryFuelMeters,0),ROUNDUP((COLUMN()+1)/3-2,0))),"") | AM7: =IFERROR(IF(ISBLANK($A7),"",INDEX(Array_StationaryCharges,MATCH($A7,List_StationaryFuelMeters,0),ROUNDUP((COLUMN()+1)/3-2,0))),"") | AP7: =IFERROR(IF(ISBLANK($A7),"",INDEX(Array_StationaryCharges,MATCH($A7,List_StationaryFuelMeters,0),ROUNDUP((COLUMN()+1)/3-2,0))),"") | AS7: =IFERROR(IF(ISBLANK($A7),"",INDEX(Array_StationaryCharges,MATCH($A7,List_StationaryFuelMeters,0),ROUNDUP((COLUMN()+1)/3-2,0))),"") | AV7: =IFERROR(IF(ISBLANK($A7),"",INDEX(Array_StationaryCharges,MATCH($A7,List_StationaryFuelMeters,0),ROUNDUP((COLUMN()+1)/3-2,0))),"")
F8: =IFERROR(IF(ISBLANK($A8),"",INDEX(Array_StationaryCharges,MATCH($A8,List_StationaryFuelMeters,0),ROUNDUP((COLUMN()+1)/3-2,0))),"") | I8: =IFERROR(IF(ISBLANK($A8),"",INDEX(Array_StationaryCharges,MATCH($A8,List_StationaryFuelMeters,0),ROUNDUP((COLUMN()+1)/3-2,0))),"") | L8: =IFERROR(IF(ISBLANK($A8),"",INDEX(Array_StationaryCharges,MATCH($A8,List_StationaryFuelMeters,0),ROUNDUP((COLUMN()+1)/3-2,0))),"") | O8: =IFERROR(IF(ISBLANK($A8),"",INDEX(Array_StationaryCharges,MATCH($A8,List_StationaryFuelMeters,0),ROUNDUP((COLUMN()+1)/3-2,0))),"") | R8: =IFERROR(IF(ISBLANK($A8),"",INDEX(Array_StationaryCharges,MATCH($A8,List_StationaryFuelMeters,0),ROUNDUP((COLUMN()+1)/3-2,0))),"") | U8: =IFERROR(IF(ISBLANK($A8),"",INDEX(Array_StationaryCharges,MATCH($A8,List_StationaryFuelMeters,0),ROUNDUP((COLUMN()+1)/3-2,0))),"") | X8: =IFERROR(IF(ISBLANK($A8),"",INDEX(Array_StationaryCharges,MATCH($A8,List_StationaryFuelMeters,0),ROUNDUP((COLUMN()+1)/3-2,0))),"") | AA8: =IFERROR(IF(ISBLANK($A8),"",INDEX(Array_StationaryCharges,MATCH($A8,List_StationaryFuelMeters,0),ROUNDUP((COLUMN()+1)/3-2,0))),"") | AD8: =IFERROR(IF(ISBLANK($A8),"",INDEX(Array_StationaryCharges,MATCH($A8,List_StationaryFuelMeters,0),ROUNDUP((COLUMN()+1)/3-2,0))),"") | AG8: =IFERROR(IF(ISBLANK($A8),"",INDEX(Array_StationaryCharges,MATCH($A8,List_StationaryFuelMeters,0),ROUNDUP((COLUMN()+1)/3-2,0))),"") | AJ8: =IFERROR(IF(ISBLANK($A8),"",INDEX(Array_StationaryCharges,MATCH($A8,List_StationaryFuelMeters,0),ROUNDUP((COLUMN()+1)/3-2,0))),"") | AM8: =IFERROR(IF(ISBLANK($A8),"",INDEX(Array_StationaryCharges,MATCH($A8,List_StationaryFuelMeters,0),ROUNDUP((COLUMN()+1)/3-2,0))),"") | AP8: =IFERROR(IF(ISBLANK($A8),"",INDEX(Array_StationaryCharges,MATCH($A8,List_StationaryFuelMeters,0),ROUNDUP((COLUMN()+1)/3-2,0))),"") | AS8: =IFERROR(IF(ISBLANK($A8),"",INDEX(Array_StationaryCharges,MATCH($A8,List_StationaryFuelMeters,0),ROUNDUP((COLUMN()+1)/3-2,0))),"") | AV8: =IFERROR(IF(ISBLANK($A8),"",INDEX(Array_StationaryCharges,MATCH($A8,List_StationaryFuelMeters,0),ROUNDUP((COLUMN()+1)/3-2,0))),"")
F9: =IFERROR(IF(ISBLANK($A9),"",INDEX(Array_StationaryCharges,MATCH($A9,List_StationaryFuelMeters,0),ROUNDUP((COLUMN()+1)/3-2,0))),"") | I9: =IFERROR(IF(ISBLANK($A9),"",INDEX(Array_StationaryCharges,MATCH($A9,List_StationaryFuelMeters,0),ROUNDUP((COLUMN()+1)/3-2,0))),"") | L9: =IFERROR(IF(ISBLANK($A9),"",INDEX(Array_StationaryCharges,MATCH($A9,List_StationaryFuelMeters,0),ROUNDUP((COLUMN()+1)/3-2,0))),"") | O9: =IFERROR(IF(ISBLANK($A9),"",INDEX(Array_StationaryCharges,MATCH($A9,List_StationaryFuelMeters,0),ROUNDUP((COLUMN()+1)/3-2,0))),"") | R9: =IFERROR(IF(ISBLANK($A9),"",INDEX(Array_StationaryCharges,MATCH($A9,List_StationaryFuelMeters,0),ROUNDUP((COLUMN()+1)/3-2,0))),"") | U9: =IFERROR(IF(ISBLANK($A9),"",INDEX(Array_StationaryCharges,MATCH($A9,List_StationaryFuelMeters,0),ROUNDUP((COLUMN()+1)/3-2,0))),"") | X9: =IFERROR(IF(ISBLANK($A9),"",INDEX(Array_StationaryCharges,MATCH($A9,List_StationaryFuelMeters,0),ROUNDUP((COLUMN()+1)/3-2,0))),"") | AA9: =IFERROR(IF(ISBLANK($A9),"",INDEX(Array_StationaryCharges,MATCH($A9,List_StationaryFuelMeters,0),ROUNDUP((COLUMN()+1)/3-2,0))),"") | AD9: =IFERROR(IF(ISBLANK($A9),"",INDEX(Array_StationaryCharges,MATCH($A9,List_StationaryFuelMeters,0),ROUNDUP((COLUMN()+1)/3-2,0))),"") | AG9: =IFERROR(IF(ISBLANK($A9),"",INDEX(Array_StationaryCharges,MATCH($A9,List_StationaryFuelMeters,0),ROUNDUP((COLUMN()+1)/3-2,0))),"") | AJ9: =IFERROR(IF(ISBLANK($A9),"",INDEX(Array_StationaryCharges,MATCH($A9,List_StationaryFuelMeters,0),ROUNDUP((COLUMN()+1)/3-2,0))),"") | AM9: =IFERROR(IF(ISBLANK($A9),"",INDEX(Array_StationaryCharges,MATCH($A9,List_StationaryFuelMeters,0),ROUNDUP((COLUMN()+1)/3-2,0))),"") | AP9: =IFERROR(IF(ISBLANK($A9),"",INDEX(Array_StationaryCharges,MATCH($A9,List_StationaryFuelMeters,0),ROUNDUP((COLUMN()+1)/3-2,0))),"") | AS9: =IFERROR(IF(ISBLANK($A9),"",INDEX(Array_StationaryCharges,MATCH($A9,List_StationaryFuelMeters,0),ROUNDUP((COLUMN()+1)/3-2,0))),"") | AV9: =IFERROR(IF(ISBLANK($A9),"",INDEX(Array_StationaryCharges,MATCH($A9,List_StationaryFuelMeters,0),ROUNDUP((COLUMN()+1)/3-2,0))),"")
F10: =IFERROR(IF(ISBLANK($A10),"",INDEX(Array_StationaryCharges,MATCH($A10,List_StationaryFuelMeters,0),ROUNDUP((COLUMN()+1)/3-2,0))),"") | I10: =IFERROR(IF(ISBLANK($A10),"",INDEX(Array_StationaryCharges,MATCH($A10,List_StationaryFuelMeters,0),ROUNDUP((COLUMN()+1)/3-2,0))),"") | L10: =IFERROR(IF(ISBLANK($A10),"",INDEX(Array_StationaryCharges,MATCH($A10,List_StationaryFuelMeters,0),ROUNDUP((COLUMN()+1)/3-2,0))),"") | O10: =IFERROR(IF(ISBLANK($A10),"",INDEX(Array_StationaryCharges,MATCH($A10,List_StationaryFuelMeters,0),ROUNDUP((COLUMN()+1)/3-2,0))),"") | R10: =IFERROR(IF(ISBLANK($A10),"",INDEX(Array_StationaryCharges,MATCH($A10,List_StationaryFuelMeters,0),ROUNDUP((COLUMN()+1)/3-2,0))),"") | U10: =IFERROR(IF(ISBLANK($A10),"",INDEX(Array_StationaryCharges,MATCH($A10,List_StationaryFuelMeters,0),ROUNDUP((COLUMN()+1)/3-2,0))),"") | X10: =IFERROR(IF(ISBLANK($A10),"",INDEX(Array_StationaryCharges,MATCH($A10,List_StationaryFuelMeters,0),ROUNDUP((COLUMN()+1)/3-2,0))),"") | AA10: =IFERROR(IF(ISBLANK($A10),"",INDEX(Array_StationaryCharges,MATCH($A10,List_StationaryFuelMeters,0),ROUNDUP((COLUMN()+1)/3-2,0))),"") | AD10: =IFERROR(IF(ISBLANK($A10),"",INDEX(Array_StationaryCharges,MATCH($A10,List_StationaryFuelMeters,0),ROUNDUP((COLUMN()+1)/3-2,0))),"") | AG10: =IFERROR(IF(ISBLANK($A10),"",INDEX(Array_StationaryCharges,MATCH($A10,List_StationaryFuelMeters,0),ROUNDUP((COLUMN()+1)/3-2,0))),"") | AJ10: =IFERROR(IF(ISBLANK($A10),"",INDEX(Array_StationaryCharges,MATCH($A10,List_StationaryFuelMeters,0),ROUNDUP((COLUMN()+1)/3-2,0))),"") | AM10: =IFERROR(IF(ISBLANK($A10),"",INDEX(Array_StationaryCharges,MATCH($A10,List_StationaryFuelMeters,0),ROUNDUP((COLUMN()+1)/3-2,0))),"") | AP10: =IFERROR(IF(ISBLANK($A10),"",INDEX(Array_StationaryCharges,MATCH($A10,List_StationaryFuelMeters,0),ROUNDUP((COLUMN()+1)/3-2,0))),"") | AS10: =IFERROR(IF(ISBLANK($A10),"",INDEX(Array_StationaryCharges,MATCH($A10,List_StationaryFuelMeters,0),ROUNDUP((COLUMN()+1)/3-2,0))),"") | AV10: =IFERROR(IF(ISBLANK($A10),"",INDEX(Array_StationaryCharges,MATCH($A10,List_StationaryFuelMeters,0),ROUNDUP((COLUMN()+1)/3-2,0))),"")
F11: =IFERROR(IF(ISBLANK($A11),"",INDEX(Array_StationaryCharges,MATCH($A11,List_StationaryFuelMeters,0),ROUNDUP((COLUMN()+1)/3-2,0))),"") | I11: =IFERROR(IF(ISBLANK($A11),"",INDEX(Array_StationaryCharges,MATCH($A11,List_StationaryFuelMeters,0),ROUNDUP((COLUMN()+1)/3-2,0))),"") | L11: =IFERROR(IF(ISBLANK($A11),"",INDEX(Array_StationaryCharges,MATCH($A11,List_StationaryFuelMeters,0),ROUNDUP((COLUMN()+1)/3-2,0))),"") | O11: =IFERROR(IF(ISBLANK($A11),"",INDEX(Array_StationaryCharges,MATCH($A11,List_StationaryFuelMeters,0),ROUNDUP((COLUMN()+1)/3-2,0))),"") | R11: =IFERROR(IF(ISBLANK($A11),"",INDEX(Array_StationaryCharges,MATCH($A11,List_StationaryFuelMeters,0),ROUNDUP((COLUMN()+1)/3-2,0))),"") | U11: =IFERROR(IF(ISBLANK($A11),"",INDEX(Array_StationaryCharges,MATCH($A11,List_StationaryFuelMeters,0),ROUNDUP((COLUMN()+1)/3-2,0))),"") | X11: =IFERROR(IF(ISBLANK($A11),"",INDEX(Array_StationaryCharges,MATCH($A11,List_StationaryFuelMeters,0),ROUNDUP((COLUMN()+1)/3-2,0))),"") | AA11: =IFERROR(IF(ISBLANK($A11),"",INDEX(Array_StationaryCharges,MATCH($A11,List_StationaryFuelMeters,0),ROUNDUP((COLUMN()+1)/3-2,0))),"") | AD11: =IFERROR(IF(ISBLANK($A11),"",INDEX(Array_StationaryCharges,MATCH($A11,List_StationaryFuelMeters,0),ROUNDUP((COLUMN()+1)/3-2,0))),"") | AG11: =IFERROR(IF(ISBLANK($A11),"",INDEX(Array_StationaryCharges,MATCH($A11,List_StationaryFuelMeters,0),ROUNDUP((COLUMN()+1)/3-2,0))),"") | AJ11: =IFERROR(IF(ISBLANK($A11),"",INDEX(Array_StationaryCharges,MATCH($A11,List_StationaryFuelMeters,0),ROUNDUP((COLUMN()+1)/3-2,0))),"") | AM11: =IFERROR(IF(ISBLANK($A11),"",INDEX(Array_StationaryCharges,MATCH($A11,List_StationaryFuelMeters,0),ROUNDUP((COLUMN()+1)/3-2,0))),"") | AP11: =IFERROR(IF(ISBLANK($A11),"",INDEX(Array_StationaryCharges,MATCH($A11,List_StationaryFuelMeters,0),ROUNDUP((COLUMN()+1)/3-2,0))),"") | AS11: =IFERROR(IF(ISBLANK($A11),"",INDEX(Array_StationaryCharges,MATCH($A11,List_StationaryFuelMeters,0),ROUNDUP((COLUMN()+1)/3-2,0))),"") | AV11: =IFERROR(IF(ISBLANK($A11),"",INDEX(Array_StationaryCharges,MATCH($A11,List_StationaryFuelMeters,0),ROUNDUP((COLUMN()+1)/3-2,0))),"")
F12: =IFERROR(IF(ISBLANK($A12),"",INDEX(Array_StationaryCharges,MATCH($A12,List_StationaryFuelMeters,0),ROUNDUP((COLUMN()+1)/3-2,0))),"") | I12: =IFERROR(IF(ISBLANK($A12),"",INDEX(Array_StationaryCharges,MATCH($A12,List_StationaryFuelMeters,0),ROUNDUP((COLUMN()+1)/3-2,0))),"") | L12: =IFERROR(IF(ISBLANK($A12),"",INDEX(Array_StationaryCharges,MATCH($A12,List_StationaryFuelMeters,0),ROUNDUP((COLUMN()+1)/3-2,0))),"") | O12: =IFERROR(IF(ISBLANK($A12),"",INDEX(Array_StationaryCharges,MATCH($A12,List_StationaryFuelMeters,0),ROUNDUP((COLUMN()+1)/3-2,0))),"") | R12: =IFERROR(IF(ISBLANK($A12),"",INDEX(Array_StationaryCharges,MATCH($A12,List_StationaryFuelMeters,0),ROUNDUP((COLUMN()+1)/3-2,0))),"") | U12: =IFERROR(IF(ISBLANK($A12),"",INDEX(Array_StationaryCharges,MATCH($A12,List_StationaryFuelMeters,0),ROUNDUP((COLUMN()+1)/3-2,0))),"") | X12: =IFERROR(IF(ISBLANK($A12),"",INDEX(Array_StationaryCharges,MATCH($A12,List_StationaryFuelMeters,0),ROUNDUP((COLUMN()+1)/3-2,0))),"") | AA12: =IFERROR(IF(ISBLANK($A12),"",INDEX(Array_StationaryCharges,MATCH($A12,List_StationaryFuelMeters,0),ROUNDUP((COLUMN()+1)/3-2,0))),"") | AD12: =IFERROR(IF(ISBLANK($A12),"",INDEX(Array_StationaryCharges,MATCH($A12,List_StationaryFuelMeters,0),ROUNDUP((COLUMN()+1)/3-2,0))),"") | AG12: =IFERROR(IF(ISBLANK($A12),"",INDEX(Array_StationaryCharges,MATCH($A12,List_StationaryFuelMeters,0),ROUNDUP((COLUMN()+1)/3-2,0))),"") | AJ12: =IFERROR(IF(ISBLANK($A12),"",INDEX(Array_StationaryCharges,MATCH($A12,List_StationaryFuelMeters,0),ROUNDUP((COLUMN()+1)/3-2,0))),"") | AM12: =IFERROR(IF(ISBLANK($A12),"",INDEX(Array_StationaryCharges,MATCH($A12,List_StationaryFuelMeters,0),ROUNDUP((COLUMN()+1)/3-2,0))),"") | AP12: =IFERROR(IF(ISBLANK($A12),"",INDEX(Array_StationaryCharges,MATCH($A12,List_StationaryFuelMeters,0),ROUNDUP((COLUMN()+1)/3-2,0))),"") | AS12: =IFERROR(IF(ISBLANK($A12),"",INDEX(Array_StationaryCharges,MATCH($A12,List_StationaryFuelMeters,0),ROUNDUP((COLUMN()+1)/3-2,0))),"") | AV12: =IFERROR(IF(ISBLANK($A12),"",INDEX(Array_StationaryCharges,MATCH($A12,List_StationaryFuelMeters,0),ROUNDUP((COLUMN()+1)/3-2,0))),"")
F13: =IFERROR(IF(ISBLANK($A13),"",INDEX(Array_StationaryCharges,MATCH($A13,List_StationaryFuelMeters,0),ROUNDUP((COLUMN()+1)/3-2,0))),"") | I13: =IFERROR(IF(ISBLANK($A13),"",INDEX(Array_StationaryCharges,MATCH($A13,List_StationaryFuelMeters,0),ROUNDUP((COLUMN()+1)/3-2,0))),"") | L13: =IFERROR(IF(ISBLANK($A13),"",INDEX(Array_StationaryCharges,MATCH($A13,List_StationaryFuelMeters,0),ROUNDUP((COLUMN()+1)/3-2,0))),"") | O13: =IFERROR(IF(ISBLANK($A13),"",INDEX(Array_StationaryCharges,MATCH($A13,List_StationaryFuelMeters,0),ROUNDUP((COLUMN()+1)/3-2,0))),"") | R13: =IFERROR(IF(ISBLANK($A13),"",INDEX(Array_StationaryCharges,MATCH($A13,List_StationaryFuelMeters,0),ROUNDUP((COLUMN()+1)/3-2,0))),"") | U13: =IFERROR(IF(ISBLANK($A13),"",INDEX(Array_StationaryCharges,MATCH($A13,List_StationaryFuelMeters,0),ROUNDUP((COLUMN()+1)/3-2,0))),"") | X13: =IFERROR(IF(ISBLANK($A13),"",INDEX(Array_StationaryCharges,MATCH($A13,List_StationaryFuelMeters,0),ROUNDUP((COLUMN()+1)/3-2,0))),"") | AA13: =IFERROR(IF(ISBLANK($A13),"",INDEX(Array_StationaryCharges,MATCH($A13,List_StationaryFuelMeters,0),ROUNDUP((COLUMN()+1)/3-2,0))),"") | AD13: =IFERROR(IF(ISBLANK($A13),"",INDEX(Array_StationaryCharges,MATCH($A13,List_StationaryFuelMeters,0),ROUNDUP((COLUMN()+1)/3-2,0))),"") | AG13: =IFERROR(IF(ISBLANK($A13),"",INDEX(Array_StationaryCharges,MATCH($A13,List_StationaryFuelMeters,0),ROUNDUP((COLUMN()+1)/3-2,0))),"") | AJ13: =IFERROR(IF(ISBLANK($A13),"",INDEX(Array_StationaryCharges,MATCH($A13,List_StationaryFuelMeters,0),ROUNDUP((COLUMN()+1)/3-2,0))),"") | AM13: =IFERROR(IF(ISBLANK($A13),"",INDEX(Array_StationaryCharges,MATCH($A13,List_StationaryFuelMeters,0),ROUNDUP((COLUMN()+1)/3-2,0))),"") | AP13: =IFERROR(IF(ISBLANK($A13),"",INDEX(Array_StationaryCharges,MATCH($A13,List_StationaryFuelMeters,0),ROUNDUP((COLUMN()+1)/3-2,0))),"") | AS13: =IFERROR(IF(ISBLANK($A13),"",INDEX(Array_StationaryCharges,MATCH($A13,List_StationaryFuelMeters,0),ROUNDUP((COLUMN()+1)/3-2,0))),"") | AV13: =IFERROR(IF(ISBLANK($A13),"",INDEX(Array_StationaryCharges,MATCH($A13,List_StationaryFuelMeters,0),ROUNDUP((COLUMN()+1)/3-2,0))),"")
F14: =IFERROR(IF(ISBLANK($A14),"",INDEX(Array_StationaryCharges,MATCH($A14,List_StationaryFuelMeters,0),ROUNDUP((COLUMN()+1)/3-2,0))),"") | I14: =IFERROR(IF(ISBLANK($A14),"",INDEX(Array_StationaryCharges,MATCH($A14,List_StationaryFuelMeters,0),ROUNDUP((COLUMN()+1)/3-2,0))),"") | L14: =IFERROR(IF(ISBLANK($A14),"",INDEX(Array_StationaryCharges,MATCH($A14,List_StationaryFuelMeters,0),ROUNDUP((COLUMN()+1)/3-2,0))),"") | O14: =IFERROR(IF(ISBLANK($A14),"",INDEX(Array_StationaryCharges,MATCH($A14,List_StationaryFuelMeters,0),ROUNDUP((COLUMN()+1)/3-2,0))),"") | R14: =IFERROR(IF(ISBLANK($A14),"",INDEX(Array_StationaryCharges,MATCH($A14,List_StationaryFuelMeters,0),ROUNDUP((COLUMN()+1)/3-2,0))),"") | U14: =IFERROR(IF(ISBLANK($A14),"",INDEX(Array_StationaryCharges,MATCH($A14,List_StationaryFuelMeters,0),ROUNDUP((COLUMN()+1)/3-2,0))),"") | X14: =IFERROR(IF(ISBLANK($A14),"",INDEX(Array_StationaryCharges,MATCH($A14,List_StationaryFuelMeters,0),ROUNDUP((COLUMN()+1)/3-2,0))),"") | AA14: =IFERROR(IF(ISBLANK($A14),"",INDEX(Array_StationaryCharges,MATCH($A14,List_StationaryFuelMeters,0),ROUNDUP((COLUMN()+1)/3-2,0))),"") | AD14: =IFERROR(IF(ISBLANK($A14),"",INDEX(Array_StationaryCharges,MATCH($A14,List_StationaryFuelMeters,0),ROUNDUP((COLUMN()+1)/3-2,0))),"") | AG14: =IFERROR(IF(ISBLANK($A14),"",INDEX(Array_StationaryCharges,MATCH($A14,List_StationaryFuelMeters,0),ROUNDUP((COLUMN()+1)/3-2,0))),"") | AJ14: =IFERROR(IF(ISBLANK($A14),"",INDEX(Array_StationaryCharges,MATCH($A14,List_StationaryFuelMeters,0),ROUNDUP((COLUMN()+1)/3-2,0))),"") | AM14: =IFERROR(IF(ISBLANK($A14),"",INDEX(Array_StationaryCharges,MATCH($A14,List_StationaryFuelMeters,0),ROUNDUP((COLUMN()+1)/3-2,0))),"") | AP14: =IFERROR(IF(ISBLANK($A14),"",INDEX(Array_StationaryCharges,MATCH($A14,List_StationaryFuelMeters,0),ROUNDUP((COLUMN()+1)/3-2,0))),"") | AS14: =IFERROR(IF(ISBLANK($A14),"",INDEX(Array_StationaryCharges,MATCH($A14,List_StationaryFuelMeters,0),ROUNDUP((COLUMN()+1)/3-2,0))),"") | AV14: =IFERROR(IF(ISBLANK($A14),"",INDEX(Array_StationaryCharges,MATCH($A14,List_StationaryFuelMeters,0),ROUNDUP((COLUMN()+1)/3-2,0))),"")
... F502: =IFERROR(IF(ISBLANK($A502),"",INDEX(Array_StationaryCharges,MATCH($A502,List_StationaryFuelMeters,0),ROUNDUP((COLUMN()+1)/3-2,0))),"") | I502: =IFERROR(IF(ISBLANK($A502),"",INDEX(Array_StationaryCharges,MATCH($A502,List_StationaryFuelMeters,0),ROUNDUP((COLUMN()+1)/3-2,0))),"") | L502: =IFERROR(IF(ISBLANK($A502),"",INDEX(Array_StationaryCharges,MATCH($A502,List_StationaryFuelMeters,0),ROUNDUP((COLUMN()+1)/3-2,0))),"") | O502: =IFERROR(IF(ISBLANK($A502),"",INDEX(Array_StationaryCharges,MATCH($A502,List_StationaryFuelMeters,0),ROUNDUP((COLUMN()+1)/3-2,0))),"") | R502: =IFERROR(IF(ISBLANK($A502),"",INDEX(Array_StationaryCharges,MATCH($A502,List_StationaryFuelMeters,0),ROUNDUP((COLUMN()+1)/3-2,0))),"") | U502: =IFERROR(IF(ISBLANK($A502),"",INDEX(Array_StationaryCharges,MATCH($A502,List_StationaryFuelMeters,0),ROUNDUP((COLUMN()+1)/3-2,0))),"") | X502: =IFERROR(IF(ISBLANK($A502),"",INDEX(Array_StationaryCharges,MATCH($A502,List_StationaryFuelMeters,0),ROUNDUP((COLUMN()+1)/3-2,0))),"") | AA502: =IFERROR(IF(ISBLANK($A502),"",INDEX(Array_StationaryCharges,MATCH($A502,List_StationaryFuelMeters,0),ROUNDUP((COLUMN()+1)/3-2,0))),"") | AD502: =IFERROR(IF(ISBLANK($A502),"",INDEX(Array_StationaryCharges,MATCH($A502,List_StationaryFuelMeters,0),ROUNDUP((COLUMN()+1)/3-2,0))),"") | AG502: =IFERROR(IF(ISBLANK($A502),"",INDEX(Array_StationaryCharges,MATCH($A502,List_StationaryFuelMeters,0),ROUNDUP((COLUMN()+1)/3-2,0))),"") | AJ502: =IFERROR(IF(ISBLANK($A502),"",INDEX(Array_StationaryCharges,MATCH($A502,List_StationaryFuelMeters,0),ROUNDUP((COLUMN()+1)/3-2,0))),"") | AM502: =IFERROR(IF(ISBLANK($A502),"",INDEX(Array_StationaryCharges,MATCH($A502,List_StationaryFuelMeters,0),ROUNDUP((COLUMN()+1)/3-2,0))),"") | AP502: =IFERROR(IF(ISBLANK($A502),"",INDEX(Array_StationaryCharges,MATCH($A502,List_StationaryFuelMeters,0),ROUNDUP((COLUMN()+1)/3-2,0))),"") | AS502: =IFERROR(IF(ISBLANK($A502),"",INDEX(Array_StationaryCharges,MATCH($A502,List_StationaryFuelMeters,0),ROUNDUP((COLUMN()+1)/3-2,0))),"") | AV502: =IFERROR(IF(ISBLANK($A502),"",INDEX(Array_StationaryCharges,MATCH($A502,List_StationaryFuelMeters,0),ROUNDUP((COLUMN()+1)/3-2,0))),"")

Sheet HIDE_STATIONARY
A1: Fuel Phases | B1: Gas Fuels | C1: Liquid Fuels | D1: Solid Fuels | E1: Units Gas Fuels | F1: Units Liquid Fuels | G1: Units Solid Fuels | H1: Units Energy | I1: Charge Types
A2: Gas | B2: Natural Gas | C2: Benzene | D2: Biomass | E2: MMBtu | F2: MMBtu | G2: MMBtu | H2: MMBtu | I2: Usage
A3: Liquid | B3: Propane | C3: Biodiesel (100%) | D3: Black Liquor | E3: Therms | F3: Therms | G3: Therms | H3: kWh | I3: Demand/MDQ
A4: Solid | B4: Butane | C4: Butane | D4: Coal (anthracite) | E4: DTherms | F4: DTherms | G4: DTherms | H4: MWh | I4: Tax
B5: Isobutane | C5: Butene | D5: Coal (bituminous) | E5: kWh | F5: kWh | G5: kWh | H5: GJ | I5: Late Fee
B6: Blast Furnace Gas | C6: Crude Oil | D6: Coal | E6: MWh | F6: MWh | G6: MWh | H6: MJ | I6: Flat Fee
B7: Coke Oven Gas | C7: Diesel | D7: Coke | E7: GJ | F7: GJ | G7: GJ | H7: kJ | I7: Other
B8: Liquefied Petroleum Gas (LPG) | C8: Distillate Fuel Oil | D8: Peat | E8: MJ | F8: MJ | G8: MJ | H8: Therms
B9: Landfill Gas | C9: Ethanol (100%) | D9: Scrap Tires | E9: kJ | F9: kJ | G9: kJ | H9: DTherms
B10: Oil Gases | C10: Ethyl Alcohol | D10: Sulfur | E10: kcal | F10: kcal | G10: kcal | H10: kcal
C11: Ethylene | D11: Wood | E11: SCF | F11: gal | G11: lb
C12: Fuel Oil #1 | E12: CCF | F12: kgal | G12: klb
C13: Fuel Oil #2 | E13: kSCF | F13: Mgal | G13: kg
C14: Fuel Oil #4 | E14: MMCF | F14: ft3 | G14: ton
C15: Fuel Oil #5 | E15: m3 | F15: m3 | G15: tonne
C16: Fuel Oil #6 (high sulfur) | E16: MCM | F16: L
C17: Fuel Oil #6 (low sulfur) | E17: kCM
C18: Gas Oil
C19: Gasoline
C20: Heating Oil
C21: Isobutane
C22: Kerosene
C23: Liquefied Natural Gas (LNG)
C24: LPG
C25: Methyl Alcohol
C26: Pentane
C27: Pentene
C28: Propane
C29: Propylene
... C32: Xylene
A35: Charge count: | B35: =COUNTIF(B37:B136,"?*") -> 0 | C35: =COUNTIF(C37:C136,"?*") -> 0 | D35: =COUNTIF(D37:D136,"?*") -> 0 | E35: =COUNTIF(E37:E136,"?*") -> 0 | F35: =COUNTIF(F37:F136,"?*") -> 0 | G35: =COUNTIF(G37:G136,"?*") -> 0 | H35: =COUNTIF(H37:H136,"?*") -> 0 | I35: =COUNTIF(I37:I136,"?*") -> 0 | ... P35: =COUNTIF(P37:P136,"?*") -> 0
A36: Meter Numbers | B36: Charge 1 | C36: Charge 2 | D36: Charge 3 | E36: Charge 4 | F36: Charge 5 | G36: Charge 6 | H36: Charge 7 | I36: Charge 8 | J36: Charge 9 | K36: Charge 10 | L36: Charge 11 | M36: Charge 12 | N36: Charge 13 | O36: Charge 14 | P36: Charge 15
A37: =IF('Stationary Fuel Meters'!B3="",A36,'Stationary Fuel Meters'!B3) -> Meter Numbers | B37: =IF(ISBLANK(INDEX(Array_StationaryChargeData,ROW()-36,COLUMN()*2-3)),"",INDEX(Array_StationaryChargeData,ROW()-36,COLUMN()*2-3)) | C37: =IF(ISBLANK(INDEX(Array_StationaryChargeData,ROW()-36,COLUMN()*2-3)),"",INDEX(Array_StationaryChargeData,ROW()-36,COLUMN()*2-3)) | D37: =IF(ISBLANK(INDEX(Array_StationaryChargeData,ROW()-36,COLUMN()*2-3)),"",INDEX(Array_StationaryChargeData,ROW()-36,COLUMN()*2-3)) | E37: =IF(ISBLANK(INDEX(Array_StationaryChargeData,ROW()-36,COLUMN()*2-3)),"",INDEX(Array_StationaryChargeData,ROW()-36,COLUMN()*2-3)) | F37: =IF(ISBLANK(INDEX(Array_StationaryChargeData,ROW()-36,COLUMN()*2-3)),"",INDEX(Array_StationaryChargeData,ROW()-36,COLUMN()*2-3)) | G37: =IF(ISBLANK(INDEX(Array_StationaryChargeData,ROW()-36,COLUMN()*2-3)),"",INDEX(Array_StationaryChargeData,ROW()-36,COLUMN()*2-3)) | H37: =IF(ISBLANK(INDEX(Array_StationaryChargeData,ROW()-36,COLUMN()*2-3)),"",INDEX(Array_StationaryChargeData,ROW()-36,COLUMN()*2-3)) | I37: =IF(ISBLANK(INDEX(Array_StationaryChargeData,ROW()-36,COLUMN()*2-3)),"",INDEX(Array_StationaryChargeData,ROW()-36,COLUMN()*2-3)) | ... P37: =IF(ISBLANK(INDEX(Array_StationaryChargeData,ROW()-36,COLUMN()*2-3)),"",INDEX(Array_StationaryChargeData,ROW()-36,COLUMN()*2-3))
A38: =IF('Stationary Fuel Meters'!B4="",A37,'Stationary Fuel Meters'!B4) -> Meter Numbers | B38: =IF(ISBLANK(INDEX(Array_StationaryChargeData,ROW()-36,COLUMN()*2-3)),"",INDEX(Array_StationaryChargeData,ROW()-36,COLUMN()*2-3)) | C38: =IF(ISBLANK(INDEX(Array_StationaryChargeData,ROW()-36,COLUMN()*2-3)),"",INDEX(Array_StationaryChargeData,ROW()-36,COLUMN()*2-3)) | D38: =IF(ISBLANK(INDEX(Array_StationaryChargeData,ROW()-36,COLUMN()*2-3)),"",INDEX(Array_StationaryChargeData,ROW()-36,COLUMN()*2-3)) | E38: =IF(ISBLANK(INDEX(Array_StationaryChargeData,ROW()-36,COLUMN()*2-3)),"",INDEX(Array_StationaryChargeData,ROW()-36,COLUMN()*2-3)) | F38: =IF(ISBLANK(INDEX(Array_StationaryChargeData,ROW()-36,COLUMN()*2-3)),"",INDEX(Array_StationaryChargeData,ROW()-36,COLUMN()*2-3)) | G38: =IF(ISBLANK(INDEX(Array_StationaryChargeData,ROW()-36,COLUMN()*2-3)),"",INDEX(Array_StationaryChargeData,ROW()-36,COLUMN()*2-3)) | H38: =IF(ISBLANK(INDEX(Array_StationaryChargeData,ROW()-36,COLUMN()*2-3)),"",INDEX(Array_StationaryChargeData,ROW()-36,COLUMN()*2-3)) | I38: =IF(ISBLANK(INDEX(Array_StationaryChargeData,ROW()-36,COLUMN()*2-3)),"",INDEX(Array_StationaryChargeData,ROW()-36,COLUMN()*2-3)) | ... P38: =IF(ISBLANK(INDEX(Array_StationaryChargeData,ROW()-36,COLUMN()*2-3)),"",INDEX(Array_StationaryChargeData,ROW()-36,COLUMN()*2-3))
A39: =IF('Stationary Fuel Meters'!B5="",A38,'Stationary Fuel Meters'!B5) -> Meter Numbers | B39: =IF(ISBLANK(INDEX(Array_StationaryChargeData,ROW()-36,COLUMN()*2-3)),"",INDEX(Array_StationaryChargeData,ROW()-36,COLUMN()*2-3)) | C39: =IF(ISBLANK(INDEX(Array_StationaryChargeData,ROW()-36,COLUMN()*2-3)),"",INDEX(Array_StationaryChargeData,ROW()-36,COLUMN()*2-3)) | D39: =IF(ISBLANK(INDEX(Array_StationaryChargeData,ROW()-36,COLUMN()*2-3)),"",INDEX(Array_StationaryChargeData,ROW()-36,COLUMN()*2-3)) | E39: =IF(ISBLANK(INDEX(Array_StationaryChargeData,ROW()-36,COLUMN()*2-3)),"",INDEX(Array_StationaryChargeData,ROW()-36,COLUMN()*2-3)) | F39: =IF(ISBLANK(INDEX(Array_StationaryChargeData,ROW()-36,COLUMN()*2-3)),"",INDEX(Array_StationaryChargeData,ROW()-36,COLUMN()*2-3)) | G39: =IF(ISBLANK(INDEX(Array_StationaryChargeData,ROW()-36,COLUMN()*2-3)),"",INDEX(Array_StationaryChargeData,ROW()-36,COLUMN()*2-3)) | H39: =IF(ISBLANK(INDEX(Array_StationaryChargeData,ROW()-36,COLUMN()*2-3)),"",INDEX(Array_StationaryChargeData,ROW()-36,COLUMN()*2-3)) | I39: =IF(ISBLANK(INDEX(Array_StationaryChargeData,ROW()-36,COLUMN()*2-3)),"",INDEX(Array_StationaryChargeData,ROW()-36,COLUMN()*2-3)) | ... P39: =IF(ISBLANK(INDEX(Array_StationaryChargeData,ROW()-36,COLUMN()*2-3)),"",INDEX(Array_StationaryChargeData,ROW()-36,COLUMN()*2-3))
A40: =IF('Stationary Fuel Meters'!B6="",A39,'Stationary Fuel Meters'!B6) -> Meter Numbers | B40: =IF(ISBLANK(INDEX(Array_StationaryChargeData,ROW()-36,COLUMN()*2-3)),"",INDEX(Array_StationaryChargeData,ROW()-36,COLUMN()*2-3)) | C40: =IF(ISBLANK(INDEX(Array_StationaryChargeData,ROW()-36,COLUMN()*2-3)),"",INDEX(Array_StationaryChargeData,ROW()-36,COLUMN()*2-3)) | D40: =IF(ISBLANK(INDEX(Array_StationaryChargeData,ROW()-36,COLUMN()*2-3)),"",INDEX(Array_StationaryChargeData,ROW()-36,COLUMN()*2-3)) | E40: =IF(ISBLANK(INDEX(Array_StationaryChargeData,ROW()-36,COLUMN()*2-3)),"",INDEX(Array_StationaryChargeData,ROW()-36,COLUMN()*2-3)) | F40: =IF(ISBLANK(INDEX(Array_StationaryChargeData,ROW()-36,COLUMN()*2-3)),"",INDEX(Array_StationaryChargeData,ROW()-36,COLUMN()*2-3)) | G40: =IF(ISBLANK(INDEX(Array_StationaryChargeData,ROW()-36,COLUMN()*2-3)),"",INDEX(Array_StationaryChargeData,ROW()-36,COLUMN()*2-3)) | H40: =IF(ISBLANK(INDEX(Array_StationaryChargeData,ROW()-36,COLUMN()*2-3)),"",INDEX(Array_StationaryChargeData,ROW()-36,COLUMN()*2-3)) | I40: =IF(ISBLANK(INDEX(Array_StationaryChargeData,ROW()-36,COLUMN()*2-3)),"",INDEX(Array_StationaryChargeData,ROW()-36,COLUMN()*2-3)) | ... P40: =IF(ISBLANK(INDEX(Array_StationaryChargeData,ROW()-36,COLUMN()*2-3)),"",INDEX(Array_StationaryChargeData,ROW()-36,COLUMN()*2-3))
A41: =IF('Stationary Fuel Meters'!B7="",A40,'Stationary Fuel Meters'!B7) -> Meter Numbers | B41: =IF(ISBLANK(INDEX(Array_StationaryChargeData,ROW()-36,COLUMN()*2-3)),"",INDEX(Array_StationaryChargeData,ROW()-36,COLUMN()*2-3)) | C41: =IF(ISBLANK(INDEX(Array_StationaryChargeData,ROW()-36,COLUMN()*2-3)),"",INDEX(Array_StationaryChargeData,ROW()-36,COLUMN()*2-3)) | D41: =IF(ISBLANK(INDEX(Array_StationaryChargeData,ROW()-36,COLUMN()*2-3)),"",INDEX(Array_StationaryChargeData,ROW()-36,COLUMN()*2-3)) | E41: =IF(ISBLANK(INDEX(Array_StationaryChargeData,ROW()-36,COLUMN()*2-3)),"",INDEX(Array_StationaryChargeData,ROW()-36,COLUMN()*2-3)) | F41: =IF(ISBLANK(INDEX(Array_StationaryChargeData,ROW()-36,COLUMN()*2-3)),"",INDEX(Array_StationaryChargeData,ROW()-36,COLUMN()*2-3)) | G41: =IF(ISBLANK(INDEX(Array_StationaryChargeData,ROW()-36,COLUMN()*2-3)),"",INDEX(Array_StationaryChargeData,ROW()-36,COLUMN()*2-3)) | H41: =IF(ISBLANK(INDEX(Array_StationaryChargeData,ROW()-36,COLUMN()*2-3)),"",INDEX(Array_StationaryChargeData,ROW()-36,COLUMN()*2-3)) | I41: =IF(ISBLANK(INDEX(Array_StationaryChargeData,ROW()-36,COLUMN()*2-3)),"",INDEX(Array_StationaryChargeData,ROW()-36,COLUMN()*2-3)) | ... P41: =IF(ISBLANK(INDEX(Array_StationaryChargeData,ROW()-36,COLUMN()*2-3)),"",INDEX(Array_StationaryChargeData,ROW()-36,COLUMN()*2-3))
A42: =IF('Stationary Fuel Meters'!B8="",A41,'Stationary Fuel Meters'!B8) -> Meter Numbers | B42: =IF(ISBLANK(INDEX(Array_StationaryChargeData,ROW()-36,COLUMN()*2-3)),"",INDEX(Array_StationaryChargeData,ROW()-36,COLUMN()*2-3)) | C42: =IF(ISBLANK(INDEX(Array_StationaryChargeData,ROW()-36,COLUMN()*2-3)),"",INDEX(Array_StationaryChargeData,ROW()-36,COLUMN()*2-3)) | D42: =IF(ISBLANK(INDEX(Array_StationaryChargeData,ROW()-36,COLUMN()*2-3)),"",INDEX(Array_StationaryChargeData,ROW()-36,COLUMN()*2-3)) | E42: =IF(ISBLANK(INDEX(Array_StationaryChargeData,ROW()-36,COLUMN()*2-3)),"",INDEX(Array_StationaryChargeData,ROW()-36,COLUMN()*2-3)) | F42: =IF(ISBLANK(INDEX(Array_StationaryChargeData,ROW()-36,COLUMN()*2-3)),"",INDEX(Array_StationaryChargeData,ROW()-36,COLUMN()*2-3)) | G42: =IF(ISBLANK(INDEX(Array_StationaryChargeData,ROW()-36,COLUMN()*2-3)),"",INDEX(Array_StationaryChargeData,ROW()-36,COLUMN()*2-3)) | H42: =IF(ISBLANK(INDEX(Array_StationaryChargeData,ROW()-36,COLUMN()*2-3)),"",INDEX(Array_StationaryChargeData,ROW()-36,COLUMN()*2-3)) | I42: =IF(ISBLANK(INDEX(Array_StationaryChargeData,ROW()-36,COLUMN()*2-3)),"",INDEX(Array_StationaryChargeData,ROW()-36,COLUMN()*2-3)) | ... P42: =IF(ISBLANK(INDEX(Array_StationaryChargeData,ROW()-36,COLUMN()*2-3)),"",INDEX(Array_StationaryChargeData,ROW()-36,COLUMN()*2-3))
A43: =IF('Stationary Fuel Meters'!B9="",A42,'Stationary Fuel Meters'!B9) -> Meter Numbers | B43: =IF(ISBLANK(INDEX(Array_StationaryChargeData,ROW()-36,COLUMN()*2-3)),"",INDEX(Array_StationaryChargeData,ROW()-36,COLUMN()*2-3)) | C43: =IF(ISBLANK(INDEX(Array_StationaryChargeData,ROW()-36,COLUMN()*2-3)),"",INDEX(Array_StationaryChargeData,ROW()-36,COLUMN()*2-3)) | D43: =IF(ISBLANK(INDEX(Array_StationaryChargeData,ROW()-36,COLUMN()*2-3)),"",INDEX(Array_StationaryChargeData,ROW()-36,COLUMN()*2-3)) | E43: =IF(ISBLANK(INDEX(Array_StationaryChargeData,ROW()-36,COLUMN()*2-3)),"",INDEX(Array_StationaryChargeData,ROW()-36,COLUMN()*2-3)) | F43: =IF(ISBLANK(INDEX(Array_StationaryChargeData,ROW()-36,COLUMN()*2-3)),"",INDEX(Array_StationaryChargeData,ROW()-36,COLUMN()*2-3)) | G43: =IF(ISBLANK(INDEX(Array_StationaryChargeData,ROW()-36,COLUMN()*2-3)),"",INDEX(Array_StationaryChargeData,ROW()-36,COLUMN()*2-3)) | H43: =IF(ISBLANK(INDEX(Array_StationaryChargeData,ROW()-36,COLUMN()*2-3)),"",INDEX(Array_StationaryChargeData,ROW()-36,COLUMN()*2-3)) | I43: =IF(ISBLANK(INDEX(Array_StationaryChargeData,ROW()-36,COLUMN()*2-3)),"",INDEX(Array_StationaryChargeData,ROW()-36,COLUMN()*2-3)) | ... P43: =IF(ISBLANK(INDEX(Array_StationaryChargeData,ROW()-36,COLUMN()*2-3)),"",INDEX(Array_StationaryChargeData,ROW()-36,COLUMN()*2-3))
A44: =IF('Stationary Fuel Meters'!B10="",A43,'Stationary Fuel Meters'!B10) -> Meter Numbers | B44: =IF(ISBLANK(INDEX(Array_StationaryChargeData,ROW()-36,COLUMN()*2-3)),"",INDEX(Array_StationaryChargeData,ROW()-36,COLUMN()*2-3)) | C44: =IF(ISBLANK(INDEX(Array_StationaryChargeData,ROW()-36,COLUMN()*2-3)),"",INDEX(Array_StationaryChargeData,ROW()-36,COLUMN()*2-3)) | D44: =IF(ISBLANK(INDEX(Array_StationaryChargeData,ROW()-36,COLUMN()*2-3)),"",INDEX(Array_StationaryChargeData,ROW()-36,COLUMN()*2-3)) | E44: =IF(ISBLANK(INDEX(Array_StationaryChargeData,ROW()-36,COLUMN()*2-3)),"",INDEX(Array_StationaryChargeData,ROW()-36,COLUMN()*2-3)) | F44: =IF(ISBLANK(INDEX(Array_StationaryChargeData,ROW()-36,COLUMN()*2-3)),"",INDEX(Array_StationaryChargeData,ROW()-36,COLUMN()*2-3)) | G44: =IF(ISBLANK(INDEX(Array_StationaryChargeData,ROW()-36,COLUMN()*2-3)),"",INDEX(Array_StationaryChargeData,ROW()-36,COLUMN()*2-3)) | H44: =IF(ISBLANK(INDEX(Array_StationaryChargeData,ROW()-36,COLUMN()*2-3)),"",INDEX(Array_StationaryChargeData,ROW()-36,COLUMN()*2-3)) | I44: =IF(ISBLANK(INDEX(Array_StationaryChargeData,ROW()-36,COLUMN()*2-3)),"",INDEX(Array_StationaryChargeData,ROW()-36,COLUMN()*2-3)) | ... P44: =IF(ISBLANK(INDEX(Array_StationaryChargeData,ROW()-36,COLUMN()*2-3)),"",INDEX(Array_StationaryChargeData,ROW()-36,COLUMN()*2-3))
A45: =IF('Stationary Fuel Meters'!B11="",A44,'Stationary Fuel Meters'!B11) -> Meter Numbers | B45: =IF(ISBLANK(INDEX(Array_StationaryChargeData,ROW()-36,COLUMN()*2-3)),"",INDEX(Array_StationaryChargeData,ROW()-36,COLUMN()*2-3)) | C45: =IF(ISBLANK(INDEX(Array_StationaryChargeData,ROW()-36,COLUMN()*2-3)),"",INDEX(Array_StationaryChargeData,ROW()-36,COLUMN()*2-3)) | D45: =IF(ISBLANK(INDEX(Array_StationaryChargeData,ROW()-36,COLUMN()*2-3)),"",INDEX(Array_StationaryChargeData,ROW()-36,COLUMN()*2-3)) | E45: =IF(ISBLANK(INDEX(Array_StationaryChargeData,ROW()-36,COLUMN()*2-3)),"",INDEX(Array_StationaryChargeData,ROW()-36,COLUMN()*2-3)) | F45: =IF(ISBLANK(INDEX(Array_StationaryChargeData,ROW()-36,COLUMN()*2-3)),"",INDEX(Array_StationaryChargeData,ROW()-36,COLUMN()*2-3)) | G45: =IF(ISBLANK(INDEX(Array_StationaryChargeData,ROW()-36,COLUMN()*2-3)),"",INDEX(Array_StationaryChargeData,ROW()-36,COLUMN()*2-3)) | H45: =IF(ISBLANK(INDEX(Array_StationaryChargeData,ROW()-36,COLUMN()*2-3)),"",INDEX(Array_StationaryChargeData,ROW()-36,COLUMN()*2-3)) | I45: =IF(ISBLANK(INDEX(Array_StationaryChargeData,ROW()-36,COLUMN()*2-3)),"",INDEX(Array_StationaryChargeData,ROW()-36,COLUMN()*2-3)) | ... P45: =IF(ISBLANK(INDEX(Array_StationaryChargeData,ROW()-36,COLUMN()*2-3)),"",INDEX(Array_StationaryChargeData,ROW()-36,COLUMN()*2-3))
A46: =IF('Stationary Fuel Meters'!B12="",A45,'Stationary Fuel Meters'!B12) -> Meter Numbers | B46: =IF(ISBLANK(INDEX(Array_StationaryChargeData,ROW()-36,COLUMN()*2-3)),"",INDEX(Array_StationaryChargeData,ROW()-36,COLUMN()*2-3)) | C46: =IF(ISBLANK(INDEX(Array_StationaryChargeData,ROW()-36,COLUMN()*2-3)),"",INDEX(Array_StationaryChargeData,ROW()-36,COLUMN()*2-3)) | D46: =IF(ISBLANK(INDEX(Array_StationaryChargeData,ROW()-36,COLUMN()*2-3)),"",INDEX(Array_StationaryChargeData,ROW()-36,COLUMN()*2-3)) | E46: =IF(ISBLANK(INDEX(Array_StationaryChargeData,ROW()-36,COLUMN()*2-3)),"",INDEX(Array_StationaryChargeData,ROW()-36,COLUMN()*2-3)) | F46: =IF(ISBLANK(INDEX(Array_StationaryChargeData,ROW()-36,COLUMN()*2-3)),"",INDEX(Array_StationaryChargeData,ROW()-36,COLUMN()*2-3)) | G46: =IF(ISBLANK(INDEX(Array_StationaryChargeData,ROW()-36,COLUMN()*2-3)),"",INDEX(Array_StationaryChargeData,ROW()-36,COLUMN()*2-3)) | H46: =IF(ISBLANK(INDEX(Array_StationaryChargeData,ROW()-36,COLUMN()*2-3)),"",INDEX(Array_StationaryChargeData,ROW()-36,COLUMN()*2-3)) | I46: =IF(ISBLANK(INDEX(Array_StationaryChargeData,ROW()-36,COLUMN()*2-3)),"",INDEX(Array_StationaryChargeData,ROW()-36,COLUMN()*2-3)) | ... P46: =IF(ISBLANK(INDEX(Array_StationaryChargeData,ROW()-36,COLUMN()*2-3)),"",INDEX(Array_StationaryChargeData,ROW()-36,COLUMN()*2-3))
A47: =IF('Stationary Fuel Meters'!B13="",A46,'Stationary Fuel Meters'!B13) -> Meter Numbers | B47: =IF(ISBLANK(INDEX(Array_StationaryChargeData,ROW()-36,COLUMN()*2-3)),"",INDEX(Array_StationaryChargeData,ROW()-36,COLUMN()*2-3)) | C47: =IF(ISBLANK(INDEX(Array_StationaryChargeData,ROW()-36,COLUMN()*2-3)),"",INDEX(Array_StationaryChargeData,ROW()-36,COLUMN()*2-3)) | D47: =IF(ISBLANK(INDEX(Array_StationaryChargeData,ROW()-36,COLUMN()*2-3)),"",INDEX(Array_StationaryChargeData,ROW()-36,COLUMN()*2-3)) | E47: =IF(ISBLANK(INDEX(Array_StationaryChargeData,ROW()-36,COLUMN()*2-3)),"",INDEX(Array_StationaryChargeData,ROW()-36,COLUMN()*2-3)) | F47: =IF(ISBLANK(INDEX(Array_StationaryChargeData,ROW()-36,COLUMN()*2-3)),"",INDEX(Array_StationaryChargeData,ROW()-36,COLUMN()*2-3)) | G47: =IF(ISBLANK(INDEX(Array_StationaryChargeData,ROW()-36,COLUMN()*2-3)),"",INDEX(Array_StationaryChargeData,ROW()-36,COLUMN()*2-3)) | H47: =IF(ISBLANK(INDEX(Array_StationaryChargeData,ROW()-36,COLUMN()*2-3)),"",INDEX(Array_StationaryChargeData,ROW()-36,COLUMN()*2-3)) | I47: =IF(ISBLANK(INDEX(Array_StationaryChargeData,ROW()-36,COLUMN()*2-3)),"",INDEX(Array_StationaryChargeData,ROW()-36,COLUMN()*2-3)) | ... P47: =IF(ISBLANK(INDEX(Array_StationaryChargeData,ROW()-36,COLUMN()*2-3)),"",INDEX(Array_StationaryChargeData,ROW()-36,COLUMN()*2-3))
A48: =IF('Stationary Fuel Meters'!B14="",A47,'Stationary Fuel Meters'!B14) -> Meter Numbers | B48: =IF(ISBLANK(INDEX(Array_StationaryChargeData,ROW()-36,COLUMN()*2-3)),"",INDEX(Array_StationaryChargeData,ROW()-36,COLUMN()*2-3)) | C48: =IF(ISBLANK(INDEX(Array_StationaryChargeData,ROW()-36,COLUMN()*2-3)),"",INDEX(Array_StationaryChargeData,ROW()-36,COLUMN()*2-3)) | D48: =IF(ISBLANK(INDEX(Array_StationaryChargeData,ROW()-36,COLUMN()*2-3)),"",INDEX(Array_StationaryChargeData,ROW()-36,COLUMN()*2-3)) | E48: =IF(ISBLANK(INDEX(Array_StationaryChargeData,ROW()-36,COLUMN()*2-3)),"",INDEX(Array_StationaryChargeData,ROW()-36,COLUMN()*2-3)) | F48: =IF(ISBLANK(INDEX(Array_StationaryChargeData,ROW()-36,COLUMN()*2-3)),"",INDEX(Array_StationaryChargeData,ROW()-36,COLUMN()*2-3)) | G48: =IF(ISBLANK(INDEX(Array_StationaryChargeData,ROW()-36,COLUMN()*2-3)),"",INDEX(Array_StationaryChargeData,ROW()-36,COLUMN()*2-3)) | H48: =IF(ISBLANK(INDEX(Array_StationaryChargeData,ROW()-36,COLUMN()*2-3)),"",INDEX(Array_StationaryChargeData,ROW()-36,COLUMN()*2-3)) | I48: =IF(ISBLANK(INDEX(Array_StationaryChargeData,ROW()-36,COLUMN()*2-3)),"",INDEX(Array_StationaryChargeData,ROW()-36,COLUMN()*2-3)) | ... P48: =IF(ISBLANK(INDEX(Array_StationaryChargeData,ROW()-36,COLUMN()*2-3)),"",INDEX(Array_StationaryChargeData,ROW()-36,COLUMN()*2-3))
... A236: =IF('Stationary Fuel Meters'!B202="",A235,'Stationary Fuel Meters'!B202) -> Meter Numbers | B236: =IF(ISBLANK(INDEX(Array_StationaryChargeData,ROW()-36,COLUMN()*2-3)),"",INDEX(Array_StationaryChargeData,ROW()-36,COLUMN()*2-3)) | C236: =IF(ISBLANK(INDEX(Array_StationaryChargeData,ROW()-36,COLUMN()*2-3)),"",INDEX(Array_StationaryChargeData,ROW()-36,COLUMN()*2-3)) | D236: =IF(ISBLANK(INDEX(Array_StationaryChargeData,ROW()-36,COLUMN()*2-3)),"",INDEX(Array_StationaryChargeData,ROW()-36,COLUMN()*2-3)) | E236: =IF(ISBLANK(INDEX(Array_StationaryChargeData,ROW()-36,COLUMN()*2-3)),"",INDEX(Array_StationaryChargeData,ROW()-36,COLUMN()*2-3)) | F236: =IF(ISBLANK(INDEX(Array_StationaryChargeData,ROW()-36,COLUMN()*2-3)),"",INDEX(Array_StationaryChargeData,ROW()-36,COLUMN()*2-3)) | G236: =IF(ISBLANK(INDEX(Array_StationaryChargeData,ROW()-36,COLUMN()*2-3)),"",INDEX(Array_StationaryChargeData,ROW()-36,COLUMN()*2-3)) | H236: =IF(ISBLANK(INDEX(Array_StationaryChargeData,ROW()-36,COLUMN()*2-3)),"",INDEX(Array_StationaryChargeData,ROW()-36,COLUMN()*2-3)) | I236: =IF(ISBLANK(INDEX(Array_StationaryChargeData,ROW()-36,COLUMN()*2-3)),"",INDEX(Array_StationaryChargeData,ROW()-36,COLUMN()*2-3)) | ... P236: =IF(ISBLANK(INDEX(Array_StationaryChargeData,ROW()-36,COLUMN()*2-3)),"",INDEX(Array_StationaryChargeData,ROW()-36,COLUMN()*2-3))

Sheet Mobile Fuel Meters
A1: √ Mobile Fuel Meters Setup | R1: √ Mobile Fuel Charge Setup (Optional)
A2: Facility Name | B2: Meter Number (UNIQUE) | C2: Meter Name (DISPLAY) | D2: Meter Group (ANALYSIS) | E2: Calendarize Readings? | F2: Vehicle Type | G2: Fuel Type | H2: Unit (USAGE) | I2: Unit (DISTANCE) | J2: Average Fuel Efficiency | K2: Estimation Method | L2: S2S Factor | M2: Include with Energy? | N2: Account # | O2: Supplier | P2: Location | Q2: Notes | R2: ="Charge "&QUOTIENT(COLUMN()-16,2)&" Name" -> Charge 1 Name | S2: ="Charge "&QUOTIENT(COLUMN()-16,2)&" Type" -> Charge 1 Type | T2: ="Charge "&QUOTIENT(COLUMN()-16,2)&" Name" -> Charge 2 Name | U2: ="Charge "&QUOTIENT(COLUMN()-16,2)&" Type" -> Charge 2 Type | V2: ="Charge "&QUOTIENT(COLUMN()-16,2)&" Name" -> Charge 3 Name | W2: ="Charge "&QUOTIENT(COLUMN()-16,2)&" Type" -> Charge 3 Type | X2: ="Charge "&QUOTIENT(COLUMN()-16,2)&" Name" -> Charge 4 Name | Y2: ="Charge "&QUOTIENT(COLUMN()-16,2)&" Type" -> Charge 4 Type | Z2: ="Charge "&QUOTIENT(COLUMN()-16,2)&" Name" -> Charge 5 Name | AA2: ="Charge "&QUOTIENT(COLUMN()-16,2)&" Type" -> Charge 5 Type

Sheet Mobile Fuel
A1: √ Mobile Fuel Readings | G1: √ Mobile Fuel Charges (Optional)
A2: Meter Number | B2: Read Date | C2: Total Usage or Distance | D2: Fuel Efficiency | E2: Number of Vehicles | F2: Total Cost ($) | G2: =IF(INDEX(List_ChargeNumbers_Mobile, 1, ROUNDUP((COLUMN()+0)/3-2,0)) = 0,"",INDEX(List_ChargeNumbers_Mobile, 2, ROUNDUP((COLUMN()+0)/3-2,0))&" Name") | H2: =IF(INDEX(List_ChargeNumbers_Mobile, 1, ROUNDUP((COLUMN()+0)/3-2,0)) = 0,"",INDEX(List_ChargeNumbers_Mobile, 2, ROUNDUP((COLUMN()+0)/3-2,0))&" Reading") | I2: =IF(INDEX(List_ChargeNumbers_Mobile, 1, ROUNDUP((COLUMN()+0)/3-2,0)) = 0,"",INDEX(List_ChargeNumbers_Mobile, 2, ROUNDUP((COLUMN()+0)/3-2,0))&" Cost") | J2: =IF(INDEX(List_ChargeNumbers_Mobile, 1, ROUNDUP((COLUMN()+0)/3-2,0)) = 0,"",INDEX(List_ChargeNumbers_Mobile, 2, ROUNDUP((COLUMN()+0)/3-2,0))&" Name") | K2: =IF(INDEX(List_ChargeNumbers_Mobile, 1, ROUNDUP((COLUMN()+0)/3-2,0)) = 0,"",INDEX(List_ChargeNumbers_Mobile, 2, ROUNDUP((COLUMN()+0)/3-2,0))&" Reading") | L2: =IF(INDEX(List_ChargeNumbers_Mobile, 1, ROUNDUP((COLUMN()+0)/3-2,0)) = 0,"",INDEX(List_ChargeNumbers_Mobile, 2, ROUNDUP((COLUMN()+0)/3-2,0))&" Cost") | M2: =IF(INDEX(List_ChargeNumbers_Mobile, 1, ROUNDUP((COLUMN()+0)/3-2,0)) = 0,"",INDEX(List_ChargeNumbers_Mobile, 2, ROUNDUP((COLUMN()+0)/3-2,0))&" Name") | N2: =IF(INDEX(List_ChargeNumbers_Mobile, 1, ROUNDUP((COLUMN()+0)/3-2,0)) = 0,"",INDEX(List_ChargeNumbers_Mobile, 2, ROUNDUP((COLUMN()+0)/3-2,0))&" Reading") | O2: =IF(INDEX(List_ChargeNumbers_Mobile, 1, ROUNDUP((COLUMN()+0)/3-2,0)) = 0,"",INDEX(List_ChargeNumbers_Mobile, 2, ROUNDUP((COLUMN()+0)/3-2,0))&" Cost") | P2: =IF(INDEX(List_ChargeNumbers_Mobile, 1, ROUNDUP((COLUMN()+0)/3-2,0)) = 0,"",INDEX(List_ChargeNumbers_Mobile, 2, ROUNDUP((COLUMN()+0)/3-2,0))&" Name") | Q2: =IF(INDEX(List_ChargeNumbers_Mobile, 1, ROUNDUP((COLUMN()+0)/3-2,0)) = 0,"",INDEX(List_ChargeNumbers_Mobile, 2, ROUNDUP((COLUMN()+0)/3-2,0))&" Reading") | R2: =IF(INDEX(List_ChargeNumbers_Mobile, 1, ROUNDUP((COLUMN()+0)/3-2,0)) = 0,"",INDEX(List_ChargeNumbers_Mobile, 2, ROUNDUP((COLUMN()+0)/3-2,0))&" Cost") | S2: =IF(INDEX(List_ChargeNumbers_Mobile, 1, ROUNDUP((COLUMN()+0)/3-2,0)) = 0,"",INDEX(List_ChargeNumbers_Mobile, 2, ROUNDUP((COLUMN()+0)/3-2,0))&" Name") | T2: =IF(INDEX(List_ChargeNumbers_Mobile, 1, ROUNDUP((COLUMN()+0)/3-2,0)) = 0,"",INDEX(List_ChargeNumbers_Mobile, 2, ROUNDUP((COLUMN()+0)/3-2,0))&" Reading") | U2: =IF(INDEX(List_ChargeNumbers_Mobile, 1, ROUNDUP((COLUMN()+0)/3-2,0)) = 0,"",INDEX(List_ChargeNumbers_Mobile, 2, ROUNDUP((COLUMN()+0)/3-2,0))&" Cost")
G3: =IF(ISBLANK($A3),"",INDEX(Array_MobileCharges,MATCH($A3,List_MobileFuelMeters,0),ROUNDUP((COLUMN()+1)/3-2,0))) | J3: =IF(ISBLANK($A3),"",INDEX(Array_MobileCharges,MATCH($A3,List_MobileFuelMeters,0),ROUNDUP((COLUMN()+1)/3-2,0))) | M3: =IF(ISBLANK($A3),"",INDEX(Array_MobileCharges,MATCH($A3,List_MobileFuelMeters,0),ROUNDUP((COLUMN()+1)/3-2,0))) | P3: =IF(ISBLANK($A3),"",INDEX(Array_MobileCharges,MATCH($A3,List_MobileFuelMeters,0),ROUNDUP((COLUMN()+1)/3-2,0))) | S3: =IF(ISBLANK($A3),"",INDEX(Array_MobileCharges,MATCH($A3,List_MobileFuelMeters,0),ROUNDUP((COLUMN()+1)/3-2,0)))
G4: =IF(ISBLANK($A4),"",INDEX(Array_MobileCharges,MATCH($A4,List_MobileFuelMeters,0),ROUNDUP((COLUMN()+1)/3-2,0))) | J4: =IF(ISBLANK($A4),"",INDEX(Array_MobileCharges,MATCH($A4,List_MobileFuelMeters,0),ROUNDUP((COLUMN()+1)/3-2,0))) | M4: =IF(ISBLANK($A4),"",INDEX(Array_MobileCharges,MATCH($A4,List_MobileFuelMeters,0),ROUNDUP((COLUMN()+1)/3-2,0))) | P4: =IF(ISBLANK($A4),"",INDEX(Array_MobileCharges,MATCH($A4,List_MobileFuelMeters,0),ROUNDUP((COLUMN()+1)/3-2,0))) | S4: =IF(ISBLANK($A4),"",INDEX(Array_MobileCharges,MATCH($A4,List_MobileFuelMeters,0),ROUNDUP((COLUMN()+1)/3-2,0)))
G5: =IF(ISBLANK($A5),"",INDEX(Array_MobileCharges,MATCH($A5,List_MobileFuelMeters,0),ROUNDUP((COLUMN()+1)/3-2,0))) | J5: =IF(ISBLANK($A5),"",INDEX(Array_MobileCharges,MATCH($A5,List_MobileFuelMeters,0),ROUNDUP((COLUMN()+1)/3-2,0))) | M5: =IF(ISBLANK($A5),"",INDEX(Array_MobileCharges,MATCH($A5,List_MobileFuelMeters,0),ROUNDUP((COLUMN()+1)/3-2,0))) | P5: =IF(ISBLANK($A5),"",INDEX(Array_MobileCharges,MATCH($A5,List_MobileFuelMeters,0),ROUNDUP((COLUMN()+1)/3-2,0))) | S5: =IF(ISBLANK($A5),"",INDEX(Array_MobileCharges,MATCH($A5,List_MobileFuelMeters,0),ROUNDUP((COLUMN()+1)/3-2,0)))
G6: =IF(ISBLANK($A6),"",INDEX(Array_MobileCharges,MATCH($A6,List_MobileFuelMeters,0),ROUNDUP((COLUMN()+1)/3-2,0))) | J6: =IF(ISBLANK($A6),"",INDEX(Array_MobileCharges,MATCH($A6,List_MobileFuelMeters,0),ROUNDUP((COLUMN()+1)/3-2,0))) | M6: =IF(ISBLANK($A6),"",INDEX(Array_MobileCharges,MATCH($A6,List_MobileFuelMeters,0),ROUNDUP((COLUMN()+1)/3-2,0))) | P6: =IF(ISBLANK($A6),"",INDEX(Array_MobileCharges,MATCH($A6,List_MobileFuelMeters,0),ROUNDUP((COLUMN()+1)/3-2,0))) | S6: =IF(ISBLANK($A6),"",INDEX(Array_MobileCharges,MATCH($A6,List_MobileFuelMeters,0),ROUNDUP((COLUMN()+1)/3-2,0)))
G7: =IF(ISBLANK($A7),"",INDEX(Array_MobileCharges,MATCH($A7,List_MobileFuelMeters,0),ROUNDUP((COLUMN()+1)/3-2,0))) | J7: =IF(ISBLANK($A7),"",INDEX(Array_MobileCharges,MATCH($A7,List_MobileFuelMeters,0),ROUNDUP((COLUMN()+1)/3-2,0))) | M7: =IF(ISBLANK($A7),"",INDEX(Array_MobileCharges,MATCH($A7,List_MobileFuelMeters,0),ROUNDUP((COLUMN()+1)/3-2,0))) | P7: =IF(ISBLANK($A7),"",INDEX(Array_MobileCharges,MATCH($A7,List_MobileFuelMeters,0),ROUNDUP((COLUMN()+1)/3-2,0))) | S7: =IF(ISBLANK($A7),"",INDEX(Array_MobileCharges,MATCH($A7,List_MobileFuelMeters,0),ROUNDUP((COLUMN()+1)/3-2,0)))
G8: =IF(ISBLANK($A8),"",INDEX(Array_MobileCharges,MATCH($A8,List_MobileFuelMeters,0),ROUNDUP((COLUMN()+1)/3-2,0))) | J8: =IF(ISBLANK($A8),"",INDEX(Array_MobileCharges,MATCH($A8,List_MobileFuelMeters,0),ROUNDUP((COLUMN()+1)/3-2,0))) | M8: =IF(ISBLANK($A8),"",INDEX(Array_MobileCharges,MATCH($A8,List_MobileFuelMeters,0),ROUNDUP((COLUMN()+1)/3-2,0))) | P8: =IF(ISBLANK($A8),"",INDEX(Array_MobileCharges,MATCH($A8,List_MobileFuelMeters,0),ROUNDUP((COLUMN()+1)/3-2,0))) | S8: =IF(ISBLANK($A8),"",INDEX(Array_MobileCharges,MATCH($A8,List_MobileFuelMeters,0),ROUNDUP((COLUMN()+1)/3-2,0)))
G9: =IF(ISBLANK($A9),"",INDEX(Array_MobileCharges,MATCH($A9,List_MobileFuelMeters,0),ROUNDUP((COLUMN()+1)/3-2,0))) | J9: =IF(ISBLANK($A9),"",INDEX(Array_MobileCharges,MATCH($A9,List_MobileFuelMeters,0),ROUNDUP((COLUMN()+1)/3-2,0))) | M9: =IF(ISBLANK($A9),"",INDEX(Array_MobileCharges,MATCH($A9,List_MobileFuelMeters,0),ROUNDUP((COLUMN()+1)/3-2,0))) | P9: =IF(ISBLANK($A9),"",INDEX(Array_MobileCharges,MATCH($A9,List_MobileFuelMeters,0),ROUNDUP((COLUMN()+1)/3-2,0))) | S9: =IF(ISBLANK($A9),"",INDEX(Array_MobileCharges,MATCH($A9,List_MobileFuelMeters,0),ROUNDUP((COLUMN()+1)/3-2,0)))
G10: =IF(ISBLANK($A10),"",INDEX(Array_MobileCharges,MATCH($A10,List_MobileFuelMeters,0),ROUNDUP((COLUMN()+1)/3-2,0))) | J10: =IF(ISBLANK($A10),"",INDEX(Array_MobileCharges,MATCH($A10,List_MobileFuelMeters,0),ROUNDUP((COLUMN()+1)/3-2,0))) | M10: =IF(ISBLANK($A10),"",INDEX(Array_MobileCharges,MATCH($A10,List_MobileFuelMeters,0),ROUNDUP((COLUMN()+1)/3-2,0))) | P10: =IF(ISBLANK($A10),"",INDEX(Array_MobileCharges,MATCH($A10,List_MobileFuelMeters,0),ROUNDUP((COLUMN()+1)/3-2,0))) | S10: =IF(ISBLANK($A10),"",INDEX(Array_MobileCharges,MATCH($A10,List_MobileFuelMeters,0),ROUNDUP((COLUMN()+1)/3-2,0)))
G11: =IF(ISBLANK($A11),"",INDEX(Array_MobileCharges,MATCH($A11,List_MobileFuelMeters,0),ROUNDUP((COLUMN()+1)/3-2,0))) | J11: =IF(ISBLANK($A11),"",INDEX(Array_MobileCharges,MATCH($A11,List_MobileFuelMeters,0),ROUNDUP((COLUMN()+1)/3-2,0))) | M11: =IF(ISBLANK($A11),"",INDEX(Array_MobileCharges,MATCH($A11,List_MobileFuelMeters,0),ROUNDUP((COLUMN()+1)/3-2,0))) | P11: =IF(ISBLANK($A11),"",INDEX(Array_MobileCharges,MATCH($A11,List_MobileFuelMeters,0),ROUNDUP((COLUMN()+1)/3-2,0))) | S11: =IF(ISBLANK($A11),"",INDEX(Array_MobileCharges,MATCH($A11,List_MobileFuelMeters,0),ROUNDUP((COLUMN()+1)/3-2,0)))
G12: =IF(ISBLANK($A12),"",INDEX(Array_MobileCharges,MATCH($A12,List_MobileFuelMeters,0),ROUNDUP((COLUMN()+1)/3-2,0))) | J12: =IF(ISBLANK($A12),"",INDEX(Array_MobileCharges,MATCH($A12,List_MobileFuelMeters,0),ROUNDUP((COLUMN()+1)/3-2,0))) | M12: =IF(ISBLANK($A12),"",INDEX(Array_MobileCharges,MATCH($A12,List_MobileFuelMeters,0),ROUNDUP((COLUMN()+1)/3-2,0))) | P12: =IF(ISBLANK($A12),"",INDEX(Array_MobileCharges,MATCH($A12,List_MobileFuelMeters,0),ROUNDUP((COLUMN()+1)/3-2,0))) | S12: =IF(ISBLANK($A12),"",INDEX(Array_MobileCharges,MATCH($A12,List_MobileFuelMeters,0),ROUNDUP((COLUMN()+1)/3-2,0)))
G13: =IF(ISBLANK($A13),"",INDEX(Array_MobileCharges,MATCH($A13,List_MobileFuelMeters,0),ROUNDUP((COLUMN()+1)/3-2,0))) | J13: =IF(ISBLANK($A13),"",INDEX(Array_MobileCharges,MATCH($A13,List_MobileFuelMeters,0),ROUNDUP((COLUMN()+1)/3-2,0))) | M13: =IF(ISBLANK($A13),"",INDEX(Array_MobileCharges,MATCH($A13,List_MobileFuelMeters,0),ROUNDUP((COLUMN()+1)/3-2,0))) | P13: =IF(ISBLANK($A13),"",INDEX(Array_MobileCharges,MATCH($A13,List_MobileFuelMeters,0),ROUNDUP((COLUMN()+1)/3-2,0))) | S13: =IF(ISBLANK($A13),"",INDEX(Array_MobileCharges,MATCH($A13,List_MobileFuelMeters,0),ROUNDUP((COLUMN()+1)/3-2,0)))
G14: =IF(ISBLANK($A14),"",INDEX(Array_MobileCharges,MATCH($A14,List_MobileFuelMeters,0),ROUNDUP((COLUMN()+1)/3-2,0))) | J14: =IF(ISBLANK($A14),"",INDEX(Array_MobileCharges,MATCH($A14,List_MobileFuelMeters,0),ROUNDUP((COLUMN()+1)/3-2,0))) | M14: =IF(ISBLANK($A14),"",INDEX(Array_MobileCharges,MATCH($A14,List_MobileFuelMeters,0),ROUNDUP((COLUMN()+1)/3-2,0))) | P14: =IF(ISBLANK($A14),"",INDEX(Array_MobileCharges,MATCH($A14,List_MobileFuelMeters,0),ROUNDUP((COLUMN()+1)/3-2,0))) | S14: =IF(ISBLANK($A14),"",INDEX(Array_MobileCharges,MATCH($A14,List_MobileFuelMeters,0),ROUNDUP((COLUMN()+1)/3-2,0)))
... G502: =IF(ISBLANK($A502),"",INDEX(Array_MobileCharges,MATCH($A502,List_MobileFuelMeters,0),ROUNDUP((COLUMN()+1)/3-2,0))) | J502: =IF(ISBLANK($A502),"",INDEX(Array_MobileCharges,MATCH($A502,List_MobileFuelMeters,0),ROUNDUP((COLUMN()+1)/3-2,0))) | M502: =IF(ISBLANK($A502),"",INDEX(Array_MobileCharges,MATCH($A502,List_MobileFuelMeters,0),ROUNDUP((COLUMN()+1)/3-2,0))) | P502: =IF(ISBLANK($A502),"",INDEX(Array_MobileCharges,MATCH($A502,List_MobileFuelMeters,0),ROUNDUP((COLUMN()+1)/3-2,0))) | S502: =IF(ISBLANK($A502),"",INDEX(Array_MobileCharges,MATCH($A502,List_MobileFuelMeters,0),ROUNDUP((COLUMN()+1)/3-2,0)))

Sheet HIDE_MOBILE
A1: Vehicle Types | B1: On Road Fuels | C1: Off Road Fuels | D1: Non Road Fuels | E1: FuelMaterial | F1: Units Usage | G1: Units Distance | H1: Units Energy | I1: Charge Types
A2: Material Transport Onsite | B2: Gasoline | C2: Gasoline (2 stroke) | D2: Jet Fuel | E2: Propane | F2: gal | G2: mi | H2: kWh | I2: Usage
A3: On-Road Vehicle, Passenger Cars | B3: Diesel | C3: Gasoline (4 stroke) | D3: Aviation Gasoline | E3: Diesel | F3: kgal | G3: km | H3: MWh | I3: Tax
A4: On-Road Vehicle, Light-Duty Trucks | B4: Ethanol (100%) | C4: Diesel | D4: Diesel | E4: Gasoline | F4: Mgal | H4: MMBtu | I4: Late Fee
A5: On-Road Vehicle, Bus | B5: LPG | C5: LPG | D5: Residual Fuel Oil | F5: ft3 | H5: GJ | I5: Flat Fee
A6: On-Road Vehicle, Heavy-Duty Trucks | B6: Biodiesel (100%) | D6: Gasoline | F6: m3 | H6: MJ | I6: Other
A7: On-Road Vehicle, Motorcycles | F7: L | H7: kJ
A8: Off-Road Vehicle, Ag. Equipment & Trucks | H8: Therms
A9: Off-Road Vehicle, Construction/Mine Equipment & Trucks | H9: DTherms
A10: Non-Road Vehicle, Aircraft | H10: kcal
A11: Non-Road Vehicle, Rail
A12: Non-Road Vehicle, Water Transport
A14: Charge count: | B14: =COUNTIF(B16:B115,"?*") -> 0 | C14: =COUNTIF(C16:C115,"?*") -> 0 | D14: =COUNTIF(D16:D115,"?*") -> 0 | E14: =COUNTIF(E16:E115,"?*") -> 0 | F14: =COUNTIF(F16:F115,"?*") -> 0
A15: Meter Numbers | B15: Charge 1 | C15: Charge 2 | D15: Charge 3 | E15: Charge 4 | F15: Charge 5
A16: =IF('Mobile Fuel Meters'!B3="",A15,'Mobile Fuel Meters'!B3) -> Meter Numbers | B16: =IF(ISBLANK(INDEX(Array_MobileChargeData,ROW()-15,COLUMN()*2-3)),"",INDEX(Array_MobileChargeData,ROW()-15,COLUMN()*2-3)) | C16: =IF(ISBLANK(INDEX(Array_MobileChargeData,ROW()-15,COLUMN()*2-3)),"",INDEX(Array_MobileChargeData,ROW()-15,COLUMN()*2-3)) | D16: =IF(ISBLANK(INDEX(Array_MobileChargeData,ROW()-15,COLUMN()*2-3)),"",INDEX(Array_MobileChargeData,ROW()-15,COLUMN()*2-3)) | E16: =IF(ISBLANK(INDEX(Array_MobileChargeData,ROW()-15,COLUMN()*2-3)),"",INDEX(Array_MobileChargeData,ROW()-15,COLUMN()*2-3)) | F16: =IF(ISBLANK(INDEX(Array_MobileChargeData,ROW()-15,COLUMN()*2-3)),"",INDEX(Array_MobileChargeData,ROW()-15,COLUMN()*2-3))
A17: =IF('Mobile Fuel Meters'!B4="",A16,'Mobile Fuel Meters'!B4) -> Meter Numbers | B17: =IF(ISBLANK(INDEX(Array_MobileChargeData,ROW()-15,COLUMN()*2-3)),"",INDEX(Array_MobileChargeData,ROW()-15,COLUMN()*2-3)) | C17: =IF(ISBLANK(INDEX(Array_MobileChargeData,ROW()-15,COLUMN()*2-3)),"",INDEX(Array_MobileChargeData,ROW()-15,COLUMN()*2-3)) | D17: =IF(ISBLANK(INDEX(Array_MobileChargeData,ROW()-15,COLUMN()*2-3)),"",INDEX(Array_MobileChargeData,ROW()-15,COLUMN()*2-3)) | E17: =IF(ISBLANK(INDEX(Array_MobileChargeData,ROW()-15,COLUMN()*2-3)),"",INDEX(Array_MobileChargeData,ROW()-15,COLUMN()*2-3)) | F17: =IF(ISBLANK(INDEX(Array_MobileChargeData,ROW()-15,COLUMN()*2-3)),"",INDEX(Array_MobileChargeData,ROW()-15,COLUMN()*2-3))
A18: =IF('Mobile Fuel Meters'!B5="",A17,'Mobile Fuel Meters'!B5) -> Meter Numbers | B18: =IF(ISBLANK(INDEX(Array_MobileChargeData,ROW()-15,COLUMN()*2-3)),"",INDEX(Array_MobileChargeData,ROW()-15,COLUMN()*2-3)) | C18: =IF(ISBLANK(INDEX(Array_MobileChargeData,ROW()-15,COLUMN()*2-3)),"",INDEX(Array_MobileChargeData,ROW()-15,COLUMN()*2-3)) | D18: =IF(ISBLANK(INDEX(Array_MobileChargeData,ROW()-15,COLUMN()*2-3)),"",INDEX(Array_MobileChargeData,ROW()-15,COLUMN()*2-3)) | E18: =IF(ISBLANK(INDEX(Array_MobileChargeData,ROW()-15,COLUMN()*2-3)),"",INDEX(Array_MobileChargeData,ROW()-15,COLUMN()*2-3)) | F18: =IF(ISBLANK(INDEX(Array_MobileChargeData,ROW()-15,COLUMN()*2-3)),"",INDEX(Array_MobileChargeData,ROW()-15,COLUMN()*2-3))
A19: =IF('Mobile Fuel Meters'!B6="",A18,'Mobile Fuel Meters'!B6) -> Meter Numbers | B19: =IF(ISBLANK(INDEX(Array_MobileChargeData,ROW()-15,COLUMN()*2-3)),"",INDEX(Array_MobileChargeData,ROW()-15,COLUMN()*2-3)) | C19: =IF(ISBLANK(INDEX(Array_MobileChargeData,ROW()-15,COLUMN()*2-3)),"",INDEX(Array_MobileChargeData,ROW()-15,COLUMN()*2-3)) | D19: =IF(ISBLANK(INDEX(Array_MobileChargeData,ROW()-15,COLUMN()*2-3)),"",INDEX(Array_MobileChargeData,ROW()-15,COLUMN()*2-3)) | E19: =IF(ISBLANK(INDEX(Array_MobileChargeData,ROW()-15,COLUMN()*2-3)),"",INDEX(Array_MobileChargeData,ROW()-15,COLUMN()*2-3)) | F19: =IF(ISBLANK(INDEX(Array_MobileChargeData,ROW()-15,COLUMN()*2-3)),"",INDEX(Array_MobileChargeData,ROW()-15,COLUMN()*2-3))
A20: =IF('Mobile Fuel Meters'!B7="",A19,'Mobile Fuel Meters'!B7) -> Meter Numbers | B20: =IF(ISBLANK(INDEX(Array_MobileChargeData,ROW()-15,COLUMN()*2-3)),"",INDEX(Array_MobileChargeData,ROW()-15,COLUMN()*2-3)) | C20: =IF(ISBLANK(INDEX(Array_MobileChargeData,ROW()-15,COLUMN()*2-3)),"",INDEX(Array_MobileChargeData,ROW()-15,COLUMN()*2-3)) | D20: =IF(ISBLANK(INDEX(Array_MobileChargeData,ROW()-15,COLUMN()*2-3)),"",INDEX(Array_MobileChargeData,ROW()-15,COLUMN()*2-3)) | E20: =IF(ISBLANK(INDEX(Array_MobileChargeData,ROW()-15,COLUMN()*2-3)),"",INDEX(Array_MobileChargeData,ROW()-15,COLUMN()*2-3)) | F20: =IF(ISBLANK(INDEX(Array_MobileChargeData,ROW()-15,COLUMN()*2-3)),"",INDEX(Array_MobileChargeData,ROW()-15,COLUMN()*2-3))
A21: =IF('Mobile Fuel Meters'!B8="",A20,'Mobile Fuel Meters'!B8) -> Meter Numbers | B21: =IF(ISBLANK(INDEX(Array_MobileChargeData,ROW()-15,COLUMN()*2-3)),"",INDEX(Array_MobileChargeData,ROW()-15,COLUMN()*2-3)) | C21: =IF(ISBLANK(INDEX(Array_MobileChargeData,ROW()-15,COLUMN()*2-3)),"",INDEX(Array_MobileChargeData,ROW()-15,COLUMN()*2-3)) | D21: =IF(ISBLANK(INDEX(Array_MobileChargeData,ROW()-15,COLUMN()*2-3)),"",INDEX(Array_MobileChargeData,ROW()-15,COLUMN()*2-3)) | E21: =IF(ISBLANK(INDEX(Array_MobileChargeData,ROW()-15,COLUMN()*2-3)),"",INDEX(Array_MobileChargeData,ROW()-15,COLUMN()*2-3)) | F21: =IF(ISBLANK(INDEX(Array_MobileChargeData,ROW()-15,COLUMN()*2-3)),"",INDEX(Array_MobileChargeData,ROW()-15,COLUMN()*2-3))
A22: =IF('Mobile Fuel Meters'!B9="",A21,'Mobile Fuel Meters'!B9) -> Meter Numbers | B22: =IF(ISBLANK(INDEX(Array_MobileChargeData,ROW()-15,COLUMN()*2-3)),"",INDEX(Array_MobileChargeData,ROW()-15,COLUMN()*2-3)) | C22: =IF(ISBLANK(INDEX(Array_MobileChargeData,ROW()-15,COLUMN()*2-3)),"",INDEX(Array_MobileChargeData,ROW()-15,COLUMN()*2-3)) | D22: =IF(ISBLANK(INDEX(Array_MobileChargeData,ROW()-15,COLUMN()*2-3)),"",INDEX(Array_MobileChargeData,ROW()-15,COLUMN()*2-3)) | E22: =IF(ISBLANK(INDEX(Array_MobileChargeData,ROW()-15,COLUMN()*2-3)),"",INDEX(Array_MobileChargeData,ROW()-15,COLUMN()*2-3)) | F22: =IF(ISBLANK(INDEX(Array_MobileChargeData,ROW()-15,COLUMN()*2-3)),"",INDEX(Array_MobileChargeData,ROW()-15,COLUMN()*2-3))
A23: =IF('Mobile Fuel Meters'!B10="",A22,'Mobile Fuel Meters'!B10) -> Meter Numbers | B23: =IF(ISBLANK(INDEX(Array_MobileChargeData,ROW()-15,COLUMN()*2-3)),"",INDEX(Array_MobileChargeData,ROW()-15,COLUMN()*2-3)) | C23: =IF(ISBLANK(INDEX(Array_MobileChargeData,ROW()-15,COLUMN()*2-3)),"",INDEX(Array_MobileChargeData,ROW()-15,COLUMN()*2-3)) | D23: =IF(ISBLANK(INDEX(Array_MobileChargeData,ROW()-15,COLUMN()*2-3)),"",INDEX(Array_MobileChargeData,ROW()-15,COLUMN()*2-3)) | E23: =IF(ISBLANK(INDEX(Array_MobileChargeData,ROW()-15,COLUMN()*2-3)),"",INDEX(Array_MobileChargeData,ROW()-15,COLUMN()*2-3)) | F23: =IF(ISBLANK(INDEX(Array_MobileChargeData,ROW()-15,COLUMN()*2-3)),"",INDEX(Array_MobileChargeData,ROW()-15,COLUMN()*2-3))
A24: =IF('Mobile Fuel Meters'!B11="",A23,'Mobile Fuel Meters'!B11) -> Meter Numbers | B24: =IF(ISBLANK(INDEX(Array_MobileChargeData,ROW()-15,COLUMN()*2-3)),"",INDEX(Array_MobileChargeData,ROW()-15,COLUMN()*2-3)) | C24: =IF(ISBLANK(INDEX(Array_MobileChargeData,ROW()-15,COLUMN()*2-3)),"",INDEX(Array_MobileChargeData,ROW()-15,COLUMN()*2-3)) | D24: =IF(ISBLANK(INDEX(Array_MobileChargeData,ROW()-15,COLUMN()*2-3)),"",INDEX(Array_MobileChargeData,ROW()-15,COLUMN()*2-3)) | E24: =IF(ISBLANK(INDEX(Array_MobileChargeData,ROW()-15,COLUMN()*2-3)),"",INDEX(Array_MobileChargeData,ROW()-15,COLUMN()*2-3)) | F24: =IF(ISBLANK(INDEX(Array_MobileChargeData,ROW()-15,COLUMN()*2-3)),"",INDEX(Array_MobileChargeData,ROW()-15,COLUMN()*2-3))
A25: =IF('Mobile Fuel Meters'!B12="",A24,'Mobile Fuel Meters'!B12) -> Meter Numbers | B25: =IF(ISBLANK(INDEX(Array_MobileChargeData,ROW()-15,COLUMN()*2-3)),"",INDEX(Array_MobileChargeData,ROW()-15,COLUMN()*2-3)) | C25: =IF(ISBLANK(INDEX(Array_MobileChargeData,ROW()-15,COLUMN()*2-3)),"",INDEX(Array_MobileChargeData,ROW()-15,COLUMN()*2-3)) | D25: =IF(ISBLANK(INDEX(Array_MobileChargeData,ROW()-15,COLUMN()*2-3)),"",INDEX(Array_MobileChargeData,ROW()-15,COLUMN()*2-3)) | E25: =IF(ISBLANK(INDEX(Array_MobileChargeData,ROW()-15,COLUMN()*2-3)),"",INDEX(Array_MobileChargeData,ROW()-15,COLUMN()*2-3)) | F25: =IF(ISBLANK(INDEX(Array_MobileChargeData,ROW()-15,COLUMN()*2-3)),"",INDEX(Array_MobileChargeData,ROW()-15,COLUMN()*2-3))
A26: =IF('Mobile Fuel Meters'!B13="",A25,'Mobile Fuel Meters'!B13) -> Meter Numbers | B26: =IF(ISBLANK(INDEX(Array_MobileChargeData,ROW()-15,COLUMN()*2-3)),"",INDEX(Array_MobileChargeData,ROW()-15,COLUMN()*2-3)) | C26: =IF(ISBLANK(INDEX(Array_MobileChargeData,ROW()-15,COLUMN()*2-3)),"",INDEX(Array_MobileChargeData,ROW()-15,COLUMN()*2-3)) | D26: =IF(ISBLANK(INDEX(Array_MobileChargeData,ROW()-15,COLUMN()*2-3)),"",INDEX(Array_MobileChargeData,ROW()-15,COLUMN()*2-3)) | E26: =IF(ISBLANK(INDEX(Array_MobileChargeData,ROW()-15,COLUMN()*2-3)),"",INDEX(Array_MobileChargeData,ROW()-15,COLUMN()*2-3)) | F26: =IF(ISBLANK(INDEX(Array_MobileChargeData,ROW()-15,COLUMN()*2-3)),"",INDEX(Array_MobileChargeData,ROW()-15,COLUMN()*2-3))
A27: =IF('Mobile Fuel Meters'!B14="",A26,'Mobile Fuel Meters'!B14) -> Meter Numbers | B27: =IF(ISBLANK(INDEX(Array_MobileChargeData,ROW()-15,COLUMN()*2-3)),"",INDEX(Array_MobileChargeData,ROW()-15,COLUMN()*2-3)) | C27: =IF(ISBLANK(INDEX(Array_MobileChargeData,ROW()-15,COLUMN()*2-3)),"",INDEX(Array_MobileChargeData,ROW()-15,COLUMN()*2-3)) | D27: =IF(ISBLANK(INDEX(Array_MobileChargeData,ROW()-15,COLUMN()*2-3)),"",INDEX(Array_MobileChargeData,ROW()-15,COLUMN()*2-3)) | E27: =IF(ISBLANK(INDEX(Array_MobileChargeData,ROW()-15,COLUMN()*2-3)),"",INDEX(Array_MobileChargeData,ROW()-15,COLUMN()*2-3)) | F27: =IF(ISBLANK(INDEX(Array_MobileChargeData,ROW()-15,COLUMN()*2-3)),"",INDEX(Array_MobileChargeData,ROW()-15,COLUMN()*2-3))
... A215: =IF('Mobile Fuel Meters'!B202="",A214,'Mobile Fuel Meters'!B202) -> Meter Numbers | B215: =IF(ISBLANK(INDEX(Array_MobileChargeData,ROW()-15,COLUMN()*2-3)),"",INDEX(Array_MobileChargeData,ROW()-15,COLUMN()*2-3)) | C215: =IF(ISBLANK(INDEX(Array_MobileChargeData,ROW()-15,COLUMN()*2-3)),"",INDEX(Array_MobileChargeData,ROW()-15,COLUMN()*2-3)) | D215: =IF(ISBLANK(INDEX(Array_MobileChargeData,ROW()-15,COLUMN()*2-3)),"",INDEX(Array_MobileChargeData,ROW()-15,COLUMN()*2-3)) | E215: =IF(ISBLANK(INDEX(Array_MobileChargeData,ROW()-15,COLUMN()*2-3)),"",INDEX(Array_MobileChargeData,ROW()-15,COLUMN()*2-3)) | F215: =IF(ISBLANK(INDEX(Array_MobileChargeData,ROW()-15,COLUMN()*2-3)),"",INDEX(Array_MobileChargeData,ROW()-15,COLUMN()*2-3))

Sheet Other Energy Meters
A1: √ Other Energy Meters Setup | O1: √ Other Energy Charge Setup (Optional)
A2: Facility Name | B2: Meter Number (UNIQUE) | C2: Meter Name (DISPLAY) | D2: Meter Group (ANALYSIS) | E2: Calendarize Readings? | F2: Type | G2: Unit (COLLECTION) | H2: S2S Factor | I2: Energy Factor | J2: Unit (ENERGY) | K2: Account # | L2: Supplier | M2: Location | N2: Notes | O2: ="Charge "&QUOTIENT(COLUMN()-13,2)&" Name" -> Charge 1 Name | P2: ="Charge "&QUOTIENT(COLUMN()-13,2)&" Type" -> Charge 1 Type | Q2: ="Charge "&QUOTIENT(COLUMN()-13,2)&" Name" -> Charge 2 Name | R2: ="Charge "&QUOTIENT(COLUMN()-13,2)&" Type" -> Charge 2 Type | S2: ="Charge "&QUOTIENT(COLUMN()-13,2)&" Name" -> Charge 3 Name | T2: ="Charge "&QUOTIENT(COLUMN()-13,2)&" Type" -> Charge 3 Type | U2: ="Charge "&QUOTIENT(COLUMN()-13,2)&" Name" -> Charge 4 Name | V2: ="Charge "&QUOTIENT(COLUMN()-13,2)&" Type" -> Charge 4 Type | W2: ="Charge "&QUOTIENT(COLUMN()-13,2)&" Name" -> Charge 5 Name | X2: ="Charge "&QUOTIENT(COLUMN()-13,2)&" Type" -> Charge 5 Type

Sheet Other Energy
A1: √ Other Energy Readings | F1: √ Other Energy Charges (Optional)
A2: Meter Number | B2: Read Date | C2: Total Usage | D2: Energy Factor | E2: Total Cost ($) | F2: =IF(INDEX(List_ChargeNumbers_OtherEnergy, 1, ROUNDUP((COLUMN()-0)/3-1,0)) = 0,"",INDEX(List_ChargeNumbers_OtherEnergy, 2, ROUNDUP((COLUMN()+0)/3-1,0))&" Name") | G2: =IF(INDEX(List_ChargeNumbers_OtherEnergy, 1, ROUNDUP((COLUMN()-0)/3-2,0)) = 0,"",INDEX(List_ChargeNumbers_OtherEnergy, 2, ROUNDUP((COLUMN()+0)/3-2,0))&" Reading") | H2: =IF(INDEX(List_ChargeNumbers_OtherEnergy, 1, ROUNDUP((COLUMN()-0)/3-2,0)) = 0,"",INDEX(List_ChargeNumbers_OtherEnergy, 2, ROUNDUP((COLUMN()+0)/3-2,0))&" Cost") | I2: =IF(INDEX(List_ChargeNumbers_OtherEnergy, 1, ROUNDUP((COLUMN()-0)/3-1,0)) = 0,"",INDEX(List_ChargeNumbers_OtherEnergy, 2, ROUNDUP((COLUMN()+0)/3-1,0))&" Name") | J2: =IF(INDEX(List_ChargeNumbers_OtherEnergy, 1, ROUNDUP((COLUMN()-0)/3-2,0)) = 0,"",INDEX(List_ChargeNumbers_OtherEnergy, 2, ROUNDUP((COLUMN()+0)/3-2,0))&" Reading") | K2: =IF(INDEX(List_ChargeNumbers_OtherEnergy, 1, ROUNDUP((COLUMN()-0)/3-2,0)) = 0,"",INDEX(List_ChargeNumbers_OtherEnergy, 2, ROUNDUP((COLUMN()+0)/3-2,0))&" Cost") | L2: =IF(INDEX(List_ChargeNumbers_OtherEnergy, 1, ROUNDUP((COLUMN()-0)/3-1,0)) = 0,"",INDEX(List_ChargeNumbers_OtherEnergy, 2, ROUNDUP((COLUMN()+0)/3-1,0))&" Name") | M2: =IF(INDEX(List_ChargeNumbers_OtherEnergy, 1, ROUNDUP((COLUMN()-0)/3-2,0)) = 0,"",INDEX(List_ChargeNumbers_OtherEnergy, 2, ROUNDUP((COLUMN()+0)/3-2,0))&" Reading") | N2: =IF(INDEX(List_ChargeNumbers_OtherEnergy, 1, ROUNDUP((COLUMN()-0)/3-2,0)) = 0,"",INDEX(List_ChargeNumbers_OtherEnergy, 2, ROUNDUP((COLUMN()+0)/3-2,0))&" Cost") | O2: =IF(INDEX(List_ChargeNumbers_OtherEnergy, 1, ROUNDUP((COLUMN()-0)/3-1,0)) = 0,"",INDEX(List_ChargeNumbers_OtherEnergy, 2, ROUNDUP((COLUMN()+0)/3-1,0))&" Name") | P2: =IF(INDEX(List_ChargeNumbers_OtherEnergy, 1, ROUNDUP((COLUMN()-0)/3-2,0)) = 0,"",INDEX(List_ChargeNumbers_OtherEnergy, 2, ROUNDUP((COLUMN()+0)/3-2,0))&" Reading") | Q2: =IF(INDEX(List_ChargeNumbers_OtherEnergy, 1, ROUNDUP((COLUMN()-0)/3-2,0)) = 0,"",INDEX(List_ChargeNumbers_OtherEnergy, 2, ROUNDUP((COLUMN()+0)/3-2,0))&" Cost") | R2: =IF(INDEX(List_ChargeNumbers_OtherEnergy, 1, ROUNDUP((COLUMN()-0)/3-1,0)) = 0,"",INDEX(List_ChargeNumbers_OtherEnergy, 2, ROUNDUP((COLUMN()+0)/3-1,0))&" Name") | S2: =IF(INDEX(List_ChargeNumbers_OtherEnergy, 1, ROUNDUP((COLUMN()-0)/3-2,0)) = 0,"",INDEX(List_ChargeNumbers_OtherEnergy, 2, ROUNDUP((COLUMN()+0)/3-2,0))&" Reading") | T2: =IF(INDEX(List_ChargeNumbers_OtherEnergy, 1, ROUNDUP((COLUMN()-0)/3-2,0)) = 0,"",INDEX(List_ChargeNumbers_OtherEnergy, 2, ROUNDUP((COLUMN()+0)/3-2,0))&" Cost")
F3: =IF(ISBLANK($A3),"",INDEX(Array_OtherEnergyCharges,MATCH($A3,List_OtherEnergyMeters,0),ROUNDUP((COLUMN()+1)/3-2,0))) | I3: =IF(ISBLANK($A3),"",INDEX(Array_OtherEnergyCharges,MATCH($A3,List_OtherEnergyMeters,0),ROUNDUP((COLUMN()+1)/3-2,0))) | L3: =IF(ISBLANK($A3),"",INDEX(Array_OtherEnergyCharges,MATCH($A3,List_OtherEnergyMeters,0),ROUNDUP((COLUMN()+1)/3-2,0))) | O3: =IF(ISBLANK($A3),"",INDEX(Array_OtherEnergyCharges,MATCH($A3,List_OtherEnergyMeters,0),ROUNDUP((COLUMN()+1)/3-2,0))) | R3: =IF(ISBLANK($A3),"",INDEX(Array_OtherEnergyCharges,MATCH($A3,List_OtherEnergyMeters,0),ROUNDUP((COLUMN()+1)/3-2,0)))
F4: =IF(ISBLANK($A4),"",INDEX(Array_OtherEnergyCharges,MATCH($A4,List_OtherEnergyMeters,0),ROUNDUP((COLUMN()+1)/3-2,0))) | I4: =IF(ISBLANK($A4),"",INDEX(Array_OtherEnergyCharges,MATCH($A4,List_OtherEnergyMeters,0),ROUNDUP((COLUMN()+1)/3-2,0))) | L4: =IF(ISBLANK($A4),"",INDEX(Array_OtherEnergyCharges,MATCH($A4,List_OtherEnergyMeters,0),ROUNDUP((COLUMN()+1)/3-2,0))) | O4: =IF(ISBLANK($A4),"",INDEX(Array_OtherEnergyCharges,MATCH($A4,List_OtherEnergyMeters,0),ROUNDUP((COLUMN()+1)/3-2,0))) | R4: =IF(ISBLANK($A4),"",INDEX(Array_OtherEnergyCharges,MATCH($A4,List_OtherEnergyMeters,0),ROUNDUP((COLUMN()+1)/3-2,0)))
F5: =IF(ISBLANK($A5),"",INDEX(Array_OtherEnergyCharges,MATCH($A5,List_OtherEnergyMeters,0),ROUNDUP((COLUMN()+1)/3-2,0))) | I5: =IF(ISBLANK($A5),"",INDEX(Array_OtherEnergyCharges,MATCH($A5,List_OtherEnergyMeters,0),ROUNDUP((COLUMN()+1)/3-2,0))) | L5: =IF(ISBLANK($A5),"",INDEX(Array_OtherEnergyCharges,MATCH($A5,List_OtherEnergyMeters,0),ROUNDUP((COLUMN()+1)/3-2,0))) | O5: =IF(ISBLANK($A5),"",INDEX(Array_OtherEnergyCharges,MATCH($A5,List_OtherEnergyMeters,0),ROUNDUP((COLUMN()+1)/3-2,0))) | R5: =IF(ISBLANK($A5),"",INDEX(Array_OtherEnergyCharges,MATCH($A5,List_OtherEnergyMeters,0),ROUNDUP((COLUMN()+1)/3-2,0)))
F6: =IF(ISBLANK($A6),"",INDEX(Array_OtherEnergyCharges,MATCH($A6,List_OtherEnergyMeters,0),ROUNDUP((COLUMN()+1)/3-2,0))) | I6: =IF(ISBLANK($A6),"",INDEX(Array_OtherEnergyCharges,MATCH($A6,List_OtherEnergyMeters,0),ROUNDUP((COLUMN()+1)/3-2,0))) | L6: =IF(ISBLANK($A6),"",INDEX(Array_OtherEnergyCharges,MATCH($A6,List_OtherEnergyMeters,0),ROUNDUP((COLUMN()+1)/3-2,0))) | O6: =IF(ISBLANK($A6),"",INDEX(Array_OtherEnergyCharges,MATCH($A6,List_OtherEnergyMeters,0),ROUNDUP((COLUMN()+1)/3-2,0))) | R6: =IF(ISBLANK($A6),"",INDEX(Array_OtherEnergyCharges,MATCH($A6,List_OtherEnergyMeters,0),ROUNDUP((COLUMN()+1)/3-2,0)))
F7: =IF(ISBLANK($A7),"",INDEX(Array_OtherEnergyCharges,MATCH($A7,List_OtherEnergyMeters,0),ROUNDUP((COLUMN()+1)/3-2,0))) | I7: =IF(ISBLANK($A7),"",INDEX(Array_OtherEnergyCharges,MATCH($A7,List_OtherEnergyMeters,0),ROUNDUP((COLUMN()+1)/3-2,0))) | L7: =IF(ISBLANK($A7),"",INDEX(Array_OtherEnergyCharges,MATCH($A7,List_OtherEnergyMeters,0),ROUNDUP((COLUMN()+1)/3-2,0))) | O7: =IF(ISBLANK($A7),"",INDEX(Array_OtherEnergyCharges,MATCH($A7,List_OtherEnergyMeters,0),ROUNDUP((COLUMN()+1)/3-2,0))) | R7: =IF(ISBLANK($A7),"",INDEX(Array_OtherEnergyCharges,MATCH($A7,List_OtherEnergyMeters,0),ROUNDUP((COLUMN()+1)/3-2,0)))
F8: =IF(ISBLANK($A8),"",INDEX(Array_OtherEnergyCharges,MATCH($A8,List_OtherEnergyMeters,0),ROUNDUP((COLUMN()+1)/3-2,0))) | I8: =IF(ISBLANK($A8),"",INDEX(Array_OtherEnergyCharges,MATCH($A8,List_OtherEnergyMeters,0),ROUNDUP((COLUMN()+1)/3-2,0))) | L8: =IF(ISBLANK($A8),"",INDEX(Array_OtherEnergyCharges,MATCH($A8,List_OtherEnergyMeters,0),ROUNDUP((COLUMN()+1)/3-2,0))) | O8: =IF(ISBLANK($A8),"",INDEX(Array_OtherEnergyCharges,MATCH($A8,List_OtherEnergyMeters,0),ROUNDUP((COLUMN()+1)/3-2,0))) | R8: =IF(ISBLANK($A8),"",INDEX(Array_OtherEnergyCharges,MATCH($A8,List_OtherEnergyMeters,0),ROUNDUP((COLUMN()+1)/3-2,0)))
F9: =IF(ISBLANK($A9),"",INDEX(Array_OtherEnergyCharges,MATCH($A9,List_OtherEnergyMeters,0),ROUNDUP((COLUMN()+1)/3-2,0))) | I9: =IF(ISBLANK($A9),"",INDEX(Array_OtherEnergyCharges,MATCH($A9,List_OtherEnergyMeters,0),ROUNDUP((COLUMN()+1)/3-2,0))) | L9: =IF(ISBLANK($A9),"",INDEX(Array_OtherEnergyCharges,MATCH($A9,List_OtherEnergyMeters,0),ROUNDUP((COLUMN()+1)/3-2,0))) | O9: =IF(ISBLANK($A9),"",INDEX(Array_OtherEnergyCharges,MATCH($A9,List_OtherEnergyMeters,0),ROUNDUP((COLUMN()+1)/3-2,0))) | R9: =IF(ISBLANK($A9),"",INDEX(Array_OtherEnergyCharges,MATCH($A9,List_OtherEnergyMeters,0),ROUNDUP((COLUMN()+1)/3-2,0)))
F10: =IF(ISBLANK($A10),"",INDEX(Array_OtherEnergyCharges,MATCH($A10,List_OtherEnergyMeters,0),ROUNDUP((COLUMN()+1)/3-2,0))) | I10: =IF(ISBLANK($A10),"",INDEX(Array_OtherEnergyCharges,MATCH($A10,List_OtherEnergyMeters,0),ROUNDUP((COLUMN()+1)/3-2,0))) | L10: =IF(ISBLANK($A10),"",INDEX(Array_OtherEnergyCharges,MATCH($A10,List_OtherEnergyMeters,0),ROUNDUP((COLUMN()+1)/3-2,0))) | O10: =IF(ISBLANK($A10),"",INDEX(Array_OtherEnergyCharges,MATCH($A10,List_OtherEnergyMeters,0),ROUNDUP((COLUMN()+1)/3-2,0))) | R10: =IF(ISBLANK($A10),"",INDEX(Array_OtherEnergyCharges,MATCH($A10,List_OtherEnergyMeters,0),ROUNDUP((COLUMN()+1)/3-2,0)))
F11: =IF(ISBLANK($A11),"",INDEX(Array_OtherEnergyCharges,MATCH($A11,List_OtherEnergyMeters,0),ROUNDUP((COLUMN()+1)/3-2,0))) | I11: =IF(ISBLANK($A11),"",INDEX(Array_OtherEnergyCharges,MATCH($A11,List_OtherEnergyMeters,0),ROUNDUP((COLUMN()+1)/3-2,0))) | L11: =IF(ISBLANK($A11),"",INDEX(Array_OtherEnergyCharges,MATCH($A11,List_OtherEnergyMeters,0),ROUNDUP((COLUMN()+1)/3-2,0))) | O11: =IF(ISBLANK($A11),"",INDEX(Array_OtherEnergyCharges,MATCH($A11,List_OtherEnergyMeters,0),ROUNDUP((COLUMN()+1)/3-2,0))) | R11: =IF(ISBLANK($A11),"",INDEX(Array_OtherEnergyCharges,MATCH($A11,List_OtherEnergyMeters,0),ROUNDUP((COLUMN()+1)/3-2,0)))
F12: =IF(ISBLANK($A12),"",INDEX(Array_OtherEnergyCharges,MATCH($A12,List_OtherEnergyMeters,0),ROUNDUP((COLUMN()+1)/3-2,0))) | I12: =IF(ISBLANK($A12),"",INDEX(Array_OtherEnergyCharges,MATCH($A12,List_OtherEnergyMeters,0),ROUNDUP((COLUMN()+1)/3-2,0))) | L12: =IF(ISBLANK($A12),"",INDEX(Array_OtherEnergyCharges,MATCH($A12,List_OtherEnergyMeters,0),ROUNDUP((COLUMN()+1)/3-2,0))) | O12: =IF(ISBLANK($A12),"",INDEX(Array_OtherEnergyCharges,MATCH($A12,List_OtherEnergyMeters,0),ROUNDUP((COLUMN()+1)/3-2,0))) | R12: =IF(ISBLANK($A12),"",INDEX(Array_OtherEnergyCharges,MATCH($A12,List_OtherEnergyMeters,0),ROUNDUP((COLUMN()+1)/3-2,0)))
F13: =IF(ISBLANK($A13),"",INDEX(Array_OtherEnergyCharges,MATCH($A13,List_OtherEnergyMeters,0),ROUNDUP((COLUMN()+1)/3-2,0))) | I13: =IF(ISBLANK($A13),"",INDEX(Array_OtherEnergyCharges,MATCH($A13,List_OtherEnergyMeters,0),ROUNDUP((COLUMN()+1)/3-2,0))) | L13: =IF(ISBLANK($A13),"",INDEX(Array_OtherEnergyCharges,MATCH($A13,List_OtherEnergyMeters,0),ROUNDUP((COLUMN()+1)/3-2,0))) | O13: =IF(ISBLANK($A13),"",INDEX(Array_OtherEnergyCharges,MATCH($A13,List_OtherEnergyMeters,0),ROUNDUP((COLUMN()+1)/3-2,0))) | R13: =IF(ISBLANK($A13),"",INDEX(Array_OtherEnergyCharges,MATCH($A13,List_OtherEnergyMeters,0),ROUNDUP((COLUMN()+1)/3-2,0)))
F14: =IF(ISBLANK($A14),"",INDEX(Array_OtherEnergyCharges,MATCH($A14,List_OtherEnergyMeters,0),ROUNDUP((COLUMN()+1)/3-2,0))) | I14: =IF(ISBLANK($A14),"",INDEX(Array_OtherEnergyCharges,MATCH($A14,List_OtherEnergyMeters,0),ROUNDUP((COLUMN()+1)/3-2,0))) | L14: =IF(ISBLANK($A14),"",INDEX(Array_OtherEnergyCharges,MATCH($A14,List_OtherEnergyMeters,0),ROUNDUP((COLUMN()+1)/3-2,0))) | O14: =IF(ISBLANK($A14),"",INDEX(Array_OtherEnergyCharges,MATCH($A14,List_OtherEnergyMeters,0),ROUNDUP((COLUMN()+1)/3-2,0))) | R14: =IF(ISBLANK($A14),"",INDEX(Array_OtherEnergyCharges,MATCH($A14,List_OtherEnergyMeters,0),ROUNDUP((COLUMN()+1)/3-2,0)))
... F502: =IF(ISBLANK($A502),"",INDEX(Array_OtherEnergyCharges,MATCH($A502,List_OtherEnergyMeters,0),ROUNDUP((COLUMN()+1)/3-2,0))) | I502: =IF(ISBLANK($A502),"",INDEX(Array_OtherEnergyCharges,MATCH($A502,List_OtherEnergyMeters,0),ROUNDUP((COLUMN()+1)/3-2,0))) | L502: =IF(ISBLANK($A502),"",INDEX(Array_OtherEnergyCharges,MATCH($A502,List_OtherEnergyMeters,0),ROUNDUP((COLUMN()+1)/3-2,0))) | O502: =IF(ISBLANK($A502),"",INDEX(Array_OtherEnergyCharges,MATCH($A502,List_OtherEnergyMeters,0),ROUNDUP((COLUMN()+1)/3-2,0))) | R502: =IF(ISBLANK($A502),"",INDEX(Array_OtherEnergyCharges,MATCH($A502,List_OtherEnergyMeters,0),ROUNDUP((COLUMN()+1)/3-2,0)))

Sheet HIDE_ENERGY
A1: Other Energy Types | B1: Other Energy Units | C1: Charge Types | D1: Charge Units | E1: Other Cost Units
A2: District Hot Water | B2: MMBtu | C2: Usage | D2: ="$/"&B2 -> $/MMBtu | E2: %
A3: Purchased Chilled Water (Absorption Chiller) | B3: kWh | C3: Tax | D3: ="$/"&B3 -> $/kWh | E3: $
A4: Purchased Chilled Water (Electric-driven Compressor) | B4: MWh | C4: Late Fee | D4: ="$/"&B4 -> $/MWh
A5: Purchased Chilled Water (Engine-driven Compressor) | B5: GJ | C5: Flat Fee | D5: ="$/"&B5 -> $/GJ
A6: Purchased Compressed Air | B6: MJ | C6: Other | D6: ="$/"&B6 -> $/MJ
A7: Purchased Steam | B7: kJ | D7: ="$/"&B7 -> $/kJ
B8: Therms | D8: ="$/"&B8 -> $/Therms
B9: DTherms | D9: ="$/"&B9 -> $/DTherms
B10: kcal | D10: ="$/"&B10 -> $/kcal
B11: lb | D11: ="$/"&B11 -> $/lb
B12: klb | D12: ="$/"&B12 -> $/klb
B13: kg | D13: ="$/"&B13 -> $/kg
B14: SCF | D14: ="$/"&B14 -> $/SCF
B15: CCF | D15: ="$/"&B15 -> $/CCF
B16: kSCF | D16: ="$/"&B16 -> $/kSCF
B17: m3 | D17: ="$/"&B17 -> $/m3
B18: ton | D18: ="$/"&B18 -> $/ton
B19: tonne | D19: ="$/"&B19 -> $/tonne
... B21: tonHr | D21: ="$/"&B21 -> $/tonHr
A23: Charge count: | B23: =COUNTIF(B25:B124,"?*") -> 0 | C23: =COUNTIF(C25:C124,"?*") -> 0 | D23: =COUNTIF(D25:D124,"?*") -> 0 | E23: =COUNTIF(E25:E124,"?*") -> 0 | F23: =COUNTIF(F25:F124,"?*") -> 0
A24: Meter Numbers | B24: Charge 1 | C24: Charge 2 | D24: Charge 3 | E24: Charge 4 | F24: Charge 5
A25: =IF('Other Energy Meters'!B3="",A24,'Other Energy Meters'!B3) -> Meter Numbers | B25: =IF(ISBLANK(INDEX(Array_OtherEnergyChargeData,ROW()-24,COLUMN()*2-3)),"",INDEX(Array_OtherEnergyChargeData,ROW()-24,COLUMN()*2-3)) | C25: =IF(ISBLANK(INDEX(Array_OtherEnergyChargeData,ROW()-24,COLUMN()*2-3)),"",INDEX(Array_OtherEnergyChargeData,ROW()-24,COLUMN()*2-3)) | D25: =IF(ISBLANK(INDEX(Array_OtherEnergyChargeData,ROW()-24,COLUMN()*2-3)),"",INDEX(Array_OtherEnergyChargeData,ROW()-24,COLUMN()*2-3)) | E25: =IF(ISBLANK(INDEX(Array_OtherEnergyChargeData,ROW()-24,COLUMN()*2-3)),"",INDEX(Array_OtherEnergyChargeData,ROW()-24,COLUMN()*2-3)) | F25: =IF(ISBLANK(INDEX(Array_OtherEnergyChargeData,ROW()-24,COLUMN()*2-3)),"",INDEX(Array_OtherEnergyChargeData,ROW()-24,COLUMN()*2-3))
A26: =IF('Other Energy Meters'!B4="",A25,'Other Energy Meters'!B4) -> Meter Numbers | B26: =IF(ISBLANK(INDEX(Array_OtherEnergyChargeData,ROW()-24,COLUMN()*2-3)),"",INDEX(Array_OtherEnergyChargeData,ROW()-24,COLUMN()*2-3)) | C26: =IF(ISBLANK(INDEX(Array_OtherEnergyChargeData,ROW()-24,COLUMN()*2-3)),"",INDEX(Array_OtherEnergyChargeData,ROW()-24,COLUMN()*2-3)) | D26: =IF(ISBLANK(INDEX(Array_OtherEnergyChargeData,ROW()-24,COLUMN()*2-3)),"",INDEX(Array_OtherEnergyChargeData,ROW()-24,COLUMN()*2-3)) | E26: =IF(ISBLANK(INDEX(Array_OtherEnergyChargeData,ROW()-24,COLUMN()*2-3)),"",INDEX(Array_OtherEnergyChargeData,ROW()-24,COLUMN()*2-3)) | F26: =IF(ISBLANK(INDEX(Array_OtherEnergyChargeData,ROW()-24,COLUMN()*2-3)),"",INDEX(Array_OtherEnergyChargeData,ROW()-24,COLUMN()*2-3))
A27: =IF('Other Energy Meters'!B5="",A26,'Other Energy Meters'!B5) -> Meter Numbers | B27: =IF(ISBLANK(INDEX(Array_OtherEnergyChargeData,ROW()-24,COLUMN()*2-3)),"",INDEX(Array_OtherEnergyChargeData,ROW()-24,COLUMN()*2-3)) | C27: =IF(ISBLANK(INDEX(Array_OtherEnergyChargeData,ROW()-24,COLUMN()*2-3)),"",INDEX(Array_OtherEnergyChargeData,ROW()-24,COLUMN()*2-3)) | D27: =IF(ISBLANK(INDEX(Array_OtherEnergyChargeData,ROW()-24,COLUMN()*2-3)),"",INDEX(Array_OtherEnergyChargeData,ROW()-24,COLUMN()*2-3)) | E27: =IF(ISBLANK(INDEX(Array_OtherEnergyChargeData,ROW()-24,COLUMN()*2-3)),"",INDEX(Array_OtherEnergyChargeData,ROW()-24,COLUMN()*2-3)) | F27: =IF(ISBLANK(INDEX(Array_OtherEnergyChargeData,ROW()-24,COLUMN()*2-3)),"",INDEX(Array_OtherEnergyChargeData,ROW()-24,COLUMN()*2-3))
A28: =IF('Other Energy Meters'!B6="",A27,'Other Energy Meters'!B6) -> Meter Numbers | B28: =IF(ISBLANK(INDEX(Array_OtherEnergyChargeData,ROW()-24,COLUMN()*2-3)),"",INDEX(Array_OtherEnergyChargeData,ROW()-24,COLUMN()*2-3)) | C28: =IF(ISBLANK(INDEX(Array_OtherEnergyChargeData,ROW()-24,COLUMN()*2-3)),"",INDEX(Array_OtherEnergyChargeData,ROW()-24,COLUMN()*2-3)) | D28: =IF(ISBLANK(INDEX(Array_OtherEnergyChargeData,ROW()-24,COLUMN()*2-3)),"",INDEX(Array_OtherEnergyChargeData,ROW()-24,COLUMN()*2-3)) | E28: =IF(ISBLANK(INDEX(Array_OtherEnergyChargeData,ROW()-24,COLUMN()*2-3)),"",INDEX(Array_OtherEnergyChargeData,ROW()-24,COLUMN()*2-3)) | F28: =IF(ISBLANK(INDEX(Array_OtherEnergyChargeData,ROW()-24,COLUMN()*2-3)),"",INDEX(Array_OtherEnergyChargeData,ROW()-24,COLUMN()*2-3))
A29: =IF('Other Energy Meters'!B7="",A28,'Other Energy Meters'!B7) -> Meter Numbers | B29: =IF(ISBLANK(INDEX(Array_OtherEnergyChargeData,ROW()-24,COLUMN()*2-3)),"",INDEX(Array_OtherEnergyChargeData,ROW()-24,COLUMN()*2-3)) | C29: =IF(ISBLANK(INDEX(Array_OtherEnergyChargeData,ROW()-24,COLUMN()*2-3)),"",INDEX(Array_OtherEnergyChargeData,ROW()-24,COLUMN()*2-3)) | D29: =IF(ISBLANK(INDEX(Array_OtherEnergyChargeData,ROW()-24,COLUMN()*2-3)),"",INDEX(Array_OtherEnergyChargeData,ROW()-24,COLUMN()*2-3)) | E29: =IF(ISBLANK(INDEX(Array_OtherEnergyChargeData,ROW()-24,COLUMN()*2-3)),"",INDEX(Array_OtherEnergyChargeData,ROW()-24,COLUMN()*2-3)) | F29: =IF(ISBLANK(INDEX(Array_OtherEnergyChargeData,ROW()-24,COLUMN()*2-3)),"",INDEX(Array_OtherEnergyChargeData,ROW()-24,COLUMN()*2-3))
A30: =IF('Other Energy Meters'!B8="",A29,'Other Energy Meters'!B8) -> Meter Numbers | B30: =IF(ISBLANK(INDEX(Array_OtherEnergyChargeData,ROW()-24,COLUMN()*2-3)),"",INDEX(Array_OtherEnergyChargeData,ROW()-24,COLUMN()*2-3)) | C30: =IF(ISBLANK(INDEX(Array_OtherEnergyChargeData,ROW()-24,COLUMN()*2-3)),"",INDEX(Array_OtherEnergyChargeData,ROW()-24,COLUMN()*2-3)) | D30: =IF(ISBLANK(INDEX(Array_OtherEnergyChargeData,ROW()-24,COLUMN()*2-3)),"",INDEX(Array_OtherEnergyChargeData,ROW()-24,COLUMN()*2-3)) | E30: =IF(ISBLANK(INDEX(Array_OtherEnergyChargeData,ROW()-24,COLUMN()*2-3)),"",INDEX(Array_OtherEnergyChargeData,ROW()-24,COLUMN()*2-3)) | F30: =IF(ISBLANK(INDEX(Array_OtherEnergyChargeData,ROW()-24,COLUMN()*2-3)),"",INDEX(Array_OtherEnergyChargeData,ROW()-24,COLUMN()*2-3))
A31: =IF('Other Energy Meters'!B9="",A30,'Other Energy Meters'!B9) -> Meter Numbers | B31: =IF(ISBLANK(INDEX(Array_OtherEnergyChargeData,ROW()-24,COLUMN()*2-3)),"",INDEX(Array_OtherEnergyChargeData,ROW()-24,COLUMN()*2-3)) | C31: =IF(ISBLANK(INDEX(Array_OtherEnergyChargeData,ROW()-24,COLUMN()*2-3)),"",INDEX(Array_OtherEnergyChargeData,ROW()-24,COLUMN()*2-3)) | D31: =IF(ISBLANK(INDEX(Array_OtherEnergyChargeData,ROW()-24,COLUMN()*2-3)),"",INDEX(Array_OtherEnergyChargeData,ROW()-24,COLUMN()*2-3)) | E31: =IF(ISBLANK(INDEX(Array_OtherEnergyChargeData,ROW()-24,COLUMN()*2-3)),"",INDEX(Array_OtherEnergyChargeData,ROW()-24,COLUMN()*2-3)) | F31: =IF(ISBLANK(INDEX(Array_OtherEnergyChargeData,ROW()-24,COLUMN()*2-3)),"",INDEX(Array_OtherEnergyChargeData,ROW()-24,COLUMN()*2-3))
A32: =IF('Other Energy Meters'!B10="",A31,'Other Energy Meters'!B10) -> Meter Numbers | B32: =IF(ISBLANK(INDEX(Array_OtherEnergyChargeData,ROW()-24,COLUMN()*2-3)),"",INDEX(Array_OtherEnergyChargeData,ROW()-24,COLUMN()*2-3)) | C32: =IF(ISBLANK(INDEX(Array_OtherEnergyChargeData,ROW()-24,COLUMN()*2-3)),"",INDEX(Array_OtherEnergyChargeData,ROW()-24,COLUMN()*2-3)) | D32: =IF(ISBLANK(INDEX(Array_OtherEnergyChargeData,ROW()-24,COLUMN()*2-3)),"",INDEX(Array_OtherEnergyChargeData,ROW()-24,COLUMN()*2-3)) | E32: =IF(ISBLANK(INDEX(Array_OtherEnergyChargeData,ROW()-24,COLUMN()*2-3)),"",INDEX(Array_OtherEnergyChargeData,ROW()-24,COLUMN()*2-3)) | F32: =IF(ISBLANK(INDEX(Array_OtherEnergyChargeData,ROW()-24,COLUMN()*2-3)),"",INDEX(Array_OtherEnergyChargeData,ROW()-24,COLUMN()*2-3))
A33: =IF('Other Energy Meters'!B11="",A32,'Other Energy Meters'!B11) -> Meter Numbers | B33: =IF(ISBLANK(INDEX(Array_OtherEnergyChargeData,ROW()-24,COLUMN()*2-3)),"",INDEX(Array_OtherEnergyChargeData,ROW()-24,COLUMN()*2-3)) | C33: =IF(ISBLANK(INDEX(Array_OtherEnergyChargeData,ROW()-24,COLUMN()*2-3)),"",INDEX(Array_OtherEnergyChargeData,ROW()-24,COLUMN()*2-3)) | D33: =IF(ISBLANK(INDEX(Array_OtherEnergyChargeData,ROW()-24,COLUMN()*2-3)),"",INDEX(Array_OtherEnergyChargeData,ROW()-24,COLUMN()*2-3)) | E33: =IF(ISBLANK(INDEX(Array_OtherEnergyChargeData,ROW()-24,COLUMN()*2-3)),"",INDEX(Array_OtherEnergyChargeData,ROW()-24,COLUMN()*2-3)) | F33: =IF(ISBLANK(INDEX(Array_OtherEnergyChargeData,ROW()-24,COLUMN()*2-3)),"",INDEX(Array_OtherEnergyChargeData,ROW()-24,COLUMN()*2-3))
A34: =IF('Other Energy Meters'!B12="",A33,'Other Energy Meters'!B12) -> Meter Numbers | B34: =IF(ISBLANK(INDEX(Array_OtherEnergyChargeData,ROW()-24,COLUMN()*2-3)),"",INDEX(Array_OtherEnergyChargeData,ROW()-24,COLUMN()*2-3)) | C34: =IF(ISBLANK(INDEX(Array_OtherEnergyChargeData,ROW()-24,COLUMN()*2-3)),"",INDEX(Array_OtherEnergyChargeData,ROW()-24,COLUMN()*2-3)) | D34: =IF(ISBLANK(INDEX(Array_OtherEnergyChargeData,ROW()-24,COLUMN()*2-3)),"",INDEX(Array_OtherEnergyChargeData,ROW()-24,COLUMN()*2-3)) | E34: =IF(ISBLANK(INDEX(Array_OtherEnergyChargeData,ROW()-24,COLUMN()*2-3)),"",INDEX(Array_OtherEnergyChargeData,ROW()-24,COLUMN()*2-3)) | F34: =IF(ISBLANK(INDEX(Array_OtherEnergyChargeData,ROW()-24,COLUMN()*2-3)),"",INDEX(Array_OtherEnergyChargeData,ROW()-24,COLUMN()*2-3))
A35: =IF('Other Energy Meters'!B13="",A34,'Other Energy Meters'!B13) -> Meter Numbers | B35: =IF(ISBLANK(INDEX(Array_OtherEnergyChargeData,ROW()-24,COLUMN()*2-3)),"",INDEX(Array_OtherEnergyChargeData,ROW()-24,COLUMN()*2-3)) | C35: =IF(ISBLANK(INDEX(Array_OtherEnergyChargeData,ROW()-24,COLUMN()*2-3)),"",INDEX(Array_OtherEnergyChargeData,ROW()-24,COLUMN()*2-3)) | D35: =IF(ISBLANK(INDEX(Array_OtherEnergyChargeData,ROW()-24,COLUMN()*2-3)),"",INDEX(Array_OtherEnergyChargeData,ROW()-24,COLUMN()*2-3)) | E35: =IF(ISBLANK(INDEX(Array_OtherEnergyChargeData,ROW()-24,COLUMN()*2-3)),"",INDEX(Array_OtherEnergyChargeData,ROW()-24,COLUMN()*2-3)) | F35: =IF(ISBLANK(INDEX(Array_OtherEnergyChargeData,ROW()-24,COLUMN()*2-3)),"",INDEX(Array_OtherEnergyChargeData,ROW()-24,COLUMN()*2-3))
A36: =IF('Other Energy Meters'!B14="",A35,'Other Energy Meters'!B14) -> Meter Numbers | B36: =IF(ISBLANK(INDEX(Array_OtherEnergyChargeData,ROW()-24,COLUMN()*2-3)),"",INDEX(Array_OtherEnergyChargeData,ROW()-24,COLUMN()*2-3)) | C36: =IF(ISBLANK(INDEX(Array_OtherEnergyChargeData,ROW()-24,COLUMN()*2-3)),"",INDEX(Array_OtherEnergyChargeData,ROW()-24,COLUMN()*2-3)) | D36: =IF(ISBLANK(INDEX(Array_OtherEnergyChargeData,ROW()-24,COLUMN()*2-3)),"",INDEX(Array_OtherEnergyChargeData,ROW()-24,COLUMN()*2-3)) | E36: =IF(ISBLANK(INDEX(Array_OtherEnergyChargeData,ROW()-24,COLUMN()*2-3)),"",INDEX(Array_OtherEnergyChargeData,ROW()-24,COLUMN()*2-3)) | F36: =IF(ISBLANK(INDEX(Array_OtherEnergyChargeData,ROW()-24,COLUMN()*2-3)),"",INDEX(Array_OtherEnergyChargeData,ROW()-24,COLUMN()*2-3))
... A224: =IF('Other Energy Meters'!B202="",A223,'Other Energy Meters'!B202) -> Meter Numbers | B224: =IF(ISBLANK(INDEX(Array_OtherEnergyChargeData,ROW()-24,COLUMN()*2-3)),"",INDEX(Array_OtherEnergyChargeData,ROW()-24,COLUMN()*2-3)) | C224: =IF(ISBLANK(INDEX(Array_OtherEnergyChargeData,ROW()-24,COLUMN()*2-3)),"",INDEX(Array_OtherEnergyChargeData,ROW()-24,COLUMN()*2-3)) | D224: =IF(ISBLANK(INDEX(Array_OtherEnergyChargeData,ROW()-24,COLUMN()*2-3)),"",INDEX(Array_OtherEnergyChargeData,ROW()-24,COLUMN()*2-3)) | E224: =IF(ISBLANK(INDEX(Array_OtherEnergyChargeData,ROW()-24,COLUMN()*2-3)),"",INDEX(Array_OtherEnergyChargeData,ROW()-24,COLUMN()*2-3)) | F224: =IF(ISBLANK(INDEX(Array_OtherEnergyChargeData,ROW()-24,COLUMN()*2-3)),"",INDEX(Array_OtherEnergyChargeData,ROW()-24,COLUMN()*2-3))

Sheet Other Emission Meters
A1: √ Other Emissions Meters Setup | K1: √ Other Emissions Charge Setup (Optional)
A2: Facility Name | B2: Meter Number (UNIQUE) | C2: Meter Name (DISPLAY) | D2: Meter Group (ANALYSIS) | E2: Calendarize Readings? | F2: Type | G2: Greenhouse Gas | H2: Unit (COLLECTION) | I2: Location | J2: Notes | K2: ="Charge "&QUOTIENT(COLUMN()-9,2)&" Name" -> Charge 1 Name | L2: ="Charge "&QUOTIENT(COLUMN()-9,2)&" Type" -> Charge 1 Type | M2: ="Charge "&QUOTIENT(COLUMN()-9,2)&" Name" -> Charge 2 Name | N2: ="Charge "&QUOTIENT(COLUMN()-9,2)&" Type" -> Charge 2 Type | O2: ="Charge "&QUOTIENT(COLUMN()-9,2)&" Name" -> Charge 3 Name | P2: ="Charge "&QUOTIENT(COLUMN()-9,2)&" Type" -> Charge 3 Type | Q2: ="Charge "&QUOTIENT(COLUMN()-9,2)&" Name" -> Charge 4 Name | R2: ="Charge "&QUOTIENT(COLUMN()-9,2)&" Type" -> Charge 4 Type | S2: ="Charge "&QUOTIENT(COLUMN()-9,2)&" Name" -> Charge 5 Name | T2: ="Charge "&QUOTIENT(COLUMN()-9,2)&" Type" -> Charge 5 Type

Sheet HIDE_EMISSION
A1: Charge count: | B1: =COUNTIF(B3:B102,"?*") -> 0 | C1: =COUNTIF(C3:C102,"?*") -> 0 | D1: =COUNTIF(D3:D102,"?*") -> 0 | E1: =COUNTIF(E3:E102,"?*") -> 0 | F1: =COUNTIF(F3:F102,"?*") -> 0 | J1: Emission Type | K1: GHGs | L1: GHG Units | M1: GHG Cost Types | N1: GHG Costs | O1: Other Cost Units
A2: Meter Numbers | B2: Charge 1 | C2: Charge 2 | D2: Charge 3 | E2: Charge 4 | F2: Charge 5 | J2: Scope 1: Fugitive | K2: CO2 | L2: lb | M2: Usage | N2: ="$/"&L2 -> $/lb | O2: %
A3: =IF('Other Emission Meters'!B3="",A2,'Other Emission Meters'!B3) -> Meter Numbers | B3: =IF(ISBLANK(INDEX(Array_EmissionChargeData,ROW()-2,(COLUMN())*2-3)),"",INDEX(Array_EmissionChargeData,ROW()-2,(COLUMN())*2-3)) | C3: =IF(ISBLANK(INDEX(Array_EmissionChargeData,ROW()-2,(COLUMN())*2-3)),"",INDEX(Array_EmissionChargeData,ROW()-2,(COLUMN())*2-3)) | D3: =IF(ISBLANK(INDEX(Array_EmissionChargeData,ROW()-2,(COLUMN())*2-3)),"",INDEX(Array_EmissionChargeData,ROW()-2,(COLUMN())*2-3)) | E3: =IF(ISBLANK(INDEX(Array_EmissionChargeData,ROW()-2,(COLUMN())*2-3)),"",INDEX(Array_EmissionChargeData,ROW()-2,(COLUMN())*2-3)) | F3: =IF(ISBLANK(INDEX(Array_EmissionChargeData,ROW()-2,(COLUMN())*2-3)),"",INDEX(Array_EmissionChargeData,ROW()-2,(COLUMN())*2-3)) | J3: Scope 1: Process | K3: CH4 | L3: kg | M3: Tax | N3: ="$/"&L3 -> $/kg | O3: $
A4: =IF('Other Emission Meters'!B4="",A3,'Other Emission Meters'!B4) -> Meter Numbers | B4: =IF(ISBLANK(INDEX(Array_EmissionChargeData,ROW()-2,(COLUMN())*2-3)),"",INDEX(Array_EmissionChargeData,ROW()-2,(COLUMN())*2-3)) | C4: =IF(ISBLANK(INDEX(Array_EmissionChargeData,ROW()-2,(COLUMN())*2-3)),"",INDEX(Array_EmissionChargeData,ROW()-2,(COLUMN())*2-3)) | D4: =IF(ISBLANK(INDEX(Array_EmissionChargeData,ROW()-2,(COLUMN())*2-3)),"",INDEX(Array_EmissionChargeData,ROW()-2,(COLUMN())*2-3)) | E4: =IF(ISBLANK(INDEX(Array_EmissionChargeData,ROW()-2,(COLUMN())*2-3)),"",INDEX(Array_EmissionChargeData,ROW()-2,(COLUMN())*2-3)) | F4: =IF(ISBLANK(INDEX(Array_EmissionChargeData,ROW()-2,(COLUMN())*2-3)),"",INDEX(Array_EmissionChargeData,ROW()-2,(COLUMN())*2-3)) | J4: Other | K4: N2O | L4: Long Ton | M4: Late Fee | N4: ="$/"&L4 -> $/Long Ton
A5: =IF('Other Emission Meters'!B5="",A4,'Other Emission Meters'!B5) -> Meter Numbers | B5: =IF(ISBLANK(INDEX(Array_EmissionChargeData,ROW()-2,(COLUMN())*2-3)),"",INDEX(Array_EmissionChargeData,ROW()-2,(COLUMN())*2-3)) | C5: =IF(ISBLANK(INDEX(Array_EmissionChargeData,ROW()-2,(COLUMN())*2-3)),"",INDEX(Array_EmissionChargeData,ROW()-2,(COLUMN())*2-3)) | D5: =IF(ISBLANK(INDEX(Array_EmissionChargeData,ROW()-2,(COLUMN())*2-3)),"",INDEX(Array_EmissionChargeData,ROW()-2,(COLUMN())*2-3)) | E5: =IF(ISBLANK(INDEX(Array_EmissionChargeData,ROW()-2,(COLUMN())*2-3)),"",INDEX(Array_EmissionChargeData,ROW()-2,(COLUMN())*2-3)) | F5: =IF(ISBLANK(INDEX(Array_EmissionChargeData,ROW()-2,(COLUMN())*2-3)),"",INDEX(Array_EmissionChargeData,ROW()-2,(COLUMN())*2-3)) | K5: HFC-23 | L5: Short Ton | M5: Flat Fee | N5: ="$/"&L5 -> $/Short Ton
A6: =IF('Other Emission Meters'!B6="",A5,'Other Emission Meters'!B6) -> Meter Numbers | B6: =IF(ISBLANK(INDEX(Array_EmissionChargeData,ROW()-2,(COLUMN())*2-3)),"",INDEX(Array_EmissionChargeData,ROW()-2,(COLUMN())*2-3)) | C6: =IF(ISBLANK(INDEX(Array_EmissionChargeData,ROW()-2,(COLUMN())*2-3)),"",INDEX(Array_EmissionChargeData,ROW()-2,(COLUMN())*2-3)) | D6: =IF(ISBLANK(INDEX(Array_EmissionChargeData,ROW()-2,(COLUMN())*2-3)),"",INDEX(Array_EmissionChargeData,ROW()-2,(COLUMN())*2-3)) | E6: =IF(ISBLANK(INDEX(Array_EmissionChargeData,ROW()-2,(COLUMN())*2-3)),"",INDEX(Array_EmissionChargeData,ROW()-2,(COLUMN())*2-3)) | F6: =IF(ISBLANK(INDEX(Array_EmissionChargeData,ROW()-2,(COLUMN())*2-3)),"",INDEX(Array_EmissionChargeData,ROW()-2,(COLUMN())*2-3)) | K6: HFC-32 | L6: Metric Tonne (tonnes) | M6: Other | N6: ="$/"&L6 -> $/Metric Tonne (tonnes)
A7: =IF('Other Emission Meters'!B7="",A6,'Other Emission Meters'!B7) -> Meter Numbers | B7: =IF(ISBLANK(INDEX(Array_EmissionChargeData,ROW()-2,(COLUMN())*2-3)),"",INDEX(Array_EmissionChargeData,ROW()-2,(COLUMN())*2-3)) | C7: =IF(ISBLANK(INDEX(Array_EmissionChargeData,ROW()-2,(COLUMN())*2-3)),"",INDEX(Array_EmissionChargeData,ROW()-2,(COLUMN())*2-3)) | D7: =IF(ISBLANK(INDEX(Array_EmissionChargeData,ROW()-2,(COLUMN())*2-3)),"",INDEX(Array_EmissionChargeData,ROW()-2,(COLUMN())*2-3)) | E7: =IF(ISBLANK(INDEX(Array_EmissionChargeData,ROW()-2,(COLUMN())*2-3)),"",INDEX(Array_EmissionChargeData,ROW()-2,(COLUMN())*2-3)) | F7: =IF(ISBLANK(INDEX(Array_EmissionChargeData,ROW()-2,(COLUMN())*2-3)),"",INDEX(Array_EmissionChargeData,ROW()-2,(COLUMN())*2-3)) | K7: HFC-41 | L7: klb | N7: ="$/"&L7 -> $/klb
A8: =IF('Other Emission Meters'!B8="",A7,'Other Emission Meters'!B8) -> Meter Numbers | B8: =IF(ISBLANK(INDEX(Array_EmissionChargeData,ROW()-2,(COLUMN())*2-3)),"",INDEX(Array_EmissionChargeData,ROW()-2,(COLUMN())*2-3)) | C8: =IF(ISBLANK(INDEX(Array_EmissionChargeData,ROW()-2,(COLUMN())*2-3)),"",INDEX(Array_EmissionChargeData,ROW()-2,(COLUMN())*2-3)) | D8: =IF(ISBLANK(INDEX(Array_EmissionChargeData,ROW()-2,(COLUMN())*2-3)),"",INDEX(Array_EmissionChargeData,ROW()-2,(COLUMN())*2-3)) | E8: =IF(ISBLANK(INDEX(Array_EmissionChargeData,ROW()-2,(COLUMN())*2-3)),"",INDEX(Array_EmissionChargeData,ROW()-2,(COLUMN())*2-3)) | F8: =IF(ISBLANK(INDEX(Array_EmissionChargeData,ROW()-2,(COLUMN())*2-3)),"",INDEX(Array_EmissionChargeData,ROW()-2,(COLUMN())*2-3)) | K8: HFC-125
A9: =IF('Other Emission Meters'!B9="",A8,'Other Emission Meters'!B9) -> Meter Numbers | B9: =IF(ISBLANK(INDEX(Array_EmissionChargeData,ROW()-2,(COLUMN())*2-3)),"",INDEX(Array_EmissionChargeData,ROW()-2,(COLUMN())*2-3)) | C9: =IF(ISBLANK(INDEX(Array_EmissionChargeData,ROW()-2,(COLUMN())*2-3)),"",INDEX(Array_EmissionChargeData,ROW()-2,(COLUMN())*2-3)) | D9: =IF(ISBLANK(INDEX(Array_EmissionChargeData,ROW()-2,(COLUMN())*2-3)),"",INDEX(Array_EmissionChargeData,ROW()-2,(COLUMN())*2-3)) | E9: =IF(ISBLANK(INDEX(Array_EmissionChargeData,ROW()-2,(COLUMN())*2-3)),"",INDEX(Array_EmissionChargeData,ROW()-2,(COLUMN())*2-3)) | F9: =IF(ISBLANK(INDEX(Array_EmissionChargeData,ROW()-2,(COLUMN())*2-3)),"",INDEX(Array_EmissionChargeData,ROW()-2,(COLUMN())*2-3)) | K9: HFC-134
A10: =IF('Other Emission Meters'!B10="",A9,'Other Emission Meters'!B10) -> Meter Numbers | B10: =IF(ISBLANK(INDEX(Array_EmissionChargeData,ROW()-2,(COLUMN())*2-3)),"",INDEX(Array_EmissionChargeData,ROW()-2,(COLUMN())*2-3)) | C10: =IF(ISBLANK(INDEX(Array_EmissionChargeData,ROW()-2,(COLUMN())*2-3)),"",INDEX(Array_EmissionChargeData,ROW()-2,(COLUMN())*2-3)) | D10: =IF(ISBLANK(INDEX(Array_EmissionChargeData,ROW()-2,(COLUMN())*2-3)),"",INDEX(Array_EmissionChargeData,ROW()-2,(COLUMN())*2-3)) | E10: =IF(ISBLANK(INDEX(Array_EmissionChargeData,ROW()-2,(COLUMN())*2-3)),"",INDEX(Array_EmissionChargeData,ROW()-2,(COLUMN())*2-3)) | F10: =IF(ISBLANK(INDEX(Array_EmissionChargeData,ROW()-2,(COLUMN())*2-3)),"",INDEX(Array_EmissionChargeData,ROW()-2,(COLUMN())*2-3)) | K10: HFC-134a
A11: =IF('Other Emission Meters'!B11="",A10,'Other Emission Meters'!B11) -> Meter Numbers | B11: =IF(ISBLANK(INDEX(Array_EmissionChargeData,ROW()-2,(COLUMN())*2-3)),"",INDEX(Array_EmissionChargeData,ROW()-2,(COLUMN())*2-3)) | C11: =IF(ISBLANK(INDEX(Array_EmissionChargeData,ROW()-2,(COLUMN())*2-3)),"",INDEX(Array_EmissionChargeData,ROW()-2,(COLUMN())*2-3)) | D11: =IF(ISBLANK(INDEX(Array_EmissionChargeData,ROW()-2,(COLUMN())*2-3)),"",INDEX(Array_EmissionChargeData,ROW()-2,(COLUMN())*2-3)) | E11: =IF(ISBLANK(INDEX(Array_EmissionChargeData,ROW()-2,(COLUMN())*2-3)),"",INDEX(Array_EmissionChargeData,ROW()-2,(COLUMN())*2-3)) | F11: =IF(ISBLANK(INDEX(Array_EmissionChargeData,ROW()-2,(COLUMN())*2-3)),"",INDEX(Array_EmissionChargeData,ROW()-2,(COLUMN())*2-3)) | K11: HFC-143
A12: =IF('Other Emission Meters'!B12="",A11,'Other Emission Meters'!B12) -> Meter Numbers | B12: =IF(ISBLANK(INDEX(Array_EmissionChargeData,ROW()-2,(COLUMN())*2-3)),"",INDEX(Array_EmissionChargeData,ROW()-2,(COLUMN())*2-3)) | C12: =IF(ISBLANK(INDEX(Array_EmissionChargeData,ROW()-2,(COLUMN())*2-3)),"",INDEX(Array_EmissionChargeData,ROW()-2,(COLUMN())*2-3)) | D12: =IF(ISBLANK(INDEX(Array_EmissionChargeData,ROW()-2,(COLUMN())*2-3)),"",INDEX(Array_EmissionChargeData,ROW()-2,(COLUMN())*2-3)) | E12: =IF(ISBLANK(INDEX(Array_EmissionChargeData,ROW()-2,(COLUMN())*2-3)),"",INDEX(Array_EmissionChargeData,ROW()-2,(COLUMN())*2-3)) | F12: =IF(ISBLANK(INDEX(Array_EmissionChargeData,ROW()-2,(COLUMN())*2-3)),"",INDEX(Array_EmissionChargeData,ROW()-2,(COLUMN())*2-3)) | K12: HFC-143a
A13: =IF('Other Emission Meters'!B13="",A12,'Other Emission Meters'!B13) -> Meter Numbers | B13: =IF(ISBLANK(INDEX(Array_EmissionChargeData,ROW()-2,(COLUMN())*2-3)),"",INDEX(Array_EmissionChargeData,ROW()-2,(COLUMN())*2-3)) | C13: =IF(ISBLANK(INDEX(Array_EmissionChargeData,ROW()-2,(COLUMN())*2-3)),"",INDEX(Array_EmissionChargeData,ROW()-2,(COLUMN())*2-3)) | D13: =IF(ISBLANK(INDEX(Array_EmissionChargeData,ROW()-2,(COLUMN())*2-3)),"",INDEX(Array_EmissionChargeData,ROW()-2,(COLUMN())*2-3)) | E13: =IF(ISBLANK(INDEX(Array_EmissionChargeData,ROW()-2,(COLUMN())*2-3)),"",INDEX(Array_EmissionChargeData,ROW()-2,(COLUMN())*2-3)) | F13: =IF(ISBLANK(INDEX(Array_EmissionChargeData,ROW()-2,(COLUMN())*2-3)),"",INDEX(Array_EmissionChargeData,ROW()-2,(COLUMN())*2-3)) | K13: HFC-152
A14: =IF('Other Emission Meters'!B14="",A13,'Other Emission Meters'!B14) -> Meter Numbers | B14: =IF(ISBLANK(INDEX(Array_EmissionChargeData,ROW()-2,(COLUMN())*2-3)),"",INDEX(Array_EmissionChargeData,ROW()-2,(COLUMN())*2-3)) | C14: =IF(ISBLANK(INDEX(Array_EmissionChargeData,ROW()-2,(COLUMN())*2-3)),"",INDEX(Array_EmissionChargeData,ROW()-2,(COLUMN())*2-3)) | D14: =IF(ISBLANK(INDEX(Array_EmissionChargeData,ROW()-2,(COLUMN())*2-3)),"",INDEX(Array_EmissionChargeData,ROW()-2,(COLUMN())*2-3)) | E14: =IF(ISBLANK(INDEX(Array_EmissionChargeData,ROW()-2,(COLUMN())*2-3)),"",INDEX(Array_EmissionChargeData,ROW()-2,(COLUMN())*2-3)) | F14: =IF(ISBLANK(INDEX(Array_EmissionChargeData,ROW()-2,(COLUMN())*2-3)),"",INDEX(Array_EmissionChargeData,ROW()-2,(COLUMN())*2-3)) | K14: HFC-152a
A15: =IF('Other Emission Meters'!B15="",A14,'Other Emission Meters'!B15) -> Meter Numbers | B15: =IF(ISBLANK(INDEX(Array_EmissionChargeData,ROW()-2,(COLUMN())*2-3)),"",INDEX(Array_EmissionChargeData,ROW()-2,(COLUMN())*2-3)) | C15: =IF(ISBLANK(INDEX(Array_EmissionChargeData,ROW()-2,(COLUMN())*2-3)),"",INDEX(Array_EmissionChargeData,ROW()-2,(COLUMN())*2-3)) | D15: =IF(ISBLANK(INDEX(Array_EmissionChargeData,ROW()-2,(COLUMN())*2-3)),"",INDEX(Array_EmissionChargeData,ROW()-2,(COLUMN())*2-3)) | E15: =IF(ISBLANK(INDEX(Array_EmissionChargeData,ROW()-2,(COLUMN())*2-3)),"",INDEX(Array_EmissionChargeData,ROW()-2,(COLUMN())*2-3)) | F15: =IF(ISBLANK(INDEX(Array_EmissionChargeData,ROW()-2,(COLUMN())*2-3)),"",INDEX(Array_EmissionChargeData,ROW()-2,(COLUMN())*2-3)) | K15: HFC-161
A16: =IF('Other Emission Meters'!B16="",A15,'Other Emission Meters'!B16) -> Meter Numbers | B16: =IF(ISBLANK(INDEX(Array_EmissionChargeData,ROW()-2,(COLUMN())*2-3)),"",INDEX(Array_EmissionChargeData,ROW()-2,(COLUMN())*2-3)) | C16: =IF(ISBLANK(INDEX(Array_EmissionChargeData,ROW()-2,(COLUMN())*2-3)),"",INDEX(Array_EmissionChargeData,ROW()-2,(COLUMN())*2-3)) | D16: =IF(ISBLANK(INDEX(Array_EmissionChargeData,ROW()-2,(COLUMN())*2-3)),"",INDEX(Array_EmissionChargeData,ROW()-2,(COLUMN())*2-3)) | E16: =IF(ISBLANK(INDEX(Array_EmissionChargeData,ROW()-2,(COLUMN())*2-3)),"",INDEX(Array_EmissionChargeData,ROW()-2,(COLUMN())*2-3)) | F16: =IF(ISBLANK(INDEX(Array_EmissionChargeData,ROW()-2,(COLUMN())*2-3)),"",INDEX(Array_EmissionChargeData,ROW()-2,(COLUMN())*2-3)) | K16: HFC-227ea
A17: =IF('Other Emission Meters'!B17="",A16,'Other Emission Meters'!B17) -> Meter Numbers | B17: =IF(ISBLANK(INDEX(Array_EmissionChargeData,ROW()-2,(COLUMN())*2-3)),"",INDEX(Array_EmissionChargeData,ROW()-2,(COLUMN())*2-3)) | C17: =IF(ISBLANK(INDEX(Array_EmissionChargeData,ROW()-2,(COLUMN())*2-3)),"",INDEX(Array_EmissionChargeData,ROW()-2,(COLUMN())*2-3)) | D17: =IF(ISBLANK(INDEX(Array_EmissionChargeData,ROW()-2,(COLUMN())*2-3)),"",INDEX(Array_EmissionChargeData,ROW()-2,(COLUMN())*2-3)) | E17: =IF(ISBLANK(INDEX(Array_EmissionChargeData,ROW()-2,(COLUMN())*2-3)),"",INDEX(Array_EmissionChargeData,ROW()-2,(COLUMN())*2-3)) | F17: =IF(ISBLANK(INDEX(Array_EmissionChargeData,ROW()-2,(COLUMN())*2-3)),"",INDEX(Array_EmissionChargeData,ROW()-2,(COLUMN())*2-3)) | K17: HFC-236cb
A18: =IF('Other Emission Meters'!B18="",A17,'Other Emission Meters'!B18) -> Meter Numbers | B18: =IF(ISBLANK(INDEX(Array_EmissionChargeData,ROW()-2,(COLUMN())*2-3)),"",INDEX(Array_EmissionChargeData,ROW()-2,(COLUMN())*2-3)) | C18: =IF(ISBLANK(INDEX(Array_EmissionChargeData,ROW()-2,(COLUMN())*2-3)),"",INDEX(Array_EmissionChargeData,ROW()-2,(COLUMN())*2-3)) | D18: =IF(ISBLANK(INDEX(Array_EmissionChargeData,ROW()-2,(COLUMN())*2-3)),"",INDEX(Array_EmissionChargeData,ROW()-2,(COLUMN())*2-3)) | E18: =IF(ISBLANK(INDEX(Array_EmissionChargeData,ROW()-2,(COLUMN())*2-3)),"",INDEX(Array_EmissionChargeData,ROW()-2,(COLUMN())*2-3)) | F18: =IF(ISBLANK(INDEX(Array_EmissionChargeData,ROW()-2,(COLUMN())*2-3)),"",INDEX(Array_EmissionChargeData,ROW()-2,(COLUMN())*2-3)) | K18: HFC-236ea
A19: =IF('Other Emission Meters'!B19="",A18,'Other Emission Meters'!B19) -> Meter Numbers | B19: =IF(ISBLANK(INDEX(Array_EmissionChargeData,ROW()-2,(COLUMN())*2-3)),"",INDEX(Array_EmissionChargeData,ROW()-2,(COLUMN())*2-3)) | C19: =IF(ISBLANK(INDEX(Array_EmissionChargeData,ROW()-2,(COLUMN())*2-3)),"",INDEX(Array_EmissionChargeData,ROW()-2,(COLUMN())*2-3)) | D19: =IF(ISBLANK(INDEX(Array_EmissionChargeData,ROW()-2,(COLUMN())*2-3)),"",INDEX(Array_EmissionChargeData,ROW()-2,(COLUMN())*2-3)) | E19: =IF(ISBLANK(INDEX(Array_EmissionChargeData,ROW()-2,(COLUMN())*2-3)),"",INDEX(Array_EmissionChargeData,ROW()-2,(COLUMN())*2-3)) | F19: =IF(ISBLANK(INDEX(Array_EmissionChargeData,ROW()-2,(COLUMN())*2-3)),"",INDEX(Array_EmissionChargeData,ROW()-2,(COLUMN())*2-3)) | K19: HFC-236fa
... A69: =IF('Other Emission Meters'!B69="",A68,'Other Emission Meters'!B69) -> Meter Numbers | B69: =IF(ISBLANK(INDEX(Array_EmissionChargeData,ROW()-2,(COLUMN())*2-3)),"",INDEX(Array_EmissionChargeData,ROW()-2,(COLUMN())*2-3)) | C69: =IF(ISBLANK(INDEX(Array_EmissionChargeData,ROW()-2,(COLUMN())*2-3)),"",INDEX(Array_EmissionChargeData,ROW()-2,(COLUMN())*2-3)) | D69: =IF(ISBLANK(INDEX(Array_EmissionChargeData,ROW()-2,(COLUMN())*2-3)),"",INDEX(Array_EmissionChargeData,ROW()-2,(COLUMN())*2-3)) | E69: =IF(ISBLANK(INDEX(Array_EmissionChargeData,ROW()-2,(COLUMN())*2-3)),"",INDEX(Array_EmissionChargeData,ROW()-2,(COLUMN())*2-3)) | F69: =IF(ISBLANK(INDEX(Array_EmissionChargeData,ROW()-2,(COLUMN())*2-3)),"",INDEX(Array_EmissionChargeData,ROW()-2,(COLUMN())*2-3)) | K69: R-508B
A70: =IF('Other Emission Meters'!B70="",A69,'Other Emission Meters'!B70) -> Meter Numbers | B70: =IF(ISBLANK(INDEX(Array_EmissionChargeData,ROW()-2,(COLUMN())*2-3)),"",INDEX(Array_EmissionChargeData,ROW()-2,(COLUMN())*2-3)) | C70: =IF(ISBLANK(INDEX(Array_EmissionChargeData,ROW()-2,(COLUMN())*2-3)),"",INDEX(Array_EmissionChargeData,ROW()-2,(COLUMN())*2-3)) | D70: =IF(ISBLANK(INDEX(Array_EmissionChargeData,ROW()-2,(COLUMN())*2-3)),"",INDEX(Array_EmissionChargeData,ROW()-2,(COLUMN())*2-3)) | E70: =IF(ISBLANK(INDEX(Array_EmissionChargeData,ROW()-2,(COLUMN())*2-3)),"",INDEX(Array_EmissionChargeData,ROW()-2,(COLUMN())*2-3)) | F70: =IF(ISBLANK(INDEX(Array_EmissionChargeData,ROW()-2,(COLUMN())*2-3)),"",INDEX(Array_EmissionChargeData,ROW()-2,(COLUMN())*2-3))
A71: =IF('Other Emission Meters'!B71="",A70,'Other Emission Meters'!B71) -> Meter Numbers | B71: =IF(ISBLANK(INDEX(Array_EmissionChargeData,ROW()-2,(COLUMN())*2-3)),"",INDEX(Array_EmissionChargeData,ROW()-2,(COLUMN())*2-3)) | C71: =IF(ISBLANK(INDEX(Array_EmissionChargeData,ROW()-2,(COLUMN())*2-3)),"",INDEX(Array_EmissionChargeData,ROW()-2,(COLUMN())*2-3)) | D71: =IF(ISBLANK(INDEX(Array_EmissionChargeData,ROW()-2,(COLUMN())*2-3)),"",INDEX(Array_EmissionChargeData,ROW()-2,(COLUMN())*2-3)) | E71: =IF(ISBLANK(INDEX(Array_EmissionChargeData,ROW()-2,(COLUMN())*2-3)),"",INDEX(Array_EmissionChargeData,ROW()-2,(COLUMN())*2-3)) | F71: =IF(ISBLANK(INDEX(Array_EmissionChargeData,ROW()-2,(COLUMN())*2-3)),"",INDEX(Array_EmissionChargeData,ROW()-2,(COLUMN())*2-3))
A72: =IF('Other Emission Meters'!B72="",A71,'Other Emission Meters'!B72) -> Meter Numbers | B72: =IF(ISBLANK(INDEX(Array_EmissionChargeData,ROW()-2,(COLUMN())*2-3)),"",INDEX(Array_EmissionChargeData,ROW()-2,(COLUMN())*2-3)) | C72: =IF(ISBLANK(INDEX(Array_EmissionChargeData,ROW()-2,(COLUMN())*2-3)),"",INDEX(Array_EmissionChargeData,ROW()-2,(COLUMN())*2-3)) | D72: =IF(ISBLANK(INDEX(Array_EmissionChargeData,ROW()-2,(COLUMN())*2-3)),"",INDEX(Array_EmissionChargeData,ROW()-2,(COLUMN())*2-3)) | E72: =IF(ISBLANK(INDEX(Array_EmissionChargeData,ROW()-2,(COLUMN())*2-3)),"",INDEX(Array_EmissionChargeData,ROW()-2,(COLUMN())*2-3)) | F72: =IF(ISBLANK(INDEX(Array_EmissionChargeData,ROW()-2,(COLUMN())*2-3)),"",INDEX(Array_EmissionChargeData,ROW()-2,(COLUMN())*2-3))
A73: =IF('Other Emission Meters'!B73="",A72,'Other Emission Meters'!B73) -> Meter Numbers | B73: =IF(ISBLANK(INDEX(Array_EmissionChargeData,ROW()-2,(COLUMN())*2-3)),"",INDEX(Array_EmissionChargeData,ROW()-2,(COLUMN())*2-3)) | C73: =IF(ISBLANK(INDEX(Array_EmissionChargeData,ROW()-2,(COLUMN())*2-3)),"",INDEX(Array_EmissionChargeData,ROW()-2,(COLUMN())*2-3)) | D73: =IF(ISBLANK(INDEX(Array_EmissionChargeData,ROW()-2,(COLUMN())*2-3)),"",INDEX(Array_EmissionChargeData,ROW()-2,(COLUMN())*2-3)) | E73: =IF(ISBLANK(INDEX(Array_EmissionChargeData,ROW()-2,(COLUMN())*2-3)),"",INDEX(Array_EmissionChargeData,ROW()-2,(COLUMN())*2-3)) | F73: =IF(ISBLANK(INDEX(Array_EmissionChargeData,ROW()-2,(COLUMN())*2-3)),"",INDEX(Array_EmissionChargeData,ROW()-2,(COLUMN())*2-3))
A74: =IF('Other Emission Meters'!B74="",A73,'Other Emission Meters'!B74) -> Meter Numbers | B74: =IF(ISBLANK(INDEX(Array_EmissionChargeData,ROW()-2,(COLUMN())*2-3)),"",INDEX(Array_EmissionChargeData,ROW()-2,(COLUMN())*2-3)) | C74: =IF(ISBLANK(INDEX(Array_EmissionChargeData,ROW()-2,(COLUMN())*2-3)),"",INDEX(Array_EmissionChargeData,ROW()-2,(COLUMN())*2-3)) | D74: =IF(ISBLANK(INDEX(Array_EmissionChargeData,ROW()-2,(COLUMN())*2-3)),"",INDEX(Array_EmissionChargeData,ROW()-2,(COLUMN())*2-3)) | E74: =IF(ISBLANK(INDEX(Array_EmissionChargeData,ROW()-2,(COLUMN())*2-3)),"",INDEX(Array_EmissionChargeData,ROW()-2,(COLUMN())*2-3)) | F74: =IF(ISBLANK(INDEX(Array_EmissionChargeData,ROW()-2,(COLUMN())*2-3)),"",INDEX(Array_EmissionChargeData,ROW()-2,(COLUMN())*2-3))
A75: =IF('Other Emission Meters'!B75="",A74,'Other Emission Meters'!B75) -> Meter Numbers | B75: =IF(ISBLANK(INDEX(Array_EmissionChargeData,ROW()-2,(COLUMN())*2-3)),"",INDEX(Array_EmissionChargeData,ROW()-2,(COLUMN())*2-3)) | C75: =IF(ISBLANK(INDEX(Array_EmissionChargeData,ROW()-2,(COLUMN())*2-3)),"",INDEX(Array_EmissionChargeData,ROW()-2,(COLUMN())*2-3)) | D75: =IF(ISBLANK(INDEX(Array_EmissionChargeData,ROW()-2,(COLUMN())*2-3)),"",INDEX(Array_EmissionChargeData,ROW()-2,(COLUMN())*2-3)) | E75: =IF(ISBLANK(INDEX(Array_EmissionChargeData,ROW()-2,(COLUMN())*2-3)),"",INDEX(Array_EmissionChargeData,ROW()-2,(COLUMN())*2-3)) | F75: =IF(ISBLANK(INDEX(Array_EmissionChargeData,ROW()-2,(COLUMN())*2-3)),"",INDEX(Array_EmissionChargeData,ROW()-2,(COLUMN())*2-3))
A76: =IF('Other Emission Meters'!B76="",A75,'Other Emission Meters'!B76) -> Meter Numbers | B76: =IF(ISBLANK(INDEX(Array_EmissionChargeData,ROW()-2,(COLUMN())*2-3)),"",INDEX(Array_EmissionChargeData,ROW()-2,(COLUMN())*2-3)) | C76: =IF(ISBLANK(INDEX(Array_EmissionChargeData,ROW()-2,(COLUMN())*2-3)),"",INDEX(Array_EmissionChargeData,ROW()-2,(COLUMN())*2-3)) | D76: =IF(ISBLANK(INDEX(Array_EmissionChargeData,ROW()-2,(COLUMN())*2-3)),"",INDEX(Array_EmissionChargeData,ROW()-2,(COLUMN())*2-3)) | E76: =IF(ISBLANK(INDEX(Array_EmissionChargeData,ROW()-2,(COLUMN())*2-3)),"",INDEX(Array_EmissionChargeData,ROW()-2,(COLUMN())*2-3)) | F76: =IF(ISBLANK(INDEX(Array_EmissionChargeData,ROW()-2,(COLUMN())*2-3)),"",INDEX(Array_EmissionChargeData,ROW()-2,(COLUMN())*2-3))
A77: =IF('Other Emission Meters'!B77="",A76,'Other Emission Meters'!B77) -> Meter Numbers | B77: =IF(ISBLANK(INDEX(Array_EmissionChargeData,ROW()-2,(COLUMN())*2-3)),"",INDEX(Array_EmissionChargeData,ROW()-2,(COLUMN())*2-3)) | C77: =IF(ISBLANK(INDEX(Array_EmissionChargeData,ROW()-2,(COLUMN())*2-3)),"",INDEX(Array_EmissionChargeData,ROW()-2,(COLUMN())*2-3)) | D77: =IF(ISBLANK(INDEX(Array_EmissionChargeData,ROW()-2,(COLUMN())*2-3)),"",INDEX(Array_EmissionChargeData,ROW()-2,(COLUMN())*2-3)) | E77: =IF(ISBLANK(INDEX(Array_EmissionChargeData,ROW()-2,(COLUMN())*2-3)),"",INDEX(Array_EmissionChargeData,ROW()-2,(COLUMN())*2-3)) | F77: =IF(ISBLANK(INDEX(Array_EmissionChargeData,ROW()-2,(COLUMN())*2-3)),"",INDEX(Array_EmissionChargeData,ROW()-2,(COLUMN())*2-3))
A78: =IF('Other Emission Meters'!B78="",A77,'Other Emission Meters'!B78) -> Meter Numbers | B78: =IF(ISBLANK(INDEX(Array_EmissionChargeData,ROW()-2,(COLUMN())*2-3)),"",INDEX(Array_EmissionChargeData,ROW()-2,(COLUMN())*2-3)) | C78: =IF(ISBLANK(INDEX(Array_EmissionChargeData,ROW()-2,(COLUMN())*2-3)),"",INDEX(Array_EmissionChargeData,ROW()-2,(COLUMN())*2-3)) | D78: =IF(ISBLANK(INDEX(Array_EmissionChargeData,ROW()-2,(COLUMN())*2-3)),"",INDEX(Array_EmissionChargeData,ROW()-2,(COLUMN())*2-3)) | E78: =IF(ISBLANK(INDEX(Array_EmissionChargeData,ROW()-2,(COLUMN())*2-3)),"",INDEX(Array_EmissionChargeData,ROW()-2,(COLUMN())*2-3)) | F78: =IF(ISBLANK(INDEX(Array_EmissionChargeData,ROW()-2,(COLUMN())*2-3)),"",INDEX(Array_EmissionChargeData,ROW()-2,(COLUMN())*2-3))
A79: =IF('Other Emission Meters'!B79="",A78,'Other Emission Meters'!B79) -> Meter Numbers | B79: =IF(ISBLANK(INDEX(Array_EmissionChargeData,ROW()-2,(COLUMN())*2-3)),"",INDEX(Array_EmissionChargeData,ROW()-2,(COLUMN())*2-3)) | C79: =IF(ISBLANK(INDEX(Array_EmissionChargeData,ROW()-2,(COLUMN())*2-3)),"",INDEX(Array_EmissionChargeData,ROW()-2,(COLUMN())*2-3)) | D79: =IF(ISBLANK(INDEX(Array_EmissionChargeData,ROW()-2,(COLUMN())*2-3)),"",INDEX(Array_EmissionChargeData,ROW()-2,(COLUMN())*2-3)) | E79: =IF(ISBLANK(INDEX(Array_EmissionChargeData,ROW()-2,(COLUMN())*2-3)),"",INDEX(Array_EmissionChargeData,ROW()-2,(COLUMN())*2-3)) | F79: =IF(ISBLANK(INDEX(Array_EmissionChargeData,ROW()-2,(COLUMN())*2-3)),"",INDEX(Array_EmissionChargeData,ROW()-2,(COLUMN())*2-3))
A80: =IF('Other Emission Meters'!B80="",A79,'Other Emission Meters'!B80) -> Meter Numbers | B80: =IF(ISBLANK(INDEX(Array_EmissionChargeData,ROW()-2,(COLUMN())*2-3)),"",INDEX(Array_EmissionChargeData,ROW()-2,(COLUMN())*2-3)) | C80: =IF(ISBLANK(INDEX(Array_EmissionChargeData,ROW()-2,(COLUMN())*2-3)),"",INDEX(Array_EmissionChargeData,ROW()-2,(COLUMN())*2-3)) | D80: =IF(ISBLANK(INDEX(Array_EmissionChargeData,ROW()-2,(COLUMN())*2-3)),"",INDEX(Array_EmissionChargeData,ROW()-2,(COLUMN())*2-3)) | E80: =IF(ISBLANK(INDEX(Array_EmissionChargeData,ROW()-2,(COLUMN())*2-3)),"",INDEX(Array_EmissionChargeData,ROW()-2,(COLUMN())*2-3)) | F80: =IF(ISBLANK(INDEX(Array_EmissionChargeData,ROW()-2,(COLUMN())*2-3)),"",INDEX(Array_EmissionChargeData,ROW()-2,(COLUMN())*2-3))
A81: =IF('Other Emission Meters'!B81="",A80,'Other Emission Meters'!B81) -> Meter Numbers | B81: =IF(ISBLANK(INDEX(Array_EmissionChargeData,ROW()-2,(COLUMN())*2-3)),"",INDEX(Array_EmissionChargeData,ROW()-2,(COLUMN())*2-3)) | C81: =IF(ISBLANK(INDEX(Array_EmissionChargeData,ROW()-2,(COLUMN())*2-3)),"",INDEX(Array_EmissionChargeData,ROW()-2,(COLUMN())*2-3)) | D81: =IF(ISBLANK(INDEX(Array_EmissionChargeData,ROW()-2,(COLUMN())*2-3)),"",INDEX(Array_EmissionChargeData,ROW()-2,(COLUMN())*2-3)) | E81: =IF(ISBLANK(INDEX(Array_EmissionChargeData,ROW()-2,(COLUMN())*2-3)),"",INDEX(Array_EmissionChargeData,ROW()-2,(COLUMN())*2-3)) | F81: =IF(ISBLANK(INDEX(Array_EmissionChargeData,ROW()-2,(COLUMN())*2-3)),"",INDEX(Array_EmissionChargeData,ROW()-2,(COLUMN())*2-3))
... A201: =IF('Other Emission Meters'!B201="",A200,'Other Emission Meters'!B201) -> Meter Numbers | B201: =IF(ISBLANK(INDEX(Array_EmissionChargeData,ROW()-2,(COLUMN())*2-3)),"",INDEX(Array_EmissionChargeData,ROW()-2,(COLUMN())*2-3)) | C201: =IF(ISBLANK(INDEX(Array_EmissionChargeData,ROW()-2,(COLUMN())*2-3)),"",INDEX(Array_EmissionChargeData,ROW()-2,(COLUMN())*2-3)) | D201: =IF(ISBLANK(INDEX(Array_EmissionChargeData,ROW()-2,(COLUMN())*2-3)),"",INDEX(Array_EmissionChargeData,ROW()-2,(COLUMN())*2-3)) | E201: =IF(ISBLANK(INDEX(Array_EmissionChargeData,ROW()-2,(COLUMN())*2-3)),"",INDEX(Array_EmissionChargeData,ROW()-2,(COLUMN())*2-3)) | F201: =IF(ISBLANK(INDEX(Array_EmissionChargeData,ROW()-2,(COLUMN())*2-3)),"",INDEX(Array_EmissionChargeData,ROW()-2,(COLUMN())*2-3))

Sheet Other Emissions
A1: √ Other Emission Readings | E1: √ Other Emission Charges (Optional)
A2: Meter Number | B2: Read Date | C2: Total Usage or Emission | D2: Total Cost ($) | E2: =IF(INDEX(List_ChargeNumbers_Emissions, 1, ROUNDUP((COLUMN()+0)/3-0,0)) = 0,"",INDEX(List_ChargeNumbers_Emissions, 2, ROUNDUP((COLUMN()+0)/3-0,0))&" Name") | F2: =IF(INDEX(List_ChargeNumbers_Emissions, 1, ROUNDUP((COLUMN()+0)/3-0,0)) = 0,"",INDEX(List_ChargeNumbers_Emissions, 2, ROUNDUP((COLUMN()+0)/3-0,0))&" Reading") | G2: =IF(INDEX(List_ChargeNumbers_Emissions, 1, ROUNDUP((COLUMN()-1)/3-0,0)) = 0,"",INDEX(List_ChargeNumbers_Emissions, 2, ROUNDUP((COLUMN()-1)/3-0,0))&" Cost") | H2: =IF(INDEX(List_ChargeNumbers_Emissions, 1, ROUNDUP((COLUMN()+0)/3-0,0)) = 0,"",INDEX(List_ChargeNumbers_Emissions, 2, ROUNDUP((COLUMN()+0)/3-0,0))&" Name") | I2: =IF(INDEX(List_ChargeNumbers_Emissions, 1, ROUNDUP((COLUMN()+0)/3-0,0)) = 0,"",INDEX(List_ChargeNumbers_Emissions, 2, ROUNDUP((COLUMN()+0)/3-0,0))&" Reading") | J2: =IF(INDEX(List_ChargeNumbers_Emissions, 1, ROUNDUP((COLUMN()-1)/3-0,0)) = 0,"",INDEX(List_ChargeNumbers_Emissions, 2, ROUNDUP((COLUMN()-1)/3-0,0))&" Cost") | K2: =IF(INDEX(List_ChargeNumbers_Emissions, 1, ROUNDUP((COLUMN()+0)/3-0,0)) = 0,"",INDEX(List_ChargeNumbers_Emissions, 2, ROUNDUP((COLUMN()+0)/3-0,0))&" Name") | L2: =IF(INDEX(List_ChargeNumbers_Emissions, 1, ROUNDUP((COLUMN()+0)/3-0,0)) = 0,"",INDEX(List_ChargeNumbers_Emissions, 2, ROUNDUP((COLUMN()+0)/3-0,0))&" Reading") | M2: =IF(INDEX(List_ChargeNumbers_Emissions, 1, ROUNDUP((COLUMN()-1)/3-0,0)) = 0,"",INDEX(List_ChargeNumbers_Emissions, 2, ROUNDUP((COLUMN()-1)/3-0,0))&" Cost") | N2: =IF(INDEX(List_ChargeNumbers_Emissions, 1, ROUNDUP((COLUMN()+0)/3-0,0)) = 0,"",INDEX(List_ChargeNumbers_Emissions, 2, ROUNDUP((COLUMN()+0)/3-0,0))&" Name") | O2: =IF(INDEX(List_ChargeNumbers_Emissions, 1, ROUNDUP((COLUMN()+0)/3-0,0)) = 0,"",INDEX(List_ChargeNumbers_Emissions, 2, ROUNDUP((COLUMN()+0)/3-0,0))&" Reading") | P2: =IF(INDEX(List_ChargeNumbers_Emissions, 1, ROUNDUP((COLUMN()-1)/3-0,0)) = 0,"",INDEX(List_ChargeNumbers_Emissions, 2, ROUNDUP((COLUMN()-1)/3-0,0))&" Cost") | Q2: =IF(INDEX(List_ChargeNumbers_Emissions, 1, ROUNDUP((COLUMN()+0)/3-0,0)) = 0,"",INDEX(List_ChargeNumbers_Emissions, 2, ROUNDUP((COLUMN()+0)/3-0,0))&" Name") | R2: =IF(INDEX(List_ChargeNumbers_Emissions, 1, ROUNDUP((COLUMN()+0)/3-0,0)) = 0,"",INDEX(List_ChargeNumbers_Emissions, 2, ROUNDUP((COLUMN()+0)/3-0,0))&" Reading") | S2: =IF(INDEX(List_ChargeNumbers_Emissions, 1, ROUNDUP((COLUMN()-1)/3-0,0)) = 0,"",INDEX(List_ChargeNumbers_Emissions, 2, ROUNDUP((COLUMN()-1)/3-0,0))&" Cost")
E3: =IF(ISBLANK($A3),"",INDEX(Array_EmissionCharges,MATCH($A3,List_EmissionMeters,0),ROUNDUP((COLUMN()+0)/3-1,0))) | H3: =IF(ISBLANK($A3),"",INDEX(Array_EmissionCharges,MATCH($A3,List_EmissionMeters,0),ROUNDUP((COLUMN()+0)/3-1,0))) | K3: =IF(ISBLANK($A3),"",INDEX(Array_EmissionCharges,MATCH($A3,List_EmissionMeters,0),ROUNDUP((COLUMN()+0)/3-1,0))) | N3: =IF(ISBLANK($A3),"",INDEX(Array_EmissionCharges,MATCH($A3,List_EmissionMeters,0),ROUNDUP((COLUMN()+0)/3-1,0))) | Q3: =IF(ISBLANK($A3),"",INDEX(Array_EmissionCharges,MATCH($A3,List_EmissionMeters,0),ROUNDUP((COLUMN()+0)/3-1,0)))
E4: =IF(ISBLANK($A4),"",INDEX(Array_EmissionCharges,MATCH($A4,List_EmissionMeters,0),ROUNDUP((COLUMN()+0)/3-1,0))) | H4: =IF(ISBLANK($A4),"",INDEX(Array_EmissionCharges,MATCH($A4,List_EmissionMeters,0),ROUNDUP((COLUMN()+0)/3-1,0))) | K4: =IF(ISBLANK($A4),"",INDEX(Array_EmissionCharges,MATCH($A4,List_EmissionMeters,0),ROUNDUP((COLUMN()+0)/3-1,0))) | N4: =IF(ISBLANK($A4),"",INDEX(Array_EmissionCharges,MATCH($A4,List_EmissionMeters,0),ROUNDUP((COLUMN()+0)/3-1,0))) | Q4: =IF(ISBLANK($A4),"",INDEX(Array_EmissionCharges,MATCH($A4,List_EmissionMeters,0),ROUNDUP((COLUMN()+0)/3-1,0)))
E5: =IF(ISBLANK($A5),"",INDEX(Array_EmissionCharges,MATCH($A5,List_EmissionMeters,0),ROUNDUP((COLUMN()+0)/3-1,0))) | H5: =IF(ISBLANK($A5),"",INDEX(Array_EmissionCharges,MATCH($A5,List_EmissionMeters,0),ROUNDUP((COLUMN()+0)/3-1,0))) | K5: =IF(ISBLANK($A5),"",INDEX(Array_EmissionCharges,MATCH($A5,List_EmissionMeters,0),ROUNDUP((COLUMN()+0)/3-1,0))) | N5: =IF(ISBLANK($A5),"",INDEX(Array_EmissionCharges,MATCH($A5,List_EmissionMeters,0),ROUNDUP((COLUMN()+0)/3-1,0))) | Q5: =IF(ISBLANK($A5),"",INDEX(Array_EmissionCharges,MATCH($A5,List_EmissionMeters,0),ROUNDUP((COLUMN()+0)/3-1,0)))
E6: =IF(ISBLANK($A6),"",INDEX(Array_EmissionCharges,MATCH($A6,List_EmissionMeters,0),ROUNDUP((COLUMN()+0)/3-1,0))) | H6: =IF(ISBLANK($A6),"",INDEX(Array_EmissionCharges,MATCH($A6,List_EmissionMeters,0),ROUNDUP((COLUMN()+0)/3-1,0))) | K6: =IF(ISBLANK($A6),"",INDEX(Array_EmissionCharges,MATCH($A6,List_EmissionMeters,0),ROUNDUP((COLUMN()+0)/3-1,0))) | N6: =IF(ISBLANK($A6),"",INDEX(Array_EmissionCharges,MATCH($A6,List_EmissionMeters,0),ROUNDUP((COLUMN()+0)/3-1,0))) | Q6: =IF(ISBLANK($A6),"",INDEX(Array_EmissionCharges,MATCH($A6,List_EmissionMeters,0),ROUNDUP((COLUMN()+0)/3-1,0)))
E7: =IF(ISBLANK($A7),"",INDEX(Array_EmissionCharges,MATCH($A7,List_EmissionMeters,0),ROUNDUP((COLUMN()+0)/3-1,0))) | H7: =IF(ISBLANK($A7),"",INDEX(Array_EmissionCharges,MATCH($A7,List_EmissionMeters,0),ROUNDUP((COLUMN()+0)/3-1,0))) | K7: =IF(ISBLANK($A7),"",INDEX(Array_EmissionCharges,MATCH($A7,List_EmissionMeters,0),ROUNDUP((COLUMN()+0)/3-1,0))) | N7: =IF(ISBLANK($A7),"",INDEX(Array_EmissionCharges,MATCH($A7,List_EmissionMeters,0),ROUNDUP((COLUMN()+0)/3-1,0))) | Q7: =IF(ISBLANK($A7),"",INDEX(Array_EmissionCharges,MATCH($A7,List_EmissionMeters,0),ROUNDUP((COLUMN()+0)/3-1,0)))
E8: =IF(ISBLANK($A8),"",INDEX(Array_EmissionCharges,MATCH($A8,List_EmissionMeters,0),ROUNDUP((COLUMN()+0)/3-1,0))) | H8: =IF(ISBLANK($A8),"",INDEX(Array_EmissionCharges,MATCH($A8,List_EmissionMeters,0),ROUNDUP((COLUMN()+0)/3-1,0))) | K8: =IF(ISBLANK($A8),"",INDEX(Array_EmissionCharges,MATCH($A8,List_EmissionMeters,0),ROUNDUP((COLUMN()+0)/3-1,0))) | N8: =IF(ISBLANK($A8),"",INDEX(Array_EmissionCharges,MATCH($A8,List_EmissionMeters,0),ROUNDUP((COLUMN()+0)/3-1,0))) | Q8: =IF(ISBLANK($A8),"",INDEX(Array_EmissionCharges,MATCH($A8,List_EmissionMeters,0),ROUNDUP((COLUMN()+0)/3-1,0)))
E9: =IF(ISBLANK($A9),"",INDEX(Array_EmissionCharges,MATCH($A9,List_EmissionMeters,0),ROUNDUP((COLUMN()+0)/3-1,0))) | H9: =IF(ISBLANK($A9),"",INDEX(Array_EmissionCharges,MATCH($A9,List_EmissionMeters,0),ROUNDUP((COLUMN()+0)/3-1,0))) | K9: =IF(ISBLANK($A9),"",INDEX(Array_EmissionCharges,MATCH($A9,List_EmissionMeters,0),ROUNDUP((COLUMN()+0)/3-1,0))) | N9: =IF(ISBLANK($A9),"",INDEX(Array_EmissionCharges,MATCH($A9,List_EmissionMeters,0),ROUNDUP((COLUMN()+0)/3-1,0))) | Q9: =IF(ISBLANK($A9),"",INDEX(Array_EmissionCharges,MATCH($A9,List_EmissionMeters,0),ROUNDUP((COLUMN()+0)/3-1,0)))
E10: =IF(ISBLANK($A10),"",INDEX(Array_EmissionCharges,MATCH($A10,List_EmissionMeters,0),ROUNDUP((COLUMN()+0)/3-1,0))) | H10: =IF(ISBLANK($A10),"",INDEX(Array_EmissionCharges,MATCH($A10,List_EmissionMeters,0),ROUNDUP((COLUMN()+0)/3-1,0))) | K10: =IF(ISBLANK($A10),"",INDEX(Array_EmissionCharges,MATCH($A10,List_EmissionMeters,0),ROUNDUP((COLUMN()+0)/3-1,0))) | N10: =IF(ISBLANK($A10),"",INDEX(Array_EmissionCharges,MATCH($A10,List_EmissionMeters,0),ROUNDUP((COLUMN()+0)/3-1,0))) | Q10: =IF(ISBLANK($A10),"",INDEX(Array_EmissionCharges,MATCH($A10,List_EmissionMeters,0),ROUNDUP((COLUMN()+0)/3-1,0)))
